Workbook
Name Ceph_10K_Skylake: '[1]Storage-Compute'!$C$9:$C$11
Name Ceph_Broadwell: '[1]Storage-Compute'!$C$9:$C$11
Name Ceph_Skylake: '[1]Storage-Compute'!$C$9:$C$11
Name Ceph_Skylake_IBRS: '[1]Storage-Compute'!$C$45:$C$46
Name Ceph_Skylake_IBRS_VTM: '[1]Storage-Compute'!$C$47:$C$48
Name Ceph_VTM: '[1]Storage-Compute'!$C$12:$C$13
Name Cisco_2020_HLC: '[1]Storage-Compute'!$B$45:$B$65
Name Cisco_2020_HLC_image: '[1]Image-Cloud '!$B$20:$B$29
Name Cloud_HHT: '[1]Storage-Compute'!$B$70:$B$74
Name Cloud_HHT_image: '[1]Image-Cloud '!$B$36:$B$43
Name Cloud_VTT: '[1]Storage-Compute'!$B$82
Name Cloud_VTT_image: '[1]Image-Cloud '!$B$45:$B$50
Name Dell_Unity_186_G05: '[1]Storage-Compute'!$C$23:$C$29
Name Hitachi_135_H11: '[1]Storage-Compute'!$C$30:$C$32
Name Hitachi_G700_Skylake_IBRS: '[1]Storage-Compute'!$C$58:$C$59
Name HP_3PAR_C01_Broadwell: '[1]Storage-Compute'!$C$14:$C$16
Name HP_3PAR_C01_Skylake: '[1]Storage-Compute'!$C$14:$C$16
Name HP_3PAR_E04: '[1]Storage-Compute'!$C$17:$C$18
Name HP_3PAR_E06_VTT: '[1]Storage-Compute'!$C$19:$C$20
Name HPE_2019_HLC: '[1]Storage-Compute'!$B$9:$B$21
Name HPE_2019_HLC_image: '[1]Image-Cloud '!$B$9:$B$17
Name HPE_3PAR_T6H09_Skylake_IBRS_VTT: '[1]Storage-Compute'!$C$55:$C$56
Name IBM_V7000_03_T5: '[1]Storage-Compute'!$C$21
Name IBM_V7000_T5: '[1]Storage-Compute'!$C$22
Name IBM_V7000_VTS: '[1]Storage-Compute'!$C$29
Name KGM_HHT_Ceph_2022_Q1_01: '[1]Storage-Compute'!$C$72:$C$73
Name Tu_Muon: '[1]Storage-Compute'!$C$33
Name UNITY880_01_Skylake_IBRS: '[1]Storage-Compute'!$C$57
Name UNITY880_01_Skylake_IBRS_VTS_Private: '[1]Storage-Compute'!$C$57
Name UNITY880_01_Skylake_IBRS_VTS_Public: '[1]Storage-Compute'!$C$57
Name ViettelPay_PCI_DSS: '[1]Storage-Compute'!$B$36:$B$38
Name ViettelPay_PCI_DSS_image: '[1]Image-Cloud '!$B$32:$B$34
Name VTNet_Ceph_2021_Q2_01: '[1]Storage-Compute'!$C$49:$C$52
Name VTNet_Ceph_2021_Q2_02: '[1]Storage-Compute'!$C$49:$C$52
Name VTNet_HHT_Ceph_2021_Q3_01: '[1]Storage-Compute'!$C$70:$C$71
Name VTNet_HHT_Ceph_2022_Q1_01: '[1]Storage-Compute'!$C$70:$C$71
Name VTNet_HHT_SAN_2021_Q3_01: '[1]Storage-Compute'!$C$74
Name VTNet_HHT_SAN_2022_Q2_01: '[1]Storage-Compute'!$C$75
Name VTNet_SAN_2021_Q2_01: '[1]Storage-Compute'!$C$53:$C$54
Name VTNet_SAN_2021_Q2_02: '[1]Storage-Compute'!$C$53:$C$54
Name VTNet_SAN_2021_Q2_03: '[1]Storage-Compute'!$C$60
Name VTNet_SAN_2021_Q2_04: '[1]Storage-Compute'!$C$61
Name VTNet_SAN_2021_Q3_01: '[1]Storage-Compute'!$C$62
Name VTNet_SAN_2022_Q1_01: '[1]Storage-Compute'!$C$63
Name VTP_CDE: '[1]Storage-Compute'!$C$36:$C$37
Name VTP_NCDE: '[1]Storage-Compute'!$C$36:$C$37
Name VTP_OTH: '[1]Storage-Compute'!$C$36:$C$37
Name VTS_Ceph_2021_Q2_01: '[1]Storage-Compute'!$C$49:$C$52
Name VTS_SAN_2021_Q2_01: '[1]Storage-Compute'!$C$53:$C$54
Name VTS_SAN_2021_Q2_02: '[1]Storage-Compute'!$C$61
Name VTS_SAN_2021_Q2_03: '[1]Storage-Compute'!$C$60
Name VTT_SAN_2021_Q2_01: '[1]Storage-Compute'!$C$53:$C$54
Name VTT_SAN_2021_Q2_02: '[1]Storage-Compute'!$C$53:$C$54
Name VTT_SAN_2021_Q4_01: '[1]Storage-Compute'!$C$82:$C$85

Sheet Sizing
A1: STT | B1: Mã PYC | C1: Đơn vị | D1: Đầu mối tạo PYC | E1: Đầu mối xử lý | F1: Trạng thái | G1: Thời điểm đẩy yêu cầu | H1: Thời gian hoàn thành theo KPI | I1: Thời gian hoàn thành ký PNX và đóng y/c | J1: Chất lượng sizing (false) | K1: Số lần sizing qua mail | L1: Thời gian ký bản chốt sizing | M1: Tên dự án - Mục đích sizing | N1: Ghi chú
A2: 1 | B2: 4140334 | D2: sonht2 | E2: tannph | F2: Hoàn thành | G2: 44970 | H2: 44973 | I2: 44973 | M2: Logkpi TV360
A3: 2 | B3: 4140332 | D3: sonht2 | E3: hungnn27 | F3: Hoàn thành | G3: 44970 | H3: 44973 | I3: 44973 | M3: backend TV360
A4: 3 | B4: 4145107 | D4: anhnt576 | E4: tannph | F4: Hoàn thành | G4: 44985 | H4: 44988 | I4: 44986 | M4: CCAI API
A5: 4 | B5: 4145808 | D5: tuyenpv9 | E5: hungnn27 | F5: Hoàn thành | G5: 44987 | H5: 44992 | I5: 44991 | M5: VoiceBrandname
A6: 5 | B6: 4148244 | D6: Dungha7 | E6: ductn | F6: Hoàn thành | G6: 44998 | H6: 45001 | I6: 45001 | M6: sizing CCAI giai đoạn 2
A7: 6 | B7: 4148678 | D7: quanhh3 | E7: hieuhv13 | F7: Hoàn thành | G7: 44999 | H7: 45002 | I7: 45002 | M7: sizing hệ thống Payment 2
A8: 7 | B8: 4149626 | D8: tuyenpv9 | E8: hungd | F8: Hoàn thành | G8: 45001 | H8: 45006 | I8: 45006 | M8: Thẩm định sizing Voice Brandname (bổ sung vaspgw_cdr và vaspgw_log)
A9: 8 | B9: 4149624 | D9: tuyenpv9 | E9: hungd | F9: Hoàn thành | G9: 45001 | H9: 45006 | I9: 45006 | M9: Thẩm định sizing Voice Brandname (bổ sung vaspgw)
A10: 9 | B10: 4151337 | D10: tamdtt1 | E10: ductn | F10: Hoàn thành | G10: 45006 | H10: 45008 | I10: 45008 | M10: Thẩm Định lại Sizing Kafka (Vtracking)
A11: 10 | B11: 4153924 | D11: chinh3 | E11: ductn | F11: Hoàn thành | G11: 45016 | H11: 45020 | I11: 45020 | M11: Thẩm định tài liệu định cỡ tài nguyên Quầy dịch vụ viễn thông tự động
A12: 11 | B12: 4155624 | D12: tiendd | E12: hieuhv13 | F12: Hoàn thành | G12: 45023 | H12: 45027 | I12: 45027 | M12: Sizing hệ thống TMS VHT
A13: 12 | B13: 4156658 | D13: tamdtt1 | E13: ductn | F13: Hoàn thành | G13: 45028 | H13: 45030 | I13: 45030 | M13: Thẩm định sizing hệ thống Camera giám sát
... A27: 26 | B27: 4173640 | D27: trangtth11 | E27: vinhtq18 | F27: Hoàn thành | G27: 45089 | H27: 45091 | I27: 45092 | M27: Thẩm định sizing hệ thống vHealth
A28: 27 | B28: 4175442 | D28: dattht | E28: hoangld2 | F28: Hoàn thành | G28: 45093 | H28: 45097 | I28: 45096 | M28: Thẩm định sizing dự án vcontract nâng cấp bổ sung phương án kinh doanh mới
A29: 28 | B29: 4176326 | D29: duongvx | E29: ductn | F29: Hoàn thành | G29: 45096 | H29: 45099 | I29: 45097 | M29: Thẩm định sizing dự án hệ thống quản lý thuê bao IoT_CMP của VHT
A30: 29 | B30: 4178224 | D30: dattht | E30: vinhtq18 | F30: Hoàn thành | G30: 45098 | H30: 45100 | I30: 45099 | M30: Thẩm định sizing định cỡ trái tim cho em
A31: 30 | B31: 4179410 | D31: quanhh3 | E31: ductn | F31: Hoàn thành | G31: 45100 | H31: 45103 | I31: 45103 | M31: sizing hệ thống ussd199/pay199
A32: 31 | B32: 4180498 | D32: duongvx | E32: ductn | F32: Hoàn thành | G32: 45105 | H32: 45108 | I32: 45112 | M32: Thẩm định sizing dự án hệ thống quản lý thuê bao IoT_CMP của VHT | N32: Trao đổi qua điện thoại
A33: 32 | B33: 4182686 | D33: hainv71 | E33: hieuhv13 | F33: Trao đôi trực tiếp | G33: 45114 | H33: 45118 | I33: 45121 | M33: Sizing log, backup DB HDDT
A34: 33 | B34: 4183198 | D34: thund1 | E34: ductn | F34: Hoàn thành | G34: 45117 | H34: 45119 | I34: 45118 | M34: PYC Sizing của vTracking 2.0
A35: 34 | B35: 4183199 | D35: anhnt576 | E35: vinhtq18 | F35: Hoàn thành | G35: 45117 | H35: 45119 | I35: 45125 | M35: Thẩm định sizing phân hệ Dagoras ARPU
A36: 35 | B36: 4183212 | D36: dattht | E36: hoangld2 | F36: Hoàn thành | G36: 45117 | H36: 45119 | I36: 45135 | M36: Thẩm định sizing dự án vcontract phương án kinh doanh nội bộ
A37: 36 | B37: 4187821 | D37: hienlt15 | E37: hieuhv13 | F37: Hoàn thành | G37: 45127 | H37: 45130 | I37: 45131 | M37: Thẩm định sizing hệ thống hóa đơn điện tử : database truyền nhận lần 4
A38: 37 | B38: 4188679 | D38: ngoctv1 | E38: vinhtq18 | F38: Hoàn thành | G38: 45131 | H38: 45133 | I38: 45135 | M38: Sizing Bổ sung phần lưu trữ backup và cụm XDR cho db Aerospike của myviettel
A39: 38 | B39: 4189869 | D39: hieund28 | E39: hoangld2 | F39: Hoàn thành | G39: 45135 | H39: 45139 | I39: 45138 | M39: Thẩm định Sizing hệ thống RATING
A40: 39 | B40: 4198143 | D40: soncn2 | E40: ductn | F40: Hoàn thành | G40: 45163 | H40: 45167 | I40: 45166 | M40: Hỗ trợ thẩm định sizing môi trường test hệ thống Roaming 2.0
A41: 40 | B41: 4198497 | D41: tuyenvm | E41: vinhtq18 | F41: Hoàn thành | G41: 45166 | H41: 45168 | I41: 45167 | M41: sizing hệ thống BCCS_CA chuyển đổi K8s (Hệ thống TEST)
A42: 41 | B42: 4199290 | D42: chinh3 | E42: vinhtq18 | F42: Hoàn thành | G42: 45167 | H42: 45174 | I42: 45174 | M42: Thẩm định tài liệu định cỡ tài nguyên lưu trữ hệ thống QLSX VTT mới
A43: 42 | B43: 4199538 | D43: TUYENVM | E43: vinhtq18 | F43: Hoàn thành | G43: 45175 | H43: 45177 | I43: 45177 | M43: PYC sizing hệ thống BCCS_CA chuyển đổi K8s (Hệ thống TEST) lần 2
A44: 43 | B44: PYC-743 | D44: hoangnt21 | E44: hoangld2 | F44: Hoàn thành | G44: 45176 | H44: 45179 | I44: 45180 | M44: Thẩm định sizing để xin bổ sung tài nguyên cho HTĐS Trong nước tránh cao tải CPU, RAM
A45: 44 | B45: 4199082 | D45: kientt6 | E45: ductn | F45: Hoàn thành | G45: 45239 | H45: 13/09/2023 | I45: 45269 | M45: PYC thẩm định sizing bổ sung cho hệ thống Callbot (đã ký). | N45: Thời gian thực hiện thay đổi do đội dự án điền sai loại yêu cầu
A46: 45 | B46: 4200717 | D46: sonht2 | E46: hieuhv13 | F46: Hoàn thành | G46: 15/09/2023 | H46: 19/09/2023 | I46: 19/09/2023 | M46: Thẩm định sizing Backend TV360 toàn cầu
A47: 46 | B47: 4201635 | D47: tuyenvm | E47: vinhtq18 | F47: Hoàn thành | G47: 22/09/2023 | H47: 26/09/2023 | I47: 26/09/2023 | M47: PYC sizing hệ thống BCCS_CA chuyển đổi K8s (Hệ thống TEST)
A48: 47 | B48: 4200717 | D48: sonht2 | E48: hieuhv13 | F48: Hoàn thành | G48: 45087 | H48: 45179 | I48: 45240 | M48: Thẩm định sizing Backend TV360 toàn cầu lan 2
A49: 48 | B49: PYC-3146 | D49: tiendc | E49: hoangld2 | F49: Hoàn thành | G49: 45209 | H49: 13/10/2023 | I49: 45240 | M49: Đánh giá sizing FTP server hệ thống Quản lý hồ sơ
A50: 49 | B50: PYC-3240 | D50: hieund28 | E50: ductn | F50: Hoàn thành | G50: 45270 | H50: 17/10/2023 | I50: 16/10/2023 | M50: DAC][FMRA] Đánh giá sizing cho hệ thống RATING
A51: 50 | B51: PYC-3585 | D51: hoabv8 | E51: ductn | F51: Hoàn thành | G51: 20/10/2023 | H51: 24/10/2023 | I51: 20/10/2023 | M51: Thẩm định sizing để xin bổ sung tài nguyên cho SmartMotor
A52: 51 | B52: Mail | D52: khanhnn25 | E52: hieuhv13 | F52: Hoàn thành | G52: 23/10/2023 | H52: 25/10/2023 | I52: 24/10/2023 | M52: Sizing hệ thống Viettel safe platform
A53: 52 | B53: PYC-3910 | D53: tamddt1 | E53: ductn | F53: Hoàn thành | G53: 25/10/2023 | H53: 27/10/2023 | I53: 25/10/2023 | M53: THẩm định sizing Camera JF bổ sung tài nguyên
A54: 53 | B54: PYC-4002 | D54: soncn2 | E54: vinhtq18 | F54: Hoàn thành | G54: 31/10/2023 | H54: 31/10/2023 | I54: 31/10/2023 | M54: Review Sizing hệ thống Roaming 2.0 Product
A55: 54 | B55: PYC-4082 | D55: hainn31 | E55: vinhtq18 | F55: Hoàn thành | G55: 44968 | H55: 45088 | I55: 45088 | M55: Đánh giá sizing cho hệ thống Mediation
A56: 56 | B56: PYC-10656 | D56: tamdtt1 | E56: thongnv31 | F56: Hoàn thành | G56: 45414 | H56: 45475 | I56: 45445 | L56: 44997 | M56: THẩm định sizing Vtracking Nội bộ
A57: 57 | B57: PYC-4629 | D57: thaind4 | E57: ductn | F57: Hoàn thành | G57: 45088 | H57: 45149 | I57: 45149 | M57: Thẩm định sizing, cấp phát tài nguyên IPCC 2.0 phân hệ videocall của TTDVKH VTT
A58: 58 | B58: PYC-4808 | D58: khanhdn1 | E58: ductn | F58: Hoàn thành | G58: 45118 | H58: 45180 | I58: 45149 | M58: Thẩm định sizing hệ thống TMS v6
A59: 59 | B59: PYC-4244 | D59: hoppv3 | E59: hoangld2 | F59: Hoàn thành | G59: 45240 | H59: 14/11/2023 | I59: 13/11/2023 | K59: 5 | L59: 29/12/2023 | M59: Thẩm định Sizing hệ thống Quản lý khách hàng-xử lý cảnh báo rủi ro
A60: 60 | B60: PYC-4954 | D60: hoabv8 | E60: vinhtq18 | F60: Hoàn thành | G60: 45210 | H60: 13/11/2023 | I60: 45210 | J60: 1 | L60: 30/8/2024 | M60: Thẩm định sizing để xin bổ sung tài nguyên cho SmartMotor lần 2
A61: 61 | B61: PYC-5252 | D61: thaind4 | E61: ductn | F61: Hoàn thành | G61: 15/11/2023 | H61: 17/11/2023 | I61: 16/11/2023 | M61: Thẩm định sizing, cấp phát tài nguyên IPCC 2.0 phân hệ videocall của TTDVKH VTT lần 2
A62: 62 | B62: PYC-5300 | D62: thaolt34 | E62: vinhtq18 | F62: Hoàn thành | G62: 15/11/2023 | H62: 17/11/2023 | I62: 16/11/2023 | M62: Đánh giá sizing cho hệ thống Mediation Đối Soát MSC
A63: 63 | B63: PYC-5310 | D63: minhca | E63: hoangld2 | F63: Hoàn thành | G63: 15/11/2023 | H63: 17/11/2023 | I63: 16/11/2023 | M63: Thẩm định sizing cho hệ thống MyLife
A64: 64 | B64: PYC-5892 | D64: tuyenvm | E64: hoangld2 | F64: Hoàn thành | G64: 24/11/2023 | H64: 28/11/2023 | I64: 27/11/2023 | M64: Đánh giá Sizing tăng tải cho phân hệ WEB BCCS_CM_CA
A65: 65 | B65: PYC-5913 | D65: hanq1 | E65: vinhtq18 | F65: Hoàn thành | G65: 24/11/2023 | H65: 28/11/2023 | I65: 28/11/2023 | L65: 45089 | M65: MappingGW/Ví Doanh nghiệp - Bổ sung storage cho hệ thống
A66: 66 | B66: PYC-6254 | D66: tamdttt1 | E66: vinhtq18 | F66: Hoàn thành | G66: 29/11/2023 | H66: 44938 | I66: 44938 | L66: 45272 | M66: AI Home Camera - Xin cấp server | N66: bypass sizing để POC 6 tháng
A67: 67 | B67: PYC-6448 | D67: phund2 | E67: vinhtq18 | F67: Hoàn thành | G67: 44938 | H67: 45058 | I67: 45058 | M67: Videocall -
A68: 68 | B68: PYC-6451 | D68: tuyenvm | E68: hoangld2 | F68: Hoàn thành | G68: 44938 | H68: 45058 | L68: 45089 | M68: BCCS_CM_CA - Phục vụ QHĐC 2024-2025
A69: 69 | B69: PYC-6825 | D69: tungct | E69: vinhtq18 | F69: Hoàn thành | G69: 45119 | H69: 45242 | I69: 45119 | L69: 45119 | M69: Định cỡ Module AI digital Human Gateway phục vụ truyền thông và trải nghiệm | N69: bypass phục vụ sự kiện MWC
A70: 70 | B70: PYC-7045 | D70: hainv71 | E70: hoangld2 | F70: Hoàn thành | G70: 45272 | H70: 15/12/2023 | L70: 45272 | M70: Nâng cấp tài nguyên Hóa đơn điện tử phục vụ cao điểm kinh doanh hóa đơn xăng dầu | N70: Đơn vị chưa gửi file văn bản sizing
A71: 71 | B71: PYC-7061 | C71: GPDVS | D71: sonht2 | E71: vinhtq18 | F71: Hoàn thành | G71: 45352 | H71: 45444 | I71: 45383 | L71: 24/1/2024 | M71: thẩm định sizing TV360 backend và kho video
A72: 72 | B72: PYC-7062 | C72: GPDVS | D72: sonht2 | E72: vinhtq18 | F72: Hoàn thành | G72: 45272 | H72: 15/12/2023 | I72: 15/12/2023 | K72: 3 | L72: 15/12/2023 | M72: thẩm định sizing TV360 TMS
A73: 73 | B73: PYC-7152 | C73: BSS | D73: phucth20 | E73: vinhtq18 | F73: Hoàn thành | G73: 14/12/2023 | H73: 18/12/2023 | I73: 18/12/2023 | M73: Thẩm định sizing Module Kafka và CampaignConsumer cho hệ thống Happycall
A74: 74 | B74: PYC-7269 | C74: BSS | D74: soncn2 | E74: hoangld2 | F74: Hoàn thành | G74: 18/12/2023 | H74: 20/12/2023 | I74: 19/12/2023 | L74: 20/12/2023 | M74: thẩm định hệ thống BADO
A75: 75 | B75: PYC-7457 | C75: BSS | D75: soncn2 | E75: cntt_ductn | F75: Hoàn thành | G75: 19/12/2023 | H75: 21/12/2023 | I75: 20/12/2023 | L75: 22/12/2023 | M75: thẩm định hệ thống Chặn nợ cước định kỳ
A76: 76 | B76: PYC-7882 | C76: VAS | D76: kiennv8 | E76: vinhtq18 | F76: Hoàn thành | G76: 26/12/2023 | H76: 29/12/2023 | I76: 27/12/2023 | L76: 45536 | M76: thẩm định sizing Storage cho hệ thống Lifebox
A77: 77 | B77: PYC-7876 | C77: VAS | D77: hanq1 | E77: vinhtq18 | F77: Hoàn thành | G77: 26/12/2023 | H77: 29/12/2023 | I77: 29/12/2023 | L77: 45352 | M77: thẩm định sizing nhu cầu Storage Object 2024 cho các dịch vụ Video VAS
A78: 78 | B78: PYC-8223 | C78: VAS | D78: hanq1 | E78: ductn | F78: Hoàn thành | G78: 45323 | H78: 45413 | I78: 45413 | L78: 45413 | M78: PYC thẩm định sizing nhu cầu CDN 2024 cho các dịch vụ Video VAS
A79: 79 | B79: PYC-8059 | C79: BSS | D79: thanhtt69 | E79: khanhnd23 | F79: Hoàn thành | G79: 45323 | H79: 45413 | I79: 45413 | L79: 45413 | M79: sizing DB Mysign
A80: 80 | B80: PYC-8289 | C80: BSS | D80: hainv71 | E80: vinhtq18 | F80: Hoàn thành | G80: 45323 | H80: 45413 | I80: 45323 | L80: 45413 | M80: Thẩm định Nâng cấp tài nguyên Hóa đơn điện tử phục vụ cao điểm kinh doanh hóa đơn xăng dầu
A81: 81 | B81: PYC-8562 | C81: BSS | D81: vanha1 | E81: vinhtq18 | F81: Hoàn thành | G81: 45352 | H81: 45413 | I81: 45352 | L81: 45352 | M81: Thẩm định sizing để xin bổ sung tài nguyên cho VIETTEL++
A82: 82 | B82: PYC-8724 | C82: BSS | D82: minhca | E82: vinhtq18 | F82: Hoàn thành | G82: 45383 | H82: 45505 | I82: 45413 | L82: 24/1/2024 | M82: sizing cho hệ thống MyLife-clone-lần 2
A83: 83 | B83: PYC-8964 | C83: BSS | D83: giangnt109 | E83: khanhnd23 | F83: Hoàn thành | G83: 45505 | H83: 45597 | I83: 45536 | L83: 45294 | M83: Sizing hệ thống Campaign Management bổ sung
A84: 84 | B84: PYC-9185 | C84: GPDVS | D84: anhtt67 | E84: vinhtq18 | F84: Hoàn thành | G84: 45597 | H84: 15/1/2024 | I84: 45597 | M84: Sizing hệ thống My Safe
A85: 85 | B85: PYC-10448 | C85: BSS | D85: dungdt60 | E85: vinhtq18 | F85: Hoàn thành | G85: 31/1/2024 | H85: 45324 | I85: 45323 | L85: 21/2/2024 | M85: sizing hệ thống Mobile-CA
A86: 86 | B86: PYC-9367 | C86: DAC | D86: quannv28 | E86: khanhnd23 | F86: Hoàn thành | G86: 16/1/2024 | H86: 18/1/2024 | I86: 18/1/2024 | M86: sizing 2 server public phục vụ TK hệ thống báo cáo cho Ban TGĐ
A87: 87 | B87: PYC-9404 | C87: DVTH | D87: trungnt21 | E87: vinhtq18 | F87: Hoàn thành | G87: 18/1/2024 | H87: 22/1/2024 | I87: 22/1/2024 | K87: 3 | L87: 24/1/2024 | M87: sizing Storage S3 (Cloud Storage) cho TV360 năm 2024
A88: 88 | B88: PYC-10145 | C88: BSS | D88: soncn2 | E88: thongnv31 | F88: Hoàn thành | G88: 25/1/2024 | H88: 29/1/2024 | I88: 29/1/2024 | L88: 45293 | M88: Sizing hệ thống Gửi thông báo cước
A89: 89 | B89: PYC-10206 | C89: DAC | D89: thaolt34 | E89: vinhtq18 | F89: Hoàn thành | G89: 26/1/2024 | H89: 30/1/2024 | I89: 29/1/2024 | M89: Sizing hệ thống Mediation tập trung
A90: 90 | B90: PYC-10207 | C90: DAC | D90: thaolt34 | E90: thongnv31 | F90: Hoàn thành | G90: 26/1/2024 | H90: 30/1/2024 | I90: 29/1/2024 | M90: Sizing hệ thống ImportDS bổ sung backdate 2021
A91: 91 | B91: PYC-10208 | C91: DAC | D91: thaolt34 | E91: khanhnd23 | F91: Hoàn thành | G91: 26/1/2024 | H91: 30/1/2024 | I91: 29/1/2024 | M91: Sizing hệ thống ĐS VAS Mobile : MariaDB
A92: 93 | B92: PYC-10371 | C92: BSS | D92: thanhtt69 | E92: khanhnd23 | F92: Hoàn thành | G92: 30/1/2024 | H92: 45324 | I92: 22/2/2024 | L92: 45507 | M92: sizing ĐỊNH CỠ HỆ THỐNG VBHXH MySign
A93: 94 | B93: PYC-10792 | C93: BSS | D93: anhld55 | E93: vinhtq18 | F93: Hoàn thành | G93: 45445 | H93: 16/2/2024 | I93: 16/2/2024 | L93: 15/3/2024 | M93: Sizing bổ sung tài nguyên hệ thống smsbrandname cho rủi ro RISK_20231208_37706
A94: 95 | B94: PYC-10923 | C94: BSS | D94: thanhtt69 | E94: thongnv31 | F94: Hoàn thành | G94: 16/2/2024 | H94: 20/2/2024 | I94: 19/2/2024 | L94: 45599 | M94: sizing ĐỊNH CỠ HỆ THỐNG Cloud CA
A95: 96 | B95: PYC-11030 | C95: DAC | D95: anhvt105 | E95: vinhtq18 | F95: Hoàn thành | G95: 19/2/2024 | H95: 21/2/2024 | I95: 19/2/2024 | M95: Yêu cầu cấp phát server VTT-Analytic
A96: 97 | B96: PYC-11236 | C96: DAC | D96: thaolt34 | E96: vinhtq18 | F96: Hoàn thành | G96: 21/2/2024 | H96: 23/2/2024 | I96: 26/2/2024 | M96: Sizing hệ thống ĐSQT : MariaDB
A97: 98 | B97: PYC-11304 | C97: GPDVS | D97: sonht2 | E97: thongnv31 | F97: Hoàn thành | G97: 22/2/2024 | H97: 26/2/2024 | I97: 26/2/2024 | K97: 3 | L97: 45446 | M97: thẩm định sizing TV360 NMS STB
A98: 99 | B98: PYC-11971 | C98: DAC | D98: anhvt105 | E98: thongnv31 | F98: Hoàn thành | G98: 45385 | H98: 45446 | I98: 45446 | M98: sizing cụm server do VTM bàn giao | N98: quá thời gian sizing, đội dự án tạo PYC-14875 thay thế
A99: 100 | B99: PYC-12042 | C99: DAC | D99: binhvd7 | E99: khanhnd23 | F99: Hoàn thành | G99: 45385 | H99: 45446 | I99: 45385 | M99: sizing DB Oracle Server tách khỏi cụm Datalake_Viettel Report
A100: 101 | B100: PYC-12156 | C100: DAC | D100: binhnn7 | E100: ductn | F100: Hoàn thành | G100: 45415 | H100: 45476 | I100: 45476 | L100: 21/3/2024 | M100: sizing Face Search | N100: bypass
A101: 104 | B101: PYC-12313 | C101: BSS | D101: soncn2 | E101: vinhtq18 | F101: Hoàn thành | G101: 45476 | H101: 45629 | I101: 13/3/2024 | L101: 24/4/2024 | M101: Sizing ứng cứu tài nguyên hệ thống Roaming 1.0
A102: 102 | B102: PYC-11912 | C102: BSS | D102: linhnh35 | E102: vinhtq18 | F102: Hoàn thành | G102: 45507 | H102: 45629 | I102: 45507 | M102: Sizing thông tin mở kết nối ftp smsbrandname cho PYC-11853
A103: 103 | B103: PYC-12423 | C103: DAC | D103: longhv15 | E103: thongnv31 | F103: Hoàn thành | G103: 45507 | H103: 45629 | I103: 45599 | L103: 25/4/2024 | M103: sizing cụm server My Viettel recommend & AI system
A104: 104 | B104: PYC-12549 | C104: BSS | D104: huync2 | E104: ductn | F104: Hoàn thành | G104: 45629 | H104: 14/3/2024 | I104: 15/3/2024 | K104: 2 | M104: sizing định kỳ hệ thống minigame
A105: 105 | B105: PYC-12718 | C105: DAC | D105: anhvt105 | E105: thongnv31 | F105: Hoàn thành | G105: 14/3/2024 | H105: 18/3/2024 | I105: 15/3/2024 | M105: sizing cụm server do VTM bàn giao 2
A106: 106 | B106: PYC-12720 | C106: BSS | D106: kiennt9 | E106: khanhnd23 | F106: Hoàn thành | G106: 14/3/2024 | H106: 18/3/2024 | I106: 15/3/2024 | M106: sizing bổ sung thêm phân vùng /backup của DB dịch vụ VDA
A107: 107 | B107: PYC-13038 | C107: BSS | D107: hainv71 | E107: vinhtq18 | F107: Hoàn thành | G107: 19/3/2024 | H107: 21/3/2024 | I107: 20/3/2024 | K107: 2 | L107: 25/3/2024 | M107: sizing Cung cấp tài nguyên hệ thống giám sát tập trung VTT Prometheus
A108: 108 | B108: PYC-13053 | C108: DAC | D108: tinhnx | E108: ductn | F108: Hoàn thành | G108: 19/3/2024 | H108: 21/3/2024 | I108: 21/3/2024 | M108: Sizing cấp phát tài nguyên cho Hệ thống Quản lý Viettel Consent
A109: 109 | B109: PYC-13397 | C109: BSS | D109: tiendc | E109: thongnv31 | F109: Hoàn thành | G109: 25/3/2024 | H109: 27/3/2024 | I109: 26/3/2024 | K109: 3 | L109: 22/4/2024 | M109: sizing xin cấp tài nguyên triển khai lưu trữ hồ sơ storage S3
A110: 110 | B110: PYC-13464 | C110: BSS | D110: tungnp2 | E110: ductn | F110: Hoàn thành | G110: 26/3/2024 | H110: 28/3/2024 | I110: 28/3/2024 | L110: 45569 | M110: sizing định kỳ hệ thống MyViettel K8s
A111: 110 | B111: PYC-13515 | C111: BSS | D111: dungdt60 | E111: vinhtq18 | F111: Hoàn thành | G111: 27/3/2024 | H111: 29/3/2024 | I111: 45295 | L111: 45295 | M111: sizing hệ thống Mobile-CA bổ sung HDD cho hạ tầng | N111: đóng Jira ticket do nội dung trùng với PYC-10448
A112: 111 | B112: PYC-13709 | C112: GPDVS | D112: tuta8 | E112: khanhnd23 | F112: Hoàn thành | G112: 28/3/2024 | H112: 45295 | I112: 45295 | L112: 30/5/2024 | M112: sizng hệ thống Smart home
A113: 112 | B113: PYC-13900 | C113: BSS | D113: soncn2 | E113: ductn | F113: Hoàn thành | G113: 45295 | H113: 45355 | I113: 45355 | L113: 45355 | M113: hệ thống Pay199 xử lý rủi ro RISK_20230420_32435_PAY199
...

Sheet Cấp phát TN
C1: Ghi chú : - Khi có tiến độ mới thì xuống dòng ghi chữ [New] ở đầu dòng mới để lãnh đạo nắm được - Đầu mối đơn vị ghi tên mail và đơn vị yêu cầu - Khi xong thì đánh dấu x vào cột Hoàn Thành để lãnh đạo nắm được
A2: STT | B2: Mã PYC | C2: Dự án | D2: Đơn vị | E2: Đầu mối y/c | F2: Đầu mối P.HT | G2: Mã SR | H2: Tiến độ, vướng mắc, đề xuất | I2: Thời gian tiếp nhận y/c | J2: Timeline thực hiện theo GNOC | K2: Thời gian hoàn thành | L2: Hoàn thành
A3: 1 | C3: Jira | D3: BSS | F3: hieuhv13 | G3: SR_VN_20230130_729328/ SR_VN_20230312_752885 | J3: KTTC:30/1-6/2 (Thẩm định xong đúng hạn) Ngày pending: 6/2-28/2 VHKT: 8/3-16/3 | L3: x
A4: 2 | C4: C360 | D4: DAC | F4: hieuhv13 | G4: SR_VN_20230405_767360(thu hồi)/ SR_VN_20230405_767368(cấp phát) | L4: x
A5: 3 | C5: Cấp phát tài nguyên dự án QLHS vật lý 3DB Maria | D5: #N/A | F5: hieuhv13 | G5: Đã trao đổi với chaulm5 | H5: A Haipn yc bỏ do đã cắt chuyển chung với DB dự án khác | L5: x
A6: 4 | C6: Cấp phát tài nguyên dự án vật lý CCAI | D6: DAC | E6: dungha7 | F6: hieuhv13 | G6: Đã lập luồng mail với chaulm5 | H6: Đã cấp phát xong | L6: x
A7: 5 | C7: Điều chỉnh tài nguyên Survey 2.0 | D7: BSS | F7: hieuhv13 | G7: SR_VN_20230419_775285 SR_VN_20230425_779549 | H7: 2Các svr cơ bản là đã xong chỉ có 2 DB bị thiếu dung lượng do đã hết khả năng nâng cấp. tuyenpv9 đã thống nhất tạm thời sử dụng như vậy. | J7: KTTC:19/4/2023-26/4/2023 VHKT: 25/4/2023-09/5/2023 | L7: x
A8: 6 | C8: Thu hồi tài nguyên Survey 2.0 | D8: BSS | F8: hieuhv13 | G8: SR_VN_20230426_780377 | J8: KTTC:26/04/2023-08/05/2023 | L8: x
A9: 7 | C9: Cấp phát tài nguyên CCAI | D9: DAC | F9: hieuhv13 | G9: SR_VN_20230419_775606 | H9: Đã hoàn thành | L9: x
A10: 8 | C10: Cấp phát tài nguyên cho MBS | D10: BSS | F10: vinhtq18 | G10: SR_VN_20230480_776480 | J10: KTTC:20/4/2023-27/4/2023 | L10: x
A11: 9 | C11: Thu hồi tài nguyên chuẩn bị cho điều chuyển HT Campaign | D11: BSS | E11: Phund2 | F11: Hoangld2 | G11: KTTC: SR_VN_20230509_786705 VHKT: SR_VN_20230509_786749 | J11: VHKT: 9/5/2023-16/5/2023 | L11: x
A12: 10 | C12: Bổ sung tài nguyên cho hệ thống data3G | D12: VTN | E12: sonnh30 | G12: KTTC: SR_VN_20230320_756800 | H12: Đội dự án cần cấp thêm 4 server qua link LB nhưng hệ thống mới của VTN chưa xong, hiện đang lỗi tủ đĩa chờ part để thay thế, dự kiến cuối tháng 6 mới hoàn thành sonnh30_PUDCNTT-TTVHKTTC-VTN | L12: ẩn | M12: Theo dõi, k tham gia trực tiếp
A13: 11 | C13: Dự án C06 BCA | D13: #N/A | E13: thangnx5 | H13: Đã review xong hồ sơ kt và báo giá gửi cho ttgp cntt | L13: ẩn | M13: Theo dõi, k tham gia trực tiếp
A14: 12 | C14: Hệ thống CMP thương mại | D14: #N/A | E14: quyln3 | H14: A Haipn đã hướng dẫn đơn vị các thủ tục cần làm trước khi được cấp tài nguyên | L14: ẩn | M14: ko có trong file cấp phát
A15: 13 | C15: APIGW | D15: DAC | E15: anhnt576 | F15: Hoangld2 | G15: KTTC: SR_VN_20230705_826658 VHKT: SR_VN_20230710_830025 | H15: đã cấp xong | L15: x
A16: 14 | C16: Bổ sung disk dự án HDDT | D16: BSS | E16: hainv71 | F16: hieuhv13 | G16: SR_VN_20230630_823903 | H16: Đã hoàn thành | J16: 30/06/2023 17:34:00-11/07/2023 17:34:00 | L16: x
A17: 15 | C17: Bổ sung storage mOffice | D17: #N/A | E17: trangttt31 | F17: hieuhv13 | H17: Đã hoàn thành | L17: x | M17: ko có trong file cấp phát
A18: 16 | C18: Hệ thống TMS VHT | D18: BSS | E18: tiendd tuanna29 | F18: hieuhv13 | G18: VHKT: SR_VN_20230711_831000 | H18: Đã cấp xong | J18: 11/07-20/07/2023 | L18: x | M18: lấy của dự án NMS wifi, k có trong file cấp phát
A19: 17 | C19: Voice brand name | D19: BSS | E19: tuyenpv9 | F19: Hoangld2 | G19: SR_VN_20230602_803532 | H19: Đã hoàn thành | J19: KTTC: 2/6-9/6 | L19: x
A20: 18 | C20: Hợp đồng điện tử | D20: BSS | E20: dattht | F20: Hoangld2 | G20: SR_VN_20230623_818696 | H20: Đã hoàn thành | L20: x
A21: 19 | C21: Hợp đồng điện tử nội bộ | D21: BSS | E21: dattht | F21: Hoangld2 | G21: KTTC: SR_VN_20230626_841238 | H21: Đã cấp phát xong | J21: KTTC: 26/7-2/8 VHKT: 3/8-9/8 | L21: x
A22: 20 | C22: Cấp UCTT DCB_DB cho TT VAS | D22: VAS | E22: hanq1 | F22: Hoangld2 | H22: Không thấy A Hanq làm sizing nên tạm đóng lại | L22: x | M22: ko có trong file cấp phát
A23: 21 | C23: Cấp bổ sung dung lượng Vtracking 1.2 | D23: BSS | E23: tuandm2 | F23: Hoangld2 | G23: KTTC: SR_VN_20230717_834515 | H23: Đã cấp xong | J23: KTTC:17/7-24/7 | L23: x | M23: ko có trong file cấp phát
A24: 22 | C24: HT quản lý hồ sơ CT Trái tim cho e | D24: BSS | E24: cuongbm,dattht | F24: vinhtq18 | G24: SR_VN_20230809_854573 | H24: Đã cấp phát xong | J24: KTTC:14/08-21/08/2023 | L24: x | M24: ko có trong file cấp phát
A25: 23 | C25: Tổng hợp nhu cầu cho phần ghi log tập trung | D25: #N/A | E25: namdx;thuynt105 | F25: vinhtq18 | H25: dừng, Hoalh1 thông báo PHT không cần phải tham gia kế hoạch nữa | L25: x | M25: ko có trong file cấp phát
A26: 24 | C26: Cấp phát tài nguyên NAS dự án HDDT | D26: BSS | E26: hainv71 | F26: hieuhv13 | G26: SR_VN_20230620_815799 | H26: Đã hoàn thành | L26: x
A27: 25 | C27: Cấp phát 5 server dự án HDDT | D27: BSS | E27: hainv71 | F27: hieuhv13 | H27: Hủy do chuyển đổi phương án | L27: x
A28: 26 | C28: Cấp phát tài nguyên DB hệ thống nhạc chờ quảng cáo phục vụ giao ban VTN | D28: BSS | E28: hanq1 | F28: ductn | H28: Đã cấp phát xong | L28: x | M28: ko có trong file cấp phát
A29: 27 | C29: Bổ sung tài nguyên cho hệ thống data3G-lần 2 | D29: BSS | F29: None | G29: SR_VN_20230705_826839 | H29: đã cấp xong | J29: KTTC:5/7-14/7 | L29: x
A30: 28 | C30: Cấp phát tài nguyên cho Vtracking 2.0 | D30: BSS | E30: ducdm25 | F30: ductn | G30: SR_VN_20230802_846756 | H30: Đã cấp phát xong | J30: KTTC:2/8-8/8 | L30: x | M30: ko có trong file cấp phát
A31: 29 | C31: Cấp phát tài nguyên cho USSD199 chuyển đổi CSDL mã nguồn mở | D31: BSS | E31: quanhh3 | F31: ductn | G31: SR_VN_20230821_859805 SR_VN_20230823_862290 | H31: Đã cấp phát xong | J31: KTTC:23-31/08/2023 | L31: x
A32: 30 | C32: Thu hồi tài nguyên hệ thống nhạc chờ quảng cáo | D32: VAS | E32: hanq1 | F32: ductn | G32: SR_VN_20230801_845766 | H32: Đã thu hồi xong | J32: KTTC:2/8-8/8 | L32: x
A33: 31 | C33: Cấp phát tài nguyên hệ thống nhạc chờ quảng cáo | D33: VAS | E33: hanq1 | F33: ductn | G33: SR_VN_20230801_845806 | H33: Đã cấp phát xong | J33: KTTC:2/8-8/8 | L33: x
A34: 32 | C34: Thu hồi phân vùng /backup DB HDDT 2.0 | D34: BSS | E34: hainv71 | F34: hieuhv13 | G34: SR_VN_20230721_838316 | H34: Đã thu hồi xong | L34: x
A35: 33 | C35: Bổ sung RAM, backup, logs, u01 DB HDDT 2.0 | D35: BSS | E35: hainv71 | F35: hieuhv13 | G35: SR_VN_20230721_838319 SR_VN_20230804_848646 SR_VN_20230822_860821 | H35: Cần dồn dịch tài nguyên nên cần thu hồi và cấp phát lại các VM Đang đẩy SR thu hồi sang VHKT. Còn 1 svr chưa move xong hạ tầng và 9 svr chưa nâng ram | J35: Do VHKT và KTTC chưa thống nhất được với nhau nên tạm ko cập nhật | L35: x
A36: 34 | C36: Bổ sung Disk DB truyền nhận HDDT | D36: BSS | E36: hainv71 | F36: hieuhv13 | G36: SR_VN_20230721_838308 SR_VN_20230804_848646 SR_VN_20230822_860821 | H36: Cần dồn dịch tài nguyên nên cần thu hồi và cấp phát lại các VM Đang đẩy SR thu hồi sang VHKT. Còn 1 svr chưa move xong hạ tầng và 9 svr chưa nâng ram | J36: Do VHKT và KTTC chưa thống nhất được với nhau nên tạm ko cập nhật | L36: x
A37: 35 | C37: Thu hồi phân vùng /backup DB truyen nhan HDDT 2.0 | D37: BSS | E37: hainv71 | F37: hieuhv13 | G37: SR_VN_20230721_838393 SR_VN_20230728_842829 | H37: Đã thu hồi xong | L37: x
A38: 36 | C38: ARPU dagoras | D38: BSS | E38: anhnt576 | F38: vinhtq18 | G38: SR_VN_20230731_843633 | H38: Đã cấp phát xong | J38: KTTC:31/07/2023-07/08/2023 | L38: x
A39: 37 | C39: Cấp phát 10 server cho Imuzik dồn dịch sang VTT private cloud | D39: VAS | E39: nhatnt2 | F39: ductn | G39: SR_VN_20230825_863935 SR_VN_20230824_863188 | H39: Đã cấp phát xong | J39: Cấp phát theo luồng nBox | L39: x
A40: 38 | C40: Cấp phát tài nguyên server FTP cho hệ thống IBM | D40: BSS | E40: dinhvv | F40: vinhtq18 | G40: SR_VN_20230830_867755 | H40: Đã cấp phát xong | J40: KTTC:30/08-08/09/2023 | L40: x
A41: 39 | C41: Cấp phát tài nguyên hệ thống USSD098 chuyển đổi CSDL mã nguồn mở | D41: BSS | E41: phucnd12 | F41: ductn | G41: SR_VN_20230912_877415 | H41: Đã cấp phát xong | J41: VHKT: 28/09 - 06/10 | L41: x
A42: 40 | C42: Cấp phát tài nguyên hệ thống IPCC 2.0 | D42: BSS | E42: thaind4 | F42: ductn | G42: SR_VN_20230831_868990 SR_VN_20230908_875132 | H42: Đã cấp phát xong | L42: x
A43: 41 | C43: Cấp phát tài nguyên hệ thống Hóa đơn điện tử truyền nhận | D43: BSS | E43: hienlt15 | F43: ductn | G43: SR_VN_20230919_883121 | H43: KTTC yêu cầu gộp lại thành 1 bản sizing duy nhất | L43: Hủy
A44: 42 | C44: Cấp phát bổ sung tài nguyên cho hệ thống QLSX Jira | D44: BSS | E44: dinhvv, chinh3 | F44: vinhtq18 | G44: SR_VN_20230915_880493 | H44: Đã cấp phát xong | J44: KTTC:15/09-22/09/2023 | L44: x
A45: 43 | C45: cấp phát tài nguyên hệ thống BCCS CC | D45: BSS | E45: hungpm6, hoangnt14 | F45: vinhtq18 | G45: SR_VN_20230915_880549 | H45: Đã cấp phát xong | J45: KTTC:15/09-22/09/2023 | L45: x
A46: 44 | C46: cấp phát tài nguyên hệ thống CMP | D46: BSS | E46: duongvx, ducdm25 | F46: hoangld2 | G46: SR_VN_20230920_883909 SR_VN_20231030_919726 | H46: Đã cấp phát xong | L46: x
A47: 45 | C47: cấp phát tài nguyên bổ sung cho hệ thống đối soát trong nước | D47: DAC | E47: hoangnt21 | F47: hoangld2 | G47: SR_VN_20231228_971876 | H47: Đã cấp phát xong | J47: KTTC: 28/12-4/1/2024 | L47: x
A48: 46 | C48: cấp phát tài nguyên cho hệ thống vBHXH | D48: BSS | E48: khanhdn1 | F48: ductn | G48: SR_VN_20230928_891118 SR_VN_20230929_891788 | H48: Đã cấp phát xong | L48: x
A49: 47 | C49: cấp phát tài nguyên cho DB tổng đài 198 | D49: DVKH | E49: trong td1 | F49: hoangld2 | G49: SR_VN_20231009_898775 SR_VN_20231016_904382 | H49: Đã cấp phát xong | J49: KTTC:9/10-16/10 VHKT: 16/10-23/10 | L49: x
A50: 48 | C50: Điều chuyển 2 sv vật lý cho IPCC HNI làm DR DB | D50: DVKH | E50: trongtd1 | F50: vinhtq18 | G50: không tạo SR | H50: Hoàn thành | L50: x
A51: 49 | C51: cấp phát tài nguyên hệ thống video call stringee | D51: BSS | E51: hoangnt14 | F51: vinhtq18 | G51: SR_VN_20231019_907977 | H51: VTNET từ chối với lí do: chưa có sở cứ rõ ràng từ 45000 cuộc gọi theo "dự kiến"; chưa chỉ rõ mở rộng trên node lưu trữ nào hay chia đều cả hai node Đang yêu cầu hoangnt14 sizing lại | I51: 19/10/2023 | J51: KTTC:19/10-26/10/2023 | L51: Hủy
A52: 50 | C52: Cấp bổ sung dung lượng cho hệ thống Smart Motor | D52: BSS | E52: hoabv8 | F52: ductn | G52: SR_VN_20231115_933218 | H52: Đã cấp phát xong | J52: KTTC:15/11-22/11/2023 | L52: x
A53: 51 | C53: Cấp tài nguyên cho hệ thống TMS V6 | D53: BSS | E53: khanhdn1 | F53: ductn | G53: SR_VN_20231114_932016 | H53: Đã cấp phát xong | J53: Nbox: 21/11-22/11/2023 | L53: x
A54: 52 | C54: Cấp phát tài nguyên hệ thống MyLife | D54: BSS | E54: minhca | F54: hoangld2 | G54: SR_VN_20231129_945650 SR_VN_20231130_946805 | H54: VTNET đang cấp phát tài nguyên | J54: VHKT: 8/12/2023 | L54: x
A55: 53 | C55: Thu hồi tài nguyên 2 server VTT - Migrate | D55: DVKH | E55: thaind4 | F55: vinhtq18 | G55: SR_VN_20240220_1016538 | H55: Đã thu hồi xong | I55: 20/2/2024 | J55: VHKT:20/2/2024 - 22/2/2024 | K55: 22/2/2024 | L55: x
A56: 54 | C56: Cấp phát tài nguyên hệ thống Vtag | D56: GPCNTT | E56: tungnt12 | F56: Hoangld2 | G56: SR_VN_20231211_955751 | H56: Hiện đã thống nhất giữa VTS và VTN về phương án cấp tài nguyên chung Vtracking, đang triển khai các bước tiếp theo | I56: 7/12/2023 | J56: KTTC:11/12-18/12/2023 | L56: Hủy
A57: 55 | C57: Cấp phát tài nguyên MapppingGW | D57: VAS | E57: hanq1 | F57: vinhtq18 | G57: SR_VN_20231211_955585 SR_VN_20231211_955847 | H57: Huỷ do hanq1 sizing lại phương án khác | I57: 45271 | J57: KTTC:11/12-18/12/2023 | L57: Hủy
A58: 56 | C58: Cấp phát tài nguyên dựng AI Digital Human | D58: DAC | E58: kientt6 | F58: vinhtq18 | G58: SR_VN_20231212_956779 | H58: Đã cấp phát xong | I58: 45272 | J58: KTTC:12/12-19/12/2023 | K58: 13/12/2023 | L58: x
A59: 57 | C59: Cấp phát tài nguyên hệ thống IPCC phân hệ Videocall và Social | D59: DVKH | E59: thaind4 | F59: ductn | G59: SR_VN_20231215_960486 | H59: Đã cấp phát xong | I59: 15/12/2023 | J59: KTTC:15/12-25/12/2023 | L59: x
A60: 58 | C60: cấp phát tài nguyên hệ thống Viettel++ chạy chương trình Tết 2024 | D60: BSS | E60: vanha1 | F60: vinhtq18 | G60: SR_VN_20240104_977532 | H60: Đã cấp phát xong | I60: 45383 | J60: KTTC:4/1-11/1/2024 | K60: 45383 | L60: x
A61: 59 | C61: cấp phát server HDDT xăng dầu VTT | D61: BSS | E61: hainv71 | F61: vinhtq18 | G61: SR_VN_20240110_982362 SR_VN_20240116_988764(thu hồi tài nguyên) | H61: Đã cấp phát xong | I61: 45505 | J61: KTTC:8/1-16/1/2024 | K61: 23/1/2024 | L61: x
A62: 60 | C62: Bổ sung dung lượng Voice Brandname | D62: BSS | E62: tuyenpv9 | F62: vinhtq18 | G62: SR_VN_20240109_981257 | H62: Đã cấp phát xong | I62: 45536 | J62: KTTC:9/1-16/1/2024 | K62: 16/1/2024 | L62: x
A63: 61 | C63: Bổ sung tài nguyên cho TV360 backend và kho Video | D63: DVTH | E63: sonht2 | F63: vinhtq18 | G63: SR_VN_20240115_987094 | H63: Đã huỷ do VTNET không đủ tài nguyên cấp | I63: 45597 | J63: KTTC:11/1-18/1/2024 | K63: 20/1/2024 | L63: Hủy
A64: 62 | C64: Cấp phát tài nguyên CCAI 2023 | D64: DAC | E64: anhvt105 | F64: vinhtq18 | G64: SR_VN_20240201_1016847 | H64: Đã cấp phát xong, VTNET chưa cấp được storage Bigdata + Archiving | I64: 19/1/2024 | J64: KTTC:16/2-23/2/2024 | K64: 23/2/2024 | L64: x
A65: 63 | C65: Bổ sung tài nguyên Stringee Video | D65: BSS | E65: hoangnt14 | F65: vinhtq18 | G65: SR_VN_20240119_992661 | H65: Đã cấp phát xong | I65: 19/1/2024 | J65: KTTC:19/1/-29/1/2024 | K65: 22/1/2024 | L65: x
A66: 64 | C66: cấp phát server thử nghiệm AI Camera cho chuỗi cửa hàng Viettel | D66: GPCNTT | E66: anhtt229 | F66: vinhtq18 | G66: SR_VN_20240131_1003698 | H66: Đã cấp phát xong | I66: 26/1/2024 | J66: KTTC:26/1-2/2/2024 | K66: 45293 | L66: x
A67: 65 | C67: Cấp phát hạ tầng Campaign Management | D67: BSS | E67: giangnt109 | F67: khanhnd23 | G67: SR_VN_20240229_1028368 | H67: Đã cấp phát xong 26/7: huyndn đã cấp phát xong | I67: 29/1/2024 | J67: KTTC:6/3-15/3/2024 | K67: 45476 | L67: x
A68: 66 | C68: Cấp phát tài nguyên DB V-Tracking 2023 | D68: BSS | E68: tamdtt1 | F68: vinhtq18 | G68: SR_VN_20240506_1079517 | H68: soncn2 đang hỏi nốt thông tin kết nối, hạ tầng VTNET đã cấp | I68: 45448 | J68: KTTC: 6/5 - 13/5/2024 | L68: Hủy
A69: 67 | C69: Cấp phát tài nguyên Cloud-CA | D69: BSS | E69: thanhtt69 | F69: thongnv31 | G69: SR_VN_20240320_1038556 | H69: Đã cấp phát xong app, còn phần DB vật lý (chaulm5) | I69: 20/3/2024 | J69: KTTC: 20/3-27/3/2024 VHKT: 11/4-19/4/2024 | K69: 26/4/2024 | L69: x
A70: 68 | C70: Cấp phát tài nguyên hệ thống giám sát prometheus VTT | D70: BSS | E70: hainv71 | F70: vinhtq18 | G70: 458488 | H70: Đã cấp phát xong | I70: 25/3/2024 | J70: 1/4 - 4/4/2024 | K70: 45386 | L70: x
A71: 69 | C71: cấp phát DB hệ thống MySign | D71: BSS | E71: thanhtt69 | F71: khanhnd23 | G71: SR_VN_20240327_1044602 | H71: Đã cấp phát xong | I71: 27/03/2024 | J71: KTTC: 27/3/2024-3/4/2024 VHKT: 11/4-19/4/2024 | K71: 26/4/2024 | L71: x
A72: 70 | C72: Tăng dung lượng Smsbrandname | D72: BSS | E72: anhld55 | F72: vinhtq18 | G72: SR_VN_20240412_1060111 | H72: Đã cấp phát xong | I72: 28/3/2024 | J72: KTTC:11/4-19/4/2024 | K72: 19/4/2024 | L72: x
A73: 71 | C73: Cấp phát tài nguyên Hoá đơn điện tử truyền nhận - stage 2 | D73: BSS | E73: hienlt15 | F73: vinhtq18 | G73: 468949 | H73: VTNET đã cấp 25 server trên tổng số 100 server VM hienlt15 yêu cầu | I73: 45295 | J73: 5/4 - 8/4/2024 | K73: 15/4/2024 | L73: x
A74: 72 | C74: Cấp phát tài nguyên Backup - ATTT | D74: ATTT | E74: duongns | F74: ductn | G74: SR_VN_20240410_1057140 | H74: Cấp phát nóng gấp: đầu mối phongkt | I74: 45569 | L74: x
A75: 73 | C75: Cấp phát tài nguyên hệ thống Nessus - ATTT | D75: ATTT | E75: duongns | F75: ductn | G75: SR_VN_20240410_1057256 | H75: Cấp phát nóng gấp: đầu mối phongkt | I75: 45569 | L75: x
A76: 74 | C76: Cấp phát tài nguyên hệ thống Eprofile | D76: BSS | E76: tiendc | F76: thongnv31 | G76: 478083 | H76: Vtnet từ chối với lý do: Bổ sung luồng dịch vụ đến các svr cần bổ sung; Tài nguyên object lấy ở đâu; Làm rõ sizing từ 300k lên 3 triệu; profile webservice đang có không đẩy sang server FTP chuyển sang đẩy vào server mới thì tại sao cần cấp phát bổ sung thêm; Hủy luồng do cấp phát bằng sr 1109579 số 89 | I76: 45327 | J76: KTTC: 2/5-5/5/2024 Hủy luồng cấp phát | L76: Hủy
A77: 75 | C77: nâng cấu hình Roaming 1 | D77: BSS | E77: soncn2 | F77: vinhtq18 | G77: 490249 | H77: Đã cấp phát xong | I77: 16/4/2024 | J77: KTTC: 9/5-12/5/2024; VHKT: 17/5/2024 | K77: 21/5/2024 | L77: x
A78: 76 | C78: Cấp phát tài nguyên hệ thống VTT Analytic | D78: DAC | E78: anhvt105 | F78: thongnv31 | H78: Vtnet yêu cầu công văn ký từ 2 bên vtt và vtnet để bàn giao acc root và cài lại OS | I78: 02/05/2024 | L78: x
A79: 77 | C79: Cấp phát tài nguyên hệ thống My Viettel recommend & AI system | D79: DAC | E79: longhv15 | F79: thongnv31 | H79: hủy do tài nguyên SAN 2021 không đủ dể cấp phát, lộ trình sẽ được cập nhật sau, đã bổ sung nội dung công việc mới số 86 | L79: Hủy
A80: 78 | C80: Cấp phát tài nguyên Voice To Text | D80: VAS | E80: thangnd21 | F80: vinhtq18 | G80: 502531 | H80: Đã cấp phát xong | I80: 26/4/2024 | J80: KTTC: 23/5-26/5/2024 | K80: 45388 | L80: x
A81: 79 | C81: Cấp phát bổ sung tài nguyên VDA VTT | D81: VAS | E81: ndtho | F81: thongnv31 | G81: SR_VN_20240504_1078614 | H81: 3 svr db: cấp NAS theo SR1079086(VHKT từ chối với lý do bổ sung sizing, PYC), cấp IP NAS theo SR1079066(hoàn thành) Thay đổi HA cho K8s: thu hồi 2 VM theo SR 1079166; cấp phát lại 2 VM theo SR 1079167 (VHKT từ chối với lý do đầu mối kiennt9 không phản hồi yêu cầu thu hồi VM) | I81: 45387 | J81: KTTC:4/5-10/5/2024(hoàn thành) VHKT: 6/5-13/5/2024 Hủy do trung tâm VAS không phản hồi | L81: Hủy
A82: 80 | C82: Cấp phát tài nguyên hệ thống Isign | D82: VAS | E82: ndtho | F82: thongnv31 | G82: 491035 | H82: Đã cấp phát xong | I82: 45540 | J82: 9/5-12/5/2024 | K82: 16/5/2024 | L82: x
A83: 81 | C83: Cấp phát tài nguyên bổ sung Vtracking2.0 | D83: GPCNTT | E83: thiendv1 | F83: khanhnd23 | G83: SR_VN_20240516_1091648 | H83: · Ngày 5/12 đã cấp xong 3VM và quy hoạch lại IP để nâng cấp tiếp 9VM Dự kiến hoàn thành trước 20/12/2024 | I83: 45479 | L83: x
A84: 82 | C84: Cấp phát tài nguyên hệ thống giám sát prometheus VTT (Quy hoạch zone có thể kết nối ra public port 80, 444) | D84: BSS | E84: hainv71 | F84: vinhtq18 | G84: SR_VN_20240628_1130334 | I84: 23/5/2024 | J84: KTTC: 28/6/2024 - 5/7/2024; VHKT: 1/7/2024 - 5/7/2024 | K84: 45298 | L84: x
A85: 83 | C85: Cấp phát thêm mBCCS_v1 | D85: BSS | E85: huylq29 | F85: vinhtq18 | G85: 534599 | I85: 24/5/2024 | J85: KTTC:27/6/2024 - 2/7/2024; VHKT: 1/7 - 4/7/2024 | K85: 45358 | L85: x
A86: 84 | C86: Cấp phát thêm AI_chatbot | D86: BSS | E86: huylq29 | F86: vinhtq18 | G86: 536944 | I86: 24/5/2024 | J86: KTTC:27/6/2024 - 2/7/2024; VHKT: 2/7 - 3/7/2024 | K86: 45389 | L86: x
A87: 85 | C87: Cấp phát tài nguyên hệ thống My viettel recommend & AI system | D87: DAC | E87: longhv15 | F87: thongnv31 | G87: SR_VN_20240531_1104153 | I87: 31/5/2024 | J87: KTTC:31/5/2024 - 7/6/2024 | L87: hủy
A88: 86 | C88: bo sung HDD cho TTONLINE | D88: VAS | E88: thangnd21 | F88: vinhtq18 | G88: SR_VN_20240620_1122498 | I88: 45357 | J88: KTTC:20/6 - 27/6/2024; VHKT: 1/7-8/7/2024 | K88: 45572 | L88: x
A89: 87 | C89: cấp phát tài nguyên cho VESS_HKD | D89: BSS | E89: minhca | F89: vinhtq18 | G89: 518686 | I89: 45388 | J89: KTTC:25/6 - 28/6/2024; VHKT: 27/6 - 9/7/2024 | K89: 26/7/2024 | L89: x
A90: 88 | C90: Cấp phát tài nguyên hệ thống Eprofile | D90: BSS | E90: tiendc | F90: thongnv31 | G90: SR_VN_20240606_1109579 | H90: Hủy do không có tài nguyên s3, VTnet yêu cầu làm rõ thêm thông tin sizing, đang tiến hành làm rõ kế hoạch cấp phát và các thông tin vtnet yêu cầu. | I90: 45449 | J90: KTTC:6/6 - 12/6/2024 Hủy SR này | L90: Hủy
A91: 89 | C91: Bổ sung dung lượng + RAM TTCE | D91: BSS | E91: nghiatn1 | F91: vinhtq18 | G91: SR_VN_20240704_1136625; SR_VN_20240710_1141281 | H91: Đã hoàn thành | I91: 17/6/2024 | J91: KTTC:24/6 - 1/7/2024; VHKT: 10/7 - 16/7/2024 | K91: 22/7/2024 | L91: x
A92: 90 | C92: đề xuất thu hồi tài nguyên dự án Imuzik phase1 để cấp phát tài nguyên nóng gấp triển khai mydio | D92: VAS | E92: hanq1 | F92: khanhnd23 | G92: SR_VN_20240621_1123835 | H92: Đã hoàn thành | I92: 21/6/2024 | J92: KTTC:21/6 - 29/6/2024 | K92: 24/06/2024 | L92: x
A93: 91 | C93: Cấp phát tài nguyên hệ thống My viettel recommend & AI system | D93: DAC | E93: longhv15 | F93: thongnv31 | G93: SR_VN_20240624_1125583 | H93: Đã hoàn thành | I93: 31/5/2024 | J93: KTTC:24/6 - 1/7/2024 VHKT:27/6-4/7/2024 | K93: 45389 | L93: x
A94: 92 | C94: Cấp phát tài nguyên hệ thống Appsealing | D94: ATTT | E94: hungnvx | F94: khanhnd23 | G94: SR_VN_20240625_1126719 | H94: Đã hoàn thành | I94: 25/06/2024 | J94: KTTC:25/6 - 2/7/2024 | K94: 45419 | L94: x
A95: 93 | C95: Cấp phát tài nguyên hệ thống CampaignManagement (ELK + API) | D95: QLCD | E95: vannx3 | F95: ductn | G95: SR_VN_20240905_1191162 SR_VN_20240913_1197869 | H95: Đã hoàn thành | I95: 45421 | J95: VHKT: 05/09 - 13/09 | K95: 4/10/2024 | L95: x
A96: 94 | C96: Cấp phát tài nguyên hệ thống Eprofile (giai đoạn 1) | D96: BSS | E96: tiendc | F96: thongnv31 | G96: SR_VN_20240627_1129447 | H96: Cấp phát giai đoạn 1 (21VM) Đã hoàn thành | I96: 45388 | J96: KTTC:27/6 - 4/7/2024 VHKT:3/7-10/7/2024(reject) VHKT:8/7-15/7/2024 | K96: 45572 | L96: x
A97: 95 | C97: Cấp phát tài nguyên hệ thống TSA | D97: BSS | E97: dungdb1 | F97: ductn | G97: SR_VN_20240708_1139274 | H97: Đã hoàn thành | J97: KTTC:8/7 - 16/7/2024 | K97: 21/08/2024 | L97: x
A98: 96 | C98: Cấp phát tài nguyên Mydio VTT | D98: VAS | E98: hanq1 | F98: vinhtq18 | G98: 538234 | H98: Đã hoàn thành | I98: 45358 | J98: KTTC: 8/7 -10/7/2024 ; VHKT: 17/7 -31/7/2024 | K98: 25/7/2024 | L98: x
A99: 97 | C99: Cấp phát tài nguyên TVBH Meta | D99: BSS | E99: linhnh35 | F99: ductn | G99: SR_VN_20240917_1200114 SR_VN_20241002_1213637 | H99: Đã hoàn thành | K99: 45332 | L99: x
A100: 98 | C100: Thu hồi VM hệ thống Unify Catalog (cụm Cisco_2020_HLC) theo SR_VN_20240719_1149112 | D100: BSS | E100: anhdt156 | F100: khanhnd23 | G100: SR_VN_20240719_1149112; SR_VN_20240719_1149113 | H100: Đã hoàn thành 2 SR: Thu hồi: SR_VN_20240719_1149112 Cấp phát: SR_VN_20240719_1149113 | I100: 26/06/2024 | J100: Vnet báo 31/07 hoàn thành | K100: 31/07//2024 | L100: x
...

Sheet Chi tiết
A1: STT | B1: Dự án | C1: Đơn vị | D1: Đầu mối y/c | E1: Đầu mối P.HT | F1: Mã SR | G1: Quý cấp phát | H1: Số lượng máy chủ | I1: vCPU | J1: Cint | K1: RAM (GB) | L1: SAN (GB) | M1: NAS (GB) | N1: Ceph (GB) | O1: Bigdata (GB) | P1: Archiving (GB) | Q1: S3 Object (GB) | R1: Pool/Nguồn tài nguyên | S1: Nhóm tài nguyên | T1: Ghi chú
A2: 1 | B2: Login_Fail | H2: 3 | I2: 72 | J2: =I2*3 -> 216 | K2: 72 | L2: 23380 | R2: Private Cloud | S2: pc2021 | T2: haipn hiệu chỉnh số liệu
A3: 2 | B3: VCGW | C3: VAS | H3: 3 | I3: 36 | J3: =I3*3 -> 108 | K3: 48 | L3: 1380 | R3: Private Cloud | S3: pc2021 | T3: haipn hiệu chỉnh số liệu
A4: 3 | B4: GSCG-CSKH | C4: DAC | H4: 16 | I4: 716 | J4: =I4*3 -> 2148 | K4: 1024 | L4: 33960 | M4: 21800 | R4: Private Cloud | S4: pc2021 | T4: haipn hiệu chỉnh số liệu
A5: 4 | B5: Callbot Inbound | C5: DAC | H5: 25 | I5: 932 | J5: =I5*3 -> 2796 | K5: 1600 | L5: 51450 | M5: 36800 | R5: Private Cloud | S5: pc2021
A6: 5 | B6: Digidata | C6: BSS | H6: 10 | I6: 120 | J6: =I6*3 -> 360 | K6: 416 | L6: 7900 | R6: Private Cloud | S6: pc2021
A7: 6 | B7: VDA | C7: VAS | H7: 20 | I7: 304 | J7: =I7*3 -> 912 | K7: 848 | L7: 20300 | R7: Private Cloud | S7: pc2021 | T7: pc2021 và pc2023
A8: 7 | B8: VSGW | C8: VAS | H8: 2 | I8: 40 | J8: =I8*3 -> 120 | K8: 32 | L8: 1120 | R8: Private Cloud | S8: pc2021 | T8: haipn hiệu chỉnh số liệu
A9: 8 | B9: SonarQube | C9: BSS | H9: 6 | I9: 126 | J9: =I9*3 -> 378 | K9: 168 | L9: 2660 | R9: Private Cloud | S9: pc2021
A10: 9 | B10: VDA lần 2 | C10: VAS | H10: 40 | I10: 416 | J10: =I10*3 -> 1248 | K10: 1696 | L10: 35300 | R10: Private Cloud | S10: pc2023
A11: 10 | B11: Payment 2.0 | C11: BSS | F11: SR_VN_20220519_580015 | H11: 2 | I11: 40 | J11: =I11*3 -> 120 | K11: 192 | L11: 1120 | R11: Private Cloud | S11: pc2021
A12: 11 | B12: MyCC (VTS) | C12: ĐHBH | D12: phuongphuong | H12: 35 | I12: 1118 | J12: =I12*3 -> 3354 | K12: 1462 | L12: 12890 | M12: 5000 | R12: Private Cloud | S12: pc2021 | T12: chuyển đầu mối về quynhntp@viettel.com.vn
A13: 12 | B13: VRBT | C13: VAS | F13: SR_VN_20220726_615748 | H13: 12 | I13: 208 | J13: =I13*3 -> 624 | K13: 384 | L13: 9920 | M13: 3400 | R13: Private Cloud | S13: pc2021
A14: 13 | B14: Imuzik | C14: BSS | H14: 51 | I14: 744 | J14: =I14*3 -> 2232 | K14: 1936 | L14: 30240 | R14: Private Cloud | S14: pc2021
A15: 14 | B15: mCC | C15: BSS | H15: 4 | I15: 58 | J15: =I15*3 -> 174 | K15: 256 | L15: 1640 | R15: Private Cloud | S15: pc2021
A16: 15 | B16: CSDL Quốc gia | C16: BSS | F16: SR_VN_20220421_567639 | H16: 2 | I16: 64 | J16: =I16*3 -> 192 | K16: 192 | L16: 2220 | R16: Private Cloud | S16: pc2021
A17: 16 | B17: vESS | C17: TTSP | F17: SR_VN_20220211_538486 | G17: Q1/2022 | H17: 33 | I17: 500 | J17: =I17*3 -> 1500 | K17: 1976 | L17: 37650 | R17: Private Cloud | S17: pc2021
A18: 17 | B18: ObserveIT | C18: ATTT | F18: SR_VN_20220228_543700 | G18: Q1/2022 | H18: 2 | I18: 48 | J18: =I18*3 -> 144 | K18: 64 | L18: 11420 | R18: Cloud HLC | S18: san2021
A19: 18 | B19: Nexus CI/CD | C19: SPHT | F19: SR_VN_20220301_544317 | G19: Q1/2022 | H19: 3 | I19: 24 | J19: =I19*3 -> 72 | K19: 48 | L19: 5250 | R19: Cloud HLC | S19: san2021
A20: 19 | B20: VCGW | C20: VAS | F20: SR_VN_20220303_545482 | G20: Q1/2022 | H20: 2 | I20: 50 | J20: =I20*3 -> 150 | K20: 80 | L20: 2200 | R20: Cloud HLC | S20: san2021
A21: 20 | B21: Bố sung dung lưọng DB truyền dẫn HĐDT | C21: BSS | F21: SR_VN_20220310_548839 | G21: Q1/2022 | H21: nâng cấp | J21: =I21*3 -> 0 | K21: 96 | L21: 3600 | R21: Cloud HLC | S21: san2020
A22: 21 | B22: Nhà Nông Xanh | C22: VAS | F22: SR_VN_20220602_586144 | G22: Q1/2022 | H22: 19 | I22: 232 | J22: =I22*3 -> 696 | K22: 192 | N22: 12980 | R22: Cloud HHT | S22: ceph2020
A23: 22 | B23: Scontract | C23: BSS | F23: SR_VN_20210928_467637 | G23: Q1/2022 | H23: 11 | I23: 176 | J23: =I23*3 -> 528 | K23: 360 | N23: 9410 | R23: VTT 2020 | S23: ceph2020
A24: 23 | B24: Bổ sung dung lưọng DB My Viettel | C24: BSS | F24: SR_VN_20220407_562042 | G24: Q2/2022 | H24: nâng cấp | I24: 72 | J24: =I24*3 -> 216 | K24: 288 | L24: 6600 | R24: Cloud HLC | S24: san2021
A25: 24 | B25: Truyền hóa đơn điện tử | C25: BSS | F25: SR_VN_20220603_587186 | G25: Q2/2022 | H25: 19 | I25: =611/3 -> 203.66667 | J25: =I25*3 -> 611 | K25: 4072 | L25: 4699 | R25: VTT 2020 | S25: san2020
A26: 25 | B26: Hóa đơn điện tử 2.0 | C26: BSS | F26: SR_VN_20220127_535611 | G26: Q2/2022 | H26: 8 | I26: =1273/3 -> 424.33333 | J26: =I26*3 -> 1273 | K26: 474 | L26: 3261 | R26: Cloud HLC | S26: san2020
A27: 26 | B27: Websecurity | C27: ATTT | F27: SR_VN_20220223_542435 | G27: Q2/2022 | H27: 8 | I27: 427 | J27: =I27*3 -> 1281 | K27: 1691 | L27: =20000*8 -> 160000 | R27: VTT 2020
A28: 27 | B28: MyViettel | C28: BSS | F28: SR_VN_20220717_611090 | G28: Q2/2022 | H28: 4 | I28: 129 | J28: =I28*3 -> 387 | K28: =90*4 -> 360 | L28: =680*4 -> 2720 | R28: Cloud HLC | S28: san2020
A29: 28 | B29: Cấp phát tài nguyên hệ thống HDĐT GW | C29: BSS | F29: SR_VN_20220530_584894 | G29: Q2/2022 | H29: 20 | I29: 124 | J29: =I29*3 -> 372 | K29: 346 | L29: 2814 | R29: Cloud HLC | S29: san2021
A30: 29 | B30: Cấp phát tài nguyên hệ thống HDĐT Tem vé | C30: BSS | F30: SR_VN_20220603_586882 | G30: Q2/2022 | H30: 111 | I30: 1513 | J30: =I30*3 -> 4539 | K30: =(140+1272)*3 -> 4236 | L30: 105466 | R30: Cloud HLC | S30: san2021
A31: 30 | B31: Nâng cấp truyền nhận HDDT lần 2 | C31: BSS | F31: SR_VN_20220401_559616 | G31: Q2/2022 | H31: nâng cấp | I31: 26 | J31: =I31*3 -> 78 | K31: 72 | L31: 30600 | R31: Cloud HLC | S31: san2020
A32: 31 | B32: Core Game | C32: BSS | F32: SR_VN_20220414_564451 | G32: Q2/2022 | H32: 13 | I32: 56 | J32: =I32*3 -> 168 | K32: 832 | L32: 15600 | R32: Cloud HLC | S32: san2021
A33: 32 | B33: TVBH | C33: BSS | F33: SR_VN_20220316_551065 | G33: Q2/2022 | H33: 13 | I33: 55 | J33: =I33*3 -> 165 | K33: =8*32+3*32+2*16 -> 384 | L33: =8*300+3*300+2*350+800 -> 4800 | R33: Cloud HLC | S33: san2021
A34: 33 | B34: DB TVBH | C34: BSS | F34: SR_VN_20220613_592188 | G34: Q2/2022 | H34: 6 | I34: 60 | J34: =I34*3 -> 180 | K34: =3*32+3*48 -> 240 | L34: =4*4531+4*10354 -> 59540 | R34: Cloud HLC | S34: san2021
A35: 34 | B35: BlockChain | C35: SPHT | F35: SR_VN_20220621_596260 | G35: Q2/2022 | H35: 2 | I35: 10 | J35: =I35*3 -> 30 | K35: 128 | N35: 750 | R35: Cloud HHT | S35: ceph2020
A36: 35 | B36: APIWG | C36: VAS | F36: SR_VN_20220325_556097 | G36: Q2/2022 | H36: 2 | I36: 24 | J36: =I36*3 -> 72 | K36: 434 | L36: 1200 | R36: Cloud HLC | S36: san2020
A37: 37 | B37: Imuzik nhạc chờ | C37: VAS | F37: SR_VN_20220414_564715 | G37: Q2/2022 | H37: 49 | I37: 696 | J37: =I37*3 -> 2088 | K37: 1840 | L37: 27140 | R37: Cloud HLC | S37: san2021
A38: 38 | B38: Vtracking Kafka | C38: BSS | F38: SR_VN_20220707_606245 | G38: Q3/2022 | H38: 4 | I38: =22*4 -> 88 | J38: =I38*3 -> 264 | K38: =44+45+46+47 -> 182 | L38: =4*(537+100) -> 2548 | R38: Cloud HLC | S38: san2020
A39: 39 | B39: BCCS_SALE | C39: BSS | F39: SR_VN_20220725_615131 | G39: Q3/2022 | H39: 10 | I39: 20 | J39: =I39*3 -> 60 | K39: 640 | L39: 3000 | R39: Cloud HLC | S39: san2021
A40: 40 | B40: Nhận diện hình ảnh mBCCS | C40: BSS | F40: SR_VN_20220809_624585 | G40: Q3/2022 | H40: 19 | I40: =46*19 -> 874 | J40: =I40*3 -> 2622 | K40: =64*19 -> 1216 | L40: =120*19 -> 2280 | R40: Cloud HLC | S40: san2021
A41: 41 | B41: Thu hồi vESS | C41: TTSP | F41: SR_VN_20220805_623161 | G41: Q3/2022 | H41: 33 | I41: -500 | J41: =I41*3 -> -1500 | K41: -1976 | L41: -37650 | R41: Private Cloud | S41: pc2021
A42: 42 | B42: DataSponsor | C42: BSS | F42: SR_VN_20220804_622622 | G42: Q3/2022 | K42: =34*3 -> 102 | R42: Cloud HLC | S42: san2020
A43: 43 | B43: Tăng RAM Rating | C43: DAC | F43: SR_VN_20220808_624269 | G43: Q3/2022 | K43: =32*3 -> 96 | R43: Cloud HLC | S43: san2020
A44: 44 | B44: Thu hồi vtracking | C44: SPHT | F44: SR_VN_20220824_632994 | G44: Q3/2022 | H44: 4 | I44: =-(20*2+32*2) -> -104 | J44: =I44*3 -> -312 | K44: =-(64*4) -> -256 | L44: =-(890*4) -> -3560 | R44: Cloud HLC | S44: san2021
A45: 45 | B45: Thu hồi VTFree | C45: BSS | F45: SR_VN_20220824_632999 | G45: Q3/2022 | H45: 6 | I45: =-(6*10) -> -60 | J45: =I45*3 -> -180 | R45: Cloud HLC | S45: san2021
A46: 46 | B46: VBN | C46: BSS | F46: SR_VN_20220909_641619 | G46: Q3/2022 | H46: 11 | I46: =2*16+9*8 -> 104 | J46: =2*48+9*24 -> 312 | K46: =2*32+9*16 -> 208 | L46: =2*610+9*160 -> 2660 | R46: Cloud HLC | S46: san2021
A47: 47 | B47: Thu hồi USSD098 | C47: BSS | F47: SR_VN_20220824_633031 | G47: Q3/2022 | H47: 12 | I47: =-(12*8) -> -96 | J47: =I47*3 -> -288 | R47: Cloud HLC | S47: san2021
A48: 48 | B48: Thu hồi DMS lite | C48: BSS | F48: SR_VN_20220906_639384 | G48: Q3/2022 | H48: 3 | I48: =-12*3 -> -36 | J48: =I48*3 -> -108 | K48: =-70*3 -> -210 | L48: =-460*3 -> -1380 | R48: Cloud HLC | S48: san2021
A49: 49 | B49: Antispam call | C49: BSS | F49: SR_VN_20211231_523676 | G49: Q3/2022 | H49: 19 | I49: =13*6+14*3+10*3 -> 150 | J49: =I49*3 -> 450 | K49: =16*3+64*3+10*3+64*4+16*3+38*3 -> 688 | L49: =1360*3+460*3+260+3+360*10 -> 9323 | R49: Cloud HLC | S49: san2021
A50: 50 | B50: Thu hồi GSCG-CSKH | C50: DAC | F50: SR_VN_20220909_641477 | G50: Q3/2022 | H50: 3 | I50: -58 | J50: =I50*3 -> -174 | R50: Private Cloud | S50: pc2021
A51: 51 | B51: Thu hồi CRM | C51: BSS | F51: SR_VN_20220909_641459 | G51: Q3/2022 | H51: 3 | I51: =-30 -> -30 | J51: =I51*3 -> -90 | R51: Cloud HLC | S51: san2021
A52: 52 | B52: DataSecurity | C52: ATTT | F52: SR_VN_20220928_654161 | G52: Q3/2022 | H52: 2 | I52: 119 | J52: =I52*3 -> 357 | K52: =28.5*2 -> 57 | L52: =153*2+26000 -> 26306 | R52: Cloud HLC | S52: san2021 | T52: 26000GB S3 Storage, trừ vào nguồn tài nguyên Cloud VTT 2021
A53: 53 | B53: CallPlus | C53: VAS | F53: SR_VN_20230112_720915 | G53: Q4/2022 | H53: 2 | I53: 98 | J53: =I53*3 -> 294 | K53: =77*2 -> 154 | L53: 4080 | R53: Cloud HLC | S53: san2021
A54: 54 | B54: AutoSMS | C54: VAS | F54: SR_VN_20221017_664463 | G54: Q4/2022 | H54: 2 | I54: =24*2 -> 48 | J54: =I54*3 -> 144 | K54: =26*2 -> 52 | L54: =671*2+402 -> 1744 | R54: Cloud HLC | S54: san2021
A55: 55 | B55: Thu hồi QLDT | C55: BSS | F55: SR_VN_20221017_664559 | G55: Q4/2022 | H55: 5 | I55: =-(8*3+15+12) -> -51 | J55: =I55*3 -> -153 | K55: =-(48+64) -> -112 | L55: =-(1360+650) -> -2010 | R55: VTT 2020 | S55: san2020
A56: 56 | B56: Ứng ngày tự động | C56: VAS | F56: SR_VN_20221020_666905 | G56: Q4/2022 | H56: 2 | I56: 48 | J56: =I56*3 -> 144 | K56: 48 | L56: =192*2+49*2 -> 482 | R56: Cloud HLC | S56: san2021
A57: 57 | B57: USSD800 | C57: VAS | F57: SR_VN_20221020_666944 | G57: Q4/2022 | H57: 2 | I57: 48 | J57: =I57*3 -> 144 | K57: 48 | L57: =204*2+92*2 -> 592 | R57: Cloud HLC | S57: san2021
A58: 58 | B58: Bổ sung dung lượng Voice Brandname | C58: BSS | F58: SR_VN_20221026_669750 | G58: Q4/2022 | L58: 100 | R58: Cloud HLC | S58: 2019
A59: 59 | B59: Call Me Back | C59: VAS | F59: SR_VN_20221031_672709 | G59: Q4/2022 | H59: 2 | I59: 23 | J59: =I59*3 -> 69 | K59: =24*2 -> 48 | L59: =200*2 -> 400 | R59: Cloud HLC | S59: san2021
A60: 60 | B60: Thu hồi XHHBH | C60: BSS | F60: SR_VN_20221108_676928 | G60: Q4/2022 | H60: 4 | I60: -24 | R60: VTT 2020 | S60: san2020
A61: 61 | B61: Thu hồi CCAI | C61: DAC | F61: SR_VN_20221116_682232 | G61: Q4/2022 | H61: 12 | I61: -90 | J61: -270 | R61: Cloud HLC | S61: san2021
A62: 62 | B62: Nâng cấp cụm DB của HDDT | C62: BSS | F62: SR_VN_20221027_671175 | G62: Q4/2022 | H62: 12 | I62: 0 | J62: 0 | K62: =64*12 -> 768 | L62: 0 | R62: Cloud HLC | S62: san2021
A63: 63 | B63: Nâng cấp hệ thống Data | C63: BSS | F63: SR_VN_20221111_679619 | G63: Q4/2022 | H63: 13 | I63: 260 | J63: =I63*3 -> 780 | K63: 816 | L63: 48000 | R63: Cloud HLC | S63: san2021
A64: 64 | B64: Thu hồi 3 DB TVBH | C64: BSS | F64: SR_VN_20221031_672855 | G64: Q4/2022 | H64: 3
A65: 65 | B65: Cấp bổ sung TN 3 DB TVBH | C65: BSS | F65: SR_VN_20221031_672855 | G65: Q4/2022 | H65: 3
A66: 66 | B66: vBHXH | C66: BSS | F66: SR_VN_20221122_685580 | G66: Q4/2022 | H66: 5 | M66: 5693 | R66: Cloud HLC | S66: san2021 | T66: Cấp tài nguyên trên hạ tầng 2019, Bù trừ vào hạ tầng 2021
A67: 67 | B67: Thu hồi vtfree | C67: BSS | F67: SR_VN_20221117_683046 | G67: Q4/2022 | H67: 6 | I67: -60 | J67: =I67*3 -> -180 | R67: Cloud HLC | S67: san2021
A68: 68 | B68: GBOC | C68: DAC | F68: SR_VN_20221130_690673 | G68: Q4/2022 | H68: 27 | I68: 300 | J68: =I68*3 -> 900 | K68: 1452 | L68: 35875 | R68: Cloud HLC | S68: san2021
A69: 69 | B69: Dự án SmartWatch Goly | C69: BSS | F69: SR_VN_20221216_701066 | G69: Q4/2022 | H69: 10 | I69: 112 | J69: =I69*3 -> 336 | K69: 224 | L69: 2060 | R69: Private Cloud | S69: pc2021
A70: 70 | B70: Dự án Unify Catalog | C70: BSS | F70: SR_VN_20230113_721674 | G70: Q1/2023 | H70: 28 | I70: 666 | J70: =I70*3 -> 1998 | K70: 1336 | L70: 38280 | R70: Cloud HLC | S70: san2021
A71: 71 | B71: Data | C71: BSS | F71: SR_VN_20230201_731146 | G71: Q1/2023 | H71: 3 | I71: 72 | J71: =I71*3 -> 216 | K71: =48*3 -> 144 | L71: 1500 | R71: Cloud HLC | S71: san2021 | T71: Cấp tài nguyên lớn hơn KH đã ký 8TB storage
A72: 72 | B72: Jira | C72: BSS | F72: =INDEX('Cấp phát TN'!C1:G1048575,MATCH(B72,'Cấp phát TN'!C1:C1048575,0),2) -> BSS | G72: Q1/2023 | H72: 4 | I72: =16*2+24*2 -> 80 | J72: =I72*3 -> 240 | K72: =16*2+32*2 -> 96 | L72: 1340 | M72: =350*2+200*2+1200 -> 2300 | R72: Private Cloud | S72: pc2021
A73: 73 | B73: Smart Motor | C73: BSS | F73: SR_VN_20230131_730256 | G73: Q1/2023 | H73: 19 | I73: 210 | J73: 630 | K73: 678 | L73: 37920 | T73: haipn hiệu chỉnh, ko có trên Cloud VTT
A74: 74 | B74: Thu hồi imuzik | C74: VAS | F74: SR_VN_20230131_730197 | G74: Q1/2023 | H74: 49 | I74: -696 | J74: =I74*3 -> -2088 | K74: -1840 | L74: -27140 | R74: Cloud HLC | S74: san2021
A75: 75 | B75: Myclip | C75: VAS | F75: SR_VN_20230202_731505 | G75: Q1/2023 | H75: 42 | I75: =8*18+4*6+8*3+24*3*5 -> 552 | J75: =I75*3 -> 1656 | K75: =16*18+8*6+24*3+24*3+25*3+24*3+63*3+31*3 -> 909 | L75: =220*18+260*6+260*3+300*3+300*3+300*3+920*3+300*3+300 -> 12960 | R75: Cloud HLC | S75: san2021
A76: 76 | B76: Survey | C76: BSS | F76: SR_VN_20230203_732524 | G76: Q1/2023 | H76: 25 | I76: 176 | J76: =I76*3 -> 528 | K76: 360 | L76: 5840 | R76: Cloud HLC | S76: san2021
A77: 77 | B77: Adhoc | C77: DAC | F77: SR_VN_20230217_740841 | G77: Q1/2023 | H77: 9 | I77: =24*3+6*8 -> 120 | J77: =I77*3 -> 360 | K77: =76*3+52*6 -> 540 | L77: =700*6+4200+2700*2 -> 13800 | R77: Cloud HLC | S77: san2021
A78: 78 | B78: C360 | C78: DAC | F78: =INDEX('Cấp phát TN'!C1:G1048575,MATCH(B78,'Cấp phát TN'!C1:C1048575,0),2) -> DAC | G78: Q1/2023 | H78: 5 | I78: =24*3+16 -> 88 | J78: =I78*3 -> 264 | K78: =24*3+44*2 -> 160 | L78: =3300+2000*2+550*2 -> 8400 | R78: Cloud HLC | S78: san2021
A79: 79 | B79: Redis -mBCCS | C79: BSS | F79: SR_VN_20230223_743535 | G79: Q1/2023 | H79: 12 | I79: =12*12 -> 144 | J79: =I79*3 -> 432 | K79: =52*12 -> 624 | L79: =314*12 -> 3768 | R79: Cloud HLC | S79: san2021
A80: 80 | B80: Cấp bổ sung dung lượng Vtracking Kafka | C80: BSS | F80: SR_VN_20230223_743574 | G80: Q1/2023 | H80: 3 | L80: 600 | R80: Cloud HLC | S80: san2021
A81: 81 | B81: mycc | C81: VAS | I81: 1118 | J81: =I81*3 -> 3354 | K81: 1462 | L81: 9860 | T81: Đã cấp phát server nhưng chưa có tải
A82: 82 | B82: Antispam | C82: BSS | I82: 702 | J82: 2321 | T82: Đã cấp phát server nhưng chưa có tải
A83: 83 | B83: QLHS | C83: BSS | F83: SR_VN_20230330_763915 | G83: Q1/2023 | H83: 5 | I83: =8*5 -> 40 | J83: =I83*3 -> 120 | K83: =55*5 -> 275 | L83: =192*5 -> 960 | R83: Cloud HLC | S83: san2021 | T83: Chi Ao Hoa
A84: 84 | B84: NDHA | C84: BSS | F84: SR_VN_20230331_764416 | G84: Q1/2023 | H84: 20 | I84: =32*20 -> 640 | J84: =I84*3 -> 1920 | K84: =32*20 -> 640 | L84: =280*20 -> 5600 | R84: Private Cloud | S84: pc2021
A85: 85 | B85: NDHA bổ sung | C85: BSS | F85: SR_VN_20230331_764617 | G85: Q1/2023 | H85: 13 | I85: =32*13 -> 416 | J85: =I85*3 -> 1248 | K85: =32*13 -> 416 | L85: =280*13 -> 3640 | R85: Private Cloud | S85: pc2021
A86: 86 | B86: Thu hồi digitata | C86: BSS | G86: Q1/2023 | H86: 10 | I86: -120 | J86: =I86*3 -> -360 | K86: -416 | L86: -7900 | R86: Private Cloud | S86: pc2021 | T86: Thu hoi cap cho NDHA
A87: 87 | B87: Thu hồi tài nguyên Survey 2.0 | C87: =VLOOKUP(B87,'Cấp phát TN'!C1:G1048575,2,FALSE) -> BSS | D87: =VLOOKUP(B87,'Cấp phát TN'!C1:G1048575,3,FALSE) -> 0 | E87: =VLOOKUP(B87,'Cấp phát TN'!C1:G1048575,4,FALSE) -> hieuhv13 | F87: =VLOOKUP(B87,'Cấp phát TN'!C1:G1048575,5,FALSE) -> SR_VN_20230426_780377 | G87: Q1/2023 | H87: 25 | I87: -176 | J87: =I87*3 -> -528 | K87: -360 | L87: -5840 | R87: Cloud HLC | S87: san2021 | T87: Note only
A88: 88 | B88: Điều chỉnh tài nguyên Survey 2.0 | C88: =VLOOKUP(B88,'Cấp phát TN'!C1:G1048575,2,FALSE) -> BSS | D88: =VLOOKUP(B88,'Cấp phát TN'!C1:G1048575,3,FALSE) -> 0 | E88: =VLOOKUP(B88,'Cấp phát TN'!C1:G1048575,4,FALSE) -> hieuhv13 | F88: =VLOOKUP(B88,'Cấp phát TN'!C1:G1048575,5,FALSE) -> SR_VN_20230419_775285 SR_VN_20230425_779549 | G88: Q2/2023 | H88: 17 | I88: 220 | J88: =220*3 -> 660 | K88: 592 | L88: =60*17+8*160+6*200+920*3+500*3+600 -> 8360 | R88: Cloud HLC | S88: san2021
A89: 89 | B89: Thu hồi tài nguyên Survey 2.0 | C89: =VLOOKUP(B89,'Cấp phát TN'!C1:G1048575,2,FALSE) -> BSS | D89: =VLOOKUP(B89,'Cấp phát TN'!C1:G1048575,3,FALSE) -> 0 | E89: =VLOOKUP(B89,'Cấp phát TN'!C1:G1048575,4,FALSE) -> hieuhv13 | F89: =VLOOKUP(B89,'Cấp phát TN'!C1:G1048575,5,FALSE) -> SR_VN_20230426_780377 | G89: Q2/2023 | H89: 8 | I89: -44 | J89: =-44*3 -> -132 | K89: -96 | L89: =-8*60-3*160-5*200-100 -> -2060 | R89: Cloud HLC | S89: san2021
A90: 90 | B90: Cấp phát tài nguyên cho MBS | C90: =VLOOKUP(B90,'Cấp phát TN'!C1:G1048575,2,FALSE) -> BSS | D90: =VLOOKUP(B90,'Cấp phát TN'!C1:G1048575,3,FALSE) -> 0 | E90: =VLOOKUP(B90,'Cấp phát TN'!C1:G1048575,4,FALSE) -> vinhtq18 | F90: =VLOOKUP(B90,'Cấp phát TN'!C1:G1048575,5,FALSE) -> SR_VN_20230480_776480 | G90: Q2/2023 | H90: 4 | I90: =4*4 -> 16 | J90: =16*3 -> 48 | K90: =2*8+4*2 -> 24 | L90: =(60+0.5+16+15+20+312+312)*2+(60+0.5+16+15+20+8+8)*2 -> 1726 | R90: Cloud HLC | S90: san2021
A91: 91 | B91: Cấp phát tài nguyên CCAI | C91: =VLOOKUP(B91,'Cấp phát TN'!C1:G1048575,2,FALSE) -> DAC | D91: =VLOOKUP(B91,'Cấp phát TN'!C1:G1048575,3,FALSE) -> 0 | E91: =VLOOKUP(B91,'Cấp phát TN'!C1:G1048575,4,FALSE) -> hieuhv13 | F91: =VLOOKUP(B91,'Cấp phát TN'!C1:G1048575,5,FALSE) -> SR_VN_20230419_775606 | G91: Q1/2023 | H91: 9 | I91: =17*3+22*3+24*3 -> 189 | J91: =I91*3 -> 567 | K91: =64*3+70*3+68*3 -> 606 | L91: =((60+900+100)*3+(60+3*1024)*3+3*(60+1024+100+1024)) -> 19200 | M91: =500+1.5*1024+500 -> 2536 | R91: Cloud HLC | S91: san2021 | T91: Nếu tính cả DB chưa cấp thì storage =45,2T
A92: 92 | B92: Thu hồi tài nguyên NDHA chuẩn bị cho điều chuyển HT Campaign | C92: =VLOOKUP(B92,'Cấp phát TN'!C1:G1048575,2,FALSE) -> #N/A | D92: =VLOOKUP(B92,'Cấp phát TN'!C1:G1048575,3,FALSE) -> #N/A | E92: =VLOOKUP(B92,'Cấp phát TN'!C1:G1048575,4,FALSE) -> #N/A | F92: =VLOOKUP(B92,'Cấp phát TN'!C1:G1048575,5,FALSE) -> #N/A | G92: Q2/2023 | H92: 33 | I92: =-33*32 -> -1056 | J92: =I92*3 -> -3168 | K92: =-33*32 -> -1056 | L92: =-(60+220)*33 -> -9240 | R92: Private Cloud | S92: pc2021 | T92: Thu hồi tài nguyên NDHA chuẩn bị cho điều chuyển HT Campaign
A93: 93 | B93: Bổ sung tài nguyên cho hệ thống data3G | C93: =VLOOKUP(B93,'Cấp phát TN'!C1:G1048575,2,FALSE) -> VTN | D93: =VLOOKUP(B93,'Cấp phát TN'!C1:G1048575,3,FALSE) -> sonnh30 | E93: =VLOOKUP(B93,'Cấp phát TN'!C1:G1048575,4,FALSE) -> 0 | F93: =VLOOKUP(B93,'Cấp phát TN'!C1:G1048575,5,FALSE) -> KTTC: SR_VN_20230320_756800 | G93: Q2/2023 | H93: 6 | I93: =34*H93 -> 204 | J93: =I93*3 -> 612 | K93: =79*H93 -> 474 | L93: =400*H93 -> 2400 | T93: Theo dõi, ko tham gia trực tiếp
A94: 94 | B94: APIGW | C94: =VLOOKUP(B94,'Cấp phát TN'!C1:G1048575,2,FALSE) -> DAC | D94: =VLOOKUP(B94,'Cấp phát TN'!C1:G1048575,3,FALSE) -> anhnt576 | E94: =VLOOKUP(B94,'Cấp phát TN'!C1:G1048575,4,FALSE) -> Hoangld2 | F94: =VLOOKUP(B94,'Cấp phát TN'!C1:G1048575,5,FALSE) -> KTTC: SR_VN_20230705_826658 VHKT: SR_VN_20230710_830025 | G94: Q2/2023 | H94: 5 | I94: =119*H94 -> 595 | J94: =I94*3 -> 1785 | K94: =96*$H$94 -> 480 | L94: =8060*$H$94 -> 40300 | R94: Cloud KV2 | S94: san2021
A95: 95 | B95: Voice brand name | C95: =VLOOKUP(B95,'Cấp phát TN'!C1:G1048575,2,FALSE) -> BSS | D95: =VLOOKUP(B95,'Cấp phát TN'!C1:G1048575,3,FALSE) -> tuyenpv9 | E95: =VLOOKUP(B95,'Cấp phát TN'!C1:G1048575,4,FALSE) -> Hoangld2 | F95: =VLOOKUP(B95,'Cấp phát TN'!C1:G1048575,5,FALSE) -> SR_VN_20230602_803532 | G95: Q2/2023 | H95: 2 | I95: =ROUND(J95/3,0) -> 65 | J95: =97*2 -> 194 | K95: =49*$H95 -> 98 | L95: =1125+802 -> 1927 | R95: Cloud HLC | S95: san2021 | T95: Phát sinh để bàn giao VTN
A96: 96 | B96: Hệ thống TMS VHT | C96: =VLOOKUP(B96,'Cấp phát TN'!C1:G1048575,2,FALSE) -> BSS | D96: =VLOOKUP(B96,'Cấp phát TN'!C1:G1048575,3,FALSE) -> tiendd tuanna29 | E96: =VLOOKUP(B96,'Cấp phát TN'!C1:G1048575,4,FALSE) -> hieuhv13 | F96: =VLOOKUP(B96,'Cấp phát TN'!C1:G1048575,5,FALSE) -> VHKT: SR_VN_20230711_831000 | G96: Q2/2023 | H96: 10 | I96: =25*2+23*2+26*2+13*2+20*2 -> 214 | J96: =I96*3 -> 642 | K96: =29*2+49*2+63*2+12*2+64*2 -> 434 | L96: =400*2+1.2*1020*2+80*2+232*2+220*2+250*2 -> 4812 | R96: Cloud HLC | S96: san2021
A97: 97 | B97: Bổ sung disk dự án HDDT | C97: =VLOOKUP(B97,'Cấp phát TN'!C1:G1048575,2,FALSE) -> BSS | D97: =VLOOKUP(B97,'Cấp phát TN'!C1:G1048575,3,FALSE) -> hainv71 | E97: =VLOOKUP(B97,'Cấp phát TN'!C1:G1048575,4,FALSE) -> hieuhv13 | F97: =VLOOKUP(B97,'Cấp phát TN'!C1:G1048575,5,FALSE) -> SR_VN_20230630_823903 | G97: Q2/2023 | H97: 15 | L97: 28395 | R97: Cloud HLC | S97: san2021
A98: 98 | B98: Cấp phát tài nguyên NAS dự án HDDT | C98: =VLOOKUP(B98,'Cấp phát TN'!C1:G1048575,2,FALSE) -> BSS | D98: =VLOOKUP(B98,'Cấp phát TN'!C1:G1048575,3,FALSE) -> hainv71 | E98: =VLOOKUP(B98,'Cấp phát TN'!C1:G1048575,4,FALSE) -> hieuhv13 | F98: =VLOOKUP(B98,'Cấp phát TN'!C1:G1048575,5,FALSE) -> SR_VN_20230620_815799 | G98: Q2/2023 | H98: 7 | M98: 5364 | R98: Cloud HLC | S98: san2021
A99: 99 | B99: Hợp đồng điện tử | C99: =VLOOKUP(B99,'Cấp phát TN'!C1:G1048575,2,FALSE) -> BSS | D99: =VLOOKUP(B99,'Cấp phát TN'!C1:G1048575,3,FALSE) -> dattht | E99: =VLOOKUP(B99,'Cấp phát TN'!C1:G1048575,4,FALSE) -> Hoangld2 | F99: =VLOOKUP(B99,'Cấp phát TN'!C1:G1048575,5,FALSE) -> SR_VN_20230623_818696 | G99: Q2/2023 | H99: 15 | I99: 153 | J99: =I99*3 -> 459 | K99: 345 | L99: 2400 | R99: Cloud HLC | S99: san2021 | T99: Phát sinh ngoài KH
A100: 100 | B100: Bổ sung tài nguyên cho hệ thống data3G-lần 2 | C100: =VLOOKUP(B100,'Cấp phát TN'!C1:G1048575,2,FALSE) -> BSS | D100: =VLOOKUP(B100,'Cấp phát TN'!C1:G1048575,3,FALSE) -> 0 | E100: =VLOOKUP(B100,'Cấp phát TN'!C1:G1048575,4,FALSE) -> None | F100: =VLOOKUP(B100,'Cấp phát TN'!C1:G1048575,5,FALSE) -> SR_VN_20230705_826839 | G100: Q3/2023 | H100: 12 | I100: =J100/3 -> 228 | J100: 684 | K100: 768 | L100: =1500*12 -> 18000 | R100: Cloud HLC | S100: san2021
...

Sheet Tài nguyên Cloud 
A1: Tài nguyên QHĐC 2020
B2: Hiên trạng tài nguyên còn dư | K2: Ghi chú
B3: vCPU | D3: RAM (TB) | F3: CEPH (GB) | G3: SAN (GB) | H3: NAS (GB)
B4: Com_Ceph | C4: Com_SAN | D4: Com_Ceph | E4: Com_SAN
A5: TN còn lại sau KH Q4 | B5: 5383.8 | C5: -4064.5714 | D5: 8815 | E5: 4065 | F5: -40790 | G5: 10332 | H5: -33800
A6: TN trong KH Q4 | B6: 1470 | C6: 1984.5714 | D6: 4.453 | E6: 5204 | F6: 84910 | G6: 131925 | H6: 8000
A7: TN đã sử dụng trong Q4 | B7: 831 | C7: 808.57143 | D7: 3459 | E7: 2546 | F7: 19400 | G7: 100291 | H7: 4000
A8: TN còn lại 2021 | B8: 6022.8 | C8: -2888.5714 | D8: 5360.453 | E8: 6723 | F8: 24720 | G8: 41966 | H8: -29800
A9: Sử dụng 2022 | B9: ='Chi tiết'!$I$259 -> 418 | C9: ='Chi tiết'!$I$260 -> 820 | D9: ='Chi tiết'!$K$259 -> 680 | E9: ='Chi tiết'!$K$260 -> 5776 | F9: ='Chi tiết'!N259 -> 23140 | G9: ='Chi tiết'!$L$260 -> 46618
A10: TN còn lại | B10: =B8-B9 -> 5604.8 | C10: =C8-C9 -> -3708.5714 | D10: =D8-D9 -> 4680.453 | E10: =E8-E9 -> 947 | F10: =F8-F9 -> 1580 | G10: =G8-G9 -> -4652 | H10: =H8-H9 -> -29800
A11: Private Cloud
B12: Hiên trạng tài nguyên còn dư | K12: Ghi chú
B13: vCPU | D13: RAM (GB) | F13: CEPH (GB) | G13: SAN (GB) | H13: NAS (GB) | I13: NAS (theo đầu mối VHKT gửi tháng 3 2025)
B14: Com_Ceph | C14: Com_SAN | D14: Com_Ceph | E14: Com_SAN
A15: Tổng TN 2021 | C15: =3264*4 -> 13056 | E15: =32*384-40 -> 12248 | G15: =612000*0.9 -> 550800 | H15: =125000*0.9 -> 112500 | I15: 109 | K15: vCPU overcomit 1:4
A16: Đã cấp phát 2021 | C16: ='Chi tiết'!$I$265 -> 4490 | E16: ='Chi tiết'!$K$265 -> 7829 | G16: ='Chi tiết'!$L$265 -> 287409 | H16: ='Chi tiết'!M265 -> 105300 | I16: 65.82
A17: TN còn lại 2021 | C17: =C15-C16 -> 8566 | E17: =E15-E16 -> 4419 | G17: =G15-G16 -> 263391 | H17: =H15-H16 -> 7200 | I17: =I15-I16 -> 43.18
A18: Tổng TN 2023 | C18: =4608*4 -> 18432 | E18: 14761 | G18: =175*2*1024*0.9 -> 322560 | H18: =50*1024*0.9 -> 46080 | I18: 50
A19: Đã cấp phát 2023 | C19: ='Chi tiết'!$I$266 -> 4979 | E19: ='Chi tiết'!$K$266 -> 12363 | G19: ='Chi tiết'!$L$266 -> 305419 | H19: ='Chi tiết'!$M$266 -> 18477 | I19: 37.96
A20: TN còn lại 2023 | C20: =C18-C19 -> 13453 | E20: =E18-E19 -> 2398 | G20: =G18-G19 -> 17141 | H20: =H18-H19 -> 27603 | I20: =I18-I19 -> 12.04
A21: Tài nguyên QHĐC 2021
B22: Hiên trạng tài nguyên còn dư | K22: Ghi chú
B23: vCPU | D23: RAM (GB) | F23: CEPH (GB) | G23: SAN (GB) | H23: NAS (GB)
B24: Com_Ceph | C24: Com_SAN | D24: Com_Ceph | E24: Com_SAN
A25: Tổng TN | B25: 689 | C25: =25280-B25 -> 24591 | D25: 1984 | E25: =37545-D25 -> 35561 | F25: 34992 | G25: =1052643-F25 -> 1017651 | H25: 106576 | K25: overcomit 1:2 ( sử dụng server 5-2, 5-1 và 6-2 để dựng cloud )
A26: Đã cấp phát | B26: ='Chi tiết'!I261 -> 0 | C26: ='Chi tiết'!$I$262 -> 10330.13 | D26: ='Chi tiết'!K261 -> 0 | E26: ='Chi tiết'!$K$262 -> 32254 | F26: ='Chi tiết'!N261 -> 10834 | G26: ='Chi tiết'!$L$262 -> 1031612 | H26: ='Chi tiết'!M262 -> 144340
A27: TN còn lại | B27: =B25-B26 -> 689 | C27: =C25-C26 -> 14260.87 | D27: =D25-D26 -> 1984 | E27: =E25-E26 -> 3307 | F27: =F25-F26 -> 24158 | G27: =G25-G26 -> -13961 | H27: =H25-H26 -> -37764
A28: Tài nguyên QHĐC 2022
A29: Hiên trạng tài nguyên còn dư
B30: Com_Ceph | D30: CEPH (GB) | E30: Com_SAN | G30: SAN (GB) | H30: NAS (GB) | I30: Object (GB) | J30: Com_Bigdata | L30: Bigdata (GB) | M30: Archiving (GB) | N30: Bare_metal
B31: vCPU | C31: RAM | E31: vCPU | F31: RAM | J31: vCPU | K31: RAM | N31: vCPU | O31: RAM
A32: Tổng TN | B32: ='DA2022'!Q6*96*0.9 -> 5184 | C32: ='DA2022'!Q6*384*0.75 -> 17280 | D32: =('DA2022'!E12*80+'DA2022'!E12*22)*1024 -> 1880064 | E32: =('DA2022'!J4+'DA2022'!H4)*96*0.9 -> 36720 | F32: =('DA2022'!H4+'DA2022'!J4)*384*0.75 -> 122400 | G32: =('DA2022'!H15*'DA2022'!I53+'DA2022'!H15*'DA2022'!J53+'DA2022'!I15*'DA2022'!I54+'DA2022'!I15*'DA2022'!J54)*1024 -> 6872064 | H32: ='DA2022'!E17*1024 -> 773314.56 | I32: =5500*1024 -> 5632000 | J32: ='vật lý free'!N27+'vật lý free'!N28 -> 20640 | K32: ='vật lý free'!O27+'vật lý free'!O28 -> 79744 | L32: 1179197.4 | M32: 1100001.3 | N32: =SUM('vật lý free'!N22:N26) -> 20064 | O32: =SUM('vật lý free'!O22:O26) -> 56576
A33: Đã cấp phát | B33: ='Chi tiết'!I263 -> 0 | C33: ='Chi tiết'!K263 -> 0 | D33: ='Chi tiết'!L263 -> 0 | E33: ='Chi tiết'!I264 -> 13974 | F33: ='Chi tiết'!K264 -> 31456.2 | G33: ='Chi tiết'!L264+'Cấp phát vật lý'!T22 -> 1150242 | H33: ='Chi tiết'!M264 -> 238396 | I33: ='Chi tiết'!Q264 -> 20490 | J33: ='vật lý free'!P28+'vật lý free'!P27 -> 0 | K33: ='vật lý free'!Q28+'vật lý free'!Q27 -> 0 | L33: ='Cấp phát vật lý'!T23 -> 0 | M33: ='Cấp phát vật lý'!T24 -> 0 | N33: =SUM('vật lý free'!P22:P26) -> 7104 | O33: =SUM('vật lý free'!Q22:Q26) -> 19456
A34: TN còn lại | B34: =B32-B33 -> 5184 | C34: =C32-C33 -> 17280 | D34: =D32-D33 -> 1880064 | E34: =E32-E33 -> 22746 | F34: =F32-F33 -> 90943.8 | G34: =G32-G33 -> 5721822 | H34: =H32-H33 -> 534918.56 | I34: =I32-I33 -> 5611510 | ... O34: =O32-O33 -> 37120

Sheet vật lý free
A1: Lô tài nguyên | B1: Mã | C1: Loại | D1: CPU | E1: RAM | F1: Disk | G1: Bigdata | H1: Archiving | I1: HBA | J1: GPU | K1: Tổng | L1: Ghi chú | M1: Đã cấp | N1: VTNet cấp phát
A2: 0405 IDC | B2: SV 1 | C2: - 2xXeon Gold 6252 6x64GB RAM 2x600HDD HBA Card RAID 2 NIC | D2: Gold 6252 | E2: 384 | F2: HDD: 2x600GB | I2: Y | K2: 7 | L2: Đang lắp 2 rack cùng hạ tầng Private Cloud
A3: 0405 IDC | B3: SV 2 | C3: - 2xXeon Bronze 3206R RAM: 4x32GB HDD: 2x600GB HBA Card RAID 2 NIC | D3: Bronze 3206R | E3: 128 | F3: HDD: 2x600GB | I3: Y | K3: 3 | L3: Đang lắp 2 rack cùng hạ tầng Private Cloud
A4: 0405 IDC | B4: SV 3 | C4: - 2xXeon Bronze 3206R RAM: 4x32GB HDD1: 2x600GB SAS HDD2: 3x2 TB SATA HDD3: 2x3.84 TB SSD HBA Card RAID 2 NIC | D4: Bronze 3206R | E4: 128 | F4: HDD1: 2x600GB SAS HDD2: 3x2 TB SATA SSD: 2x3.84 TB | I4: Y | K4: 3 | L4: Đang lắp 2 rack cùng hạ tầng Private Cloud
A5: Private cloud | B5: sv node 2 | C5: HPE DL380 Gen10 (CPU: 2 x Xeon Silver 4214R; RAM: 256GB, SSD: 2x480GB, 2 HBA 16Gbps) | D5: Silver 4214R | E5: 256 | F5: SSD: 2x480GB | I5: Y | K5: 4
A6: QHĐC 2020 | B6: SV4-1 | C6: Server HPE Apollo R2600 - | D6: Silver 4214R | E6: 128 | F6: SSD: 2 x 1.92 TB | K6: 1
C7: XL170r Gen10 (2 x Xeon Silver 4214R; RAM: 128GB, SSD: 2 x 1.92 TB)
A8: QHĐC 2020 | B8: SV4-5 | C8: DL360 Gen10 (CPU: 2 x Xeon Silver 4214R; RAM: 256GB, SSD: 2x1.92 TB) | D8: Silver 4214R | E8: 256 | F8: SSD: 2x1.92 TB | K8: 5
A9: QHĐC 2020 | B9: SV 5-1 | C9: DL360 Gen10 (CPU: 2 x Xeon Gold 5218R; RAM: 384GB, SSD: 2x600 GB) | D9: Gold 5218R | E9: 384 | F9: SSD: 2x600 GB | K9: 3
A10: Bigdata 2021 | B10: SV 5-4 | C10: 2x Gold 5318Y, 256GB RAM, SSD: 2 x 960G | D10: Gold 5318Y | E10: 256 | F10: SSD: 2 x 960G | G10: 365,000 | K10: 31 | L10: Quy hoạch cho Campaign (anhdt156) | M10: 31
A11: Bigdata 2021 | B11: SV 5-4 | C11: 2x Gold 5318Y, 256GB RAM, SSD: 2 x 960G | D11: Gold 5318Y | E11: 256 | F11: SSD: 2 x 960G | G11: 627,000 | H11: 1,035,000 | K11: 52 | L11: Quy hoạch Cus360 48, Adhoc 4 (sonln3) | M11: 28 | N11: huyndn cấp 25/6/2024, 4 sv adhoc, 20 sv cus360
A12: Bigdata 2021 | B12: SV 5-4 | C12: 2x Gold 5318Y, 256GB RAM, SSD: 2 x 960G | D12: Gold 5318Y | E12: 256 | F12: SSD: 2 x 960G | G12: 509,800 | K12: 25 | L12: Quy hoạch CCAI 6, Analytic 19 (dungha7) | M12: 25 | N12: huyndn cấp 24/6/2024, 19 sv analytic
A13: Bigdata 2021 | B13: SV 5-4 | C13: 2x Gold 5318Y, 256GB RAM, SSD: 2 x 960G | D13: Gold 5318Y | E13: 256 | F13: SSD: 2 x 960G | G13: 10,240 | K13: 6 | L13: Quy hoạch Billing (dungpt16) | M13: 6 | N13: huyndn cấp 24/6/2024, 6 sv billing
A14: VTM bàn giao 2689/BB-CNTT | B14: SV13 Cloud | C14: PowerEdge R750: 2 x Intel Xeon Silver 4314 2.4G, 4x32GB RAM, 8x3.84TB SSD SAS; 2x600GB SAS | D14: Silver 4314 | E14: 128 | F14: 8x3.84TB SSD SAS; 2x600GB SAS | I14: Y | K14: 15 | L14: Cty Truyền thông Viettel (đầu mối ThườngLX) bàn giao 30 sv cho TT.PTDL theo CV 2689/BB-CNTT ngày 31/7/2023 | M14: 15
A15: VTM bàn giao 2689/BB-CNTT | B15: SV12 Cloud | C15: PowerEdge R750: 2 xIntel Xeon Gold 6326 2.9G, 4x32GB RAM, 2x960GB SSD SAS; 2x600GB SAS, 2xA30 | D15: Gold 6326 | E15: 128 | F15: 2x960GB SSD SAS; 2x600GB SAS | I15: Y | J15: 2xA30 | K15: 15 | L15: Cty Truyền thông Viettel (đầu mối ThườngLX) bàn giao 30 sv cho TT.PTDL theo CV 2689/BB-CNTT ngày 31/7/2023 | M15: 15
A16: ThangTD1 mail 04/07/2024 | C16: PowerEdge R750XA: 2xIntel Xeon Gold 5318S 2.1G, 8x32GB RAM; 2x960GB SSD; 3xNVIDIA Ampere A30 24GB Passive | D16: Gold 5318S | E16: 256 | F16: 2x960GB SSD SAS | J16: 3xA30 | K16: 2 | L16: IP OS: 10.207.163.81/82 IP quản trị: 10.205.63.71/72 | M16: 2 | N16: ChauLM5 báo VTT có 3 sv ở HLC (whatsapp) hieupc3 mail có 2 sv, fw cho trungtd3 dùng
A17: Chaulm5 cấp phát cho TSA | C17: Máy chủ PowerEdge R650 Server: 2 x Intel Xeon Gold 5318Y 2.1G, 24C/48T, 11.2GT/s, 36M Cache, Turbo, HT (165W) DDR4-2933; 8x32GB RDIMM, 3200MT/s, Dual Rank; 2x1.92TB SSD SAS ISE; | D17: Gold 5318Y | E17: =8*32 -> 256 | F17: SSD: 2 x 1.92 TB | K17: 3 | L17: Cấp phát cho hệ thống TSA theo KH tháng 7/2024 | M17: 3
A18: Chaulm5 whatsapp 28/10/2024 | C18: Máy chủ PowerEdge R650 Server: 2 x Intel Xeon Gold 5318Y 2.1G, 24C/48T, 11.2GT/s, 36M Cache, Turbo, HT (165W) DDR4-2933; 4x32GB RDIMM, 3200MT/s, Dual Rank; 2x1.92TB SSD SAS ISE; | D18: Gold 5318Y | E18: 128 | F18: SSD: 2 x 1.92 TB | I18: Y | K18: 6 | L18: Lô 2021, không có quy hoạch dung lượng
A20: Tài nguyên vật lý QHDC 2022
A21: Mã trạm | B21: Loại server | C21: Cấu hình | D21: CPU | E21: RAM | F21: Disk | G21: Bigdata | H21: Archiving | I21: HBA | J21: GPU | K21: Tổng | L21: Ghi chú | M21: Đã cấp | N21: Tổng CPU | O21: Tổng RAM | P21: CPU used | Q21: RAM used
A22: HLC | B22: 1 | C22: Dell R650 2xIntel 5318Y 8x32GB 2x600GB SAS 2x NIC 10G dual port | D22: 96 | E22: 256 | F22: 2x600GB SAS | I22: Y | K22: 68 | L22: cấp phát 1 svr DB roaming | M22: 4 | N22: =K22*D22 -> 6528 | O22: =K22*E22 -> 17408 | P22: =($M22)*D22 -> 384 | Q22: =($M22)*E22 -> 1024
A23: HKH | B23: 1 | C23: Dell R650 2xIntel 5318Y 8x32GB 2x600GB SAS 2x NIC 10G dual port | D23: 96 | E23: 256 | F23: 2x600GB SAS | I23: Y | K23: 101 | L23: Đã cấp 50 svr cho TV360, còn 51 server VTT cầm - thongnv31 | M23: 50 | N23: =K23*D23 -> 9696 | O23: =K23*E23 -> 25856 | P23: =($M23)*D23 -> 4800 | Q23: =($M23)*E23 -> 12800
A24: HKH | B24: 2 | C24: Dell R650 2xIntel 5318Y 8x64GB 2x600GB SAS 2x NIC 10G dual port | D24: 96 | E24: 512 | F24: 2x600GB SAS | I24: Y | K24: 2 | L24: Đã cấp hết cho TV360 | M24: 2 | N24: =K24*D24 -> 192 | O24: =K24*E24 -> 1024 | P24: =($M24)*D24 -> 192 | Q24: =($M24)*E24 -> 1024
A25: HLC | B25: 4 | C25: Dell R6502xIntel 5318Y 4x32GB/4x64GB 2x600GB SAS 2x1,92TB SSD 2x NIC 10G dual port | D25: 96 | E25: 384 | F25: 2x600GB SAS 2x1,92TB SSD | K25: 20 | N25: =K25*D25 -> 1920 | O25: =K25*E25 -> 7680 | P25: =($M25)*D25 -> 0 | Q25: =($M25)*E25 -> 0
A26: HLC | B26: 6 | C26: DELL R750XA 2xIntel 5318S 4x64GB 2x800G SSD 2x1,92TB SSD 1x NIC 10G Quad port | D26: 96 | E26: 256 | F26: 2x800G SSD 2x1,92TB SSD | I26: Y | J26: 3xNVIDIA A30 | K26: 18 | L26: Cấp phát 10 server cho đội DAC (CCAI-dungha7) Cấp phát 8 server cho đội DAC (Callbot, GSCG-Kientt6) | M26: 18 | N26: =K26*D26 -> 1728 | O26: =K26*E26 -> 4608 | P26: =($M26)*D26 -> 1728 | Q26: =($M26)*E26 -> 4608
A27: HKH | B27: Big DATA1 | C27: Dell R650 2xIntel 5318Y 4x64GB 2x1.92TB SSD 2x NIC 10G dual port | D27: 96 | E27: 256 | F27: 2x1.92TB SSD | G27: x | K27: 22 | N27: =K27*D27 -> 2112 | O27: =K27*E27 -> 5632 | P27: =($M27)*D27 -> 0 | Q27: =($M27)*E27 -> 0
A28: HKH | B28: Big DATA2 | C28: Dell R650 2xIntel 5318Y 4x32GB 4x64GB 2x600GB SAS 2x NIC 10G dual port | D28: 96 | E28: 384 | F28: 2x600GB SAS | G28: x | K28: 193 | L28: Tài nguyên cloud loại 1 chuyển sang bigdata - thongnv31 cầm | N28: =K28*D28 -> 18528 | O28: =K28*E28 -> 74112 | P28: =($M28)*D28 -> 0 | Q28: =($M28)*E28 -> 0
A36: Tài nguyên vật lý QHDC 2023
A37: Mã trạm | B37: Loại server | C37: Cấu hình | D37: CPU | E37: RAM | F37: Disk | G37: Bigdata | H37: Archiving | I37: HBA | J37: GPU | K37: Tổng | L37: Ghi chú | M37: Đã cấp
A38: HLC | B38: Vật lý loại 1 | C38: 2xIntel 5318Y 4x32GB, 2x960 GB SSD | E38: 128 | F38: 2x960 GB SSD | K38: 21
A39: HLC | B39: Vật lý loại 2 | C39: 2xIntel 5318Y 4x32GB, 2x960 GB SSD | E39: 128 | F39: 2x960 GB SSD | K39: 19 | L39: Quy hoạch cấp phát DB oracle
A40: HLC | B40: Vật lý loại 3 | C40: 2xIntel 5318Y 4x64GB, 2x960 GB SSD | E40: 256 | F40: 2x960 GB SSD | I40: Y | K40: 2
A41: HLC | B41: Vật lý loại 4 | C41: 2xIntel 5318Y 4x64GB, 2x960 GB SSD | E41: 256 | F41: 2x960 GB SSD | K41: 19 | L41: Quy hoạch cấp phát DB oracle
A42: HLC | B42: Vật lý loại 5 | C42: 2xIntel 5318Y 4x64GB, 2x960 GB SSD, 3x10TB HDD | E42: 256 | F42: 2x960 GB SSD 3x10TB HDD | I42: Y | K42: 120
A43: HLC | B43: Vật lý loại 7 | C43: 2xIntel 5318Y 384GB, 2x960 GB SSD | E43: 384 | F43: 2x960 GB SSD | K43: 5
A44: HLC | B44: GPU loại 1 | C44: 2xIntel Xeon Gold 5418Y 4x64GB 2x1.96 TB SSD | D44: 192 | E44: 256 | F44: 2x1.92 TB SSD | I44: Y | J44: NVIDIA L4 | K44: 12 | L44: Kientt6: 12 sv loại 1 + 8 sv loại 3 Dungha7: 11 sv loại 2 + 5 sv loại 3 | M44: 12
A45: HLC | B45: GPU loại 2 | C45: 2xAMD AMD EPYC 9554 4x64GB, 2x1.92B; 2x3.84 GB SSD | D45: 256 | E45: 256 | F45: 2x1.92 TB SSD 2x3.84 TB SSD | I45: Y | J45: NVIDIA L4 | K45: 11 | L45: Kientt6: 12 sv loại 1 + 8 sv loại 3 Dungha7: 11 sv loại 2 + 5 sv loại 3 | M45: 11
A46: HLC | B46: GPU loại 3 | C46: 2xIntel Xeon Gold 5418Y 384 GB 2x960 GB SSD | D46: =96*2 -> 192 | E46: 384 | F46: 2x1.92 TB SSD | I46: Y | J46: NVIDIA L40 | K46: 13 | L46: Kientt6: 12 sv loại 1 + 8 sv loại 3 Dungha7: 11 sv loại 2 + 5 sv loại 3 | M46: 13
B47: Vật lý loại 3 | C47: Dell PowerEdge R660 2 xIntel Xeon-Gold 5418Y 4x64GB DDR5 2x960GB SSD 3x8TB SAS" | E47: 256 | F47: 2x960 GB SSD 3x8TB SAS | G47: 7,3PB | I47: Y | K47: 215 | L47: 7,3PB lưu trữ datalake => TK ở HLA
B48: Vật lý loại 5 | C48: Dell PowerEdge R760 2xIntel Xeon-Gold 5418Y 4x64GB DDR5 "2x960GB SSD | E48: 256 | F48: 2x960 GB SSD 3x8TB SAS | G48: 7,3PB | K48: 9 | L48: 7,3PB lưu trữ datalake => TK ở HLA
B49: Vật lý loại 6 | C49: Dell PowerEdge R760 2xIntel Xeon-Gold 5418Y 4x64GB DDR5 "2x960GB SSD 2x1.92TB SSD | E49: 256 | F49: 2x960 GB SSD 8x8TB SAS 2x1.92TB SSD | G49: 7,3PB | K49: 14 | L49: 7,3PB lưu trữ datalake => TK ở HLA
A51: Tài nguyên vật lý QHDC 2024
B52: Vật lý loại 1 | C52: 2xIntel I4516Y128GB (2x64GB), 2x960 GB SSD | E52: 128 | F52: 2x960 GB SSD | I52: Y | K52: 87
B53: Vật lý loại 2 | C53: 2xIntel I4516Y 256GB (4x64GB), 2x960 GB SSD | E53: 256 | F53: 2x960 GB SSD | I53: Y | K53: 26
B54: Vật lý loại 3 | C54: 2xIntel I4516Y 384GB (12x32GB), 2x960 GB SSD | E54: 384 | F54: 2x960 GB SSD | K54: 10
F55: 4x3.8TB
B56: Vật lý loại 4 | C56: 2xIntel I4516Y 384GB (12x32GB), 2x960 GB SSD 4x2.4TB HDD | E56: 384 | F56: 2x960 GB SSD | I56: Y | K56: 3
F57: 4x2.4TB HDD
B58: Vật lý loại 7 | C58: 2xIntel I4516Y 512GB , 2x960 GB SSD | E58: 512 | F58: 2x960 GB SSD | I58: Y | K58: 120
C59: 4x2.4TB HDD | F59: 4x2.4TB HDD
B60: GPU loại 1 | C60: 2xIntel 5318Y 4x64GB 2x960 GB SSD | E60: ? | F60: ? | I60: ? | J60: ? | K60: 38 | L60: Chưa có thông tin cấu hình
B61: DGX | C61: ? | E61: ? | F61: ? | I61: ? | J61: ? | K61: 8 | L61: Chưa có thông tin cấu hình
B62: Bigdata Vật lý loại 6 | C62: 2xIntel Xeon Gold 5418Y 2G, 256GB (4x64GB) | E62: 256 | F62: 2x1.92TB SSD, 6x7,68TB SSD | K62: 211

Sheet Cấp phát vật lý
A1: STT | B1: Dự án | C1: Đơn vị | D1: Đầu mối | E1: Đầu mối p.HT | F1: Ngày cấp | G1: Quý cấp phát | H1: Số lượng máy chủ | I1: vCPU | J1: Cint | K1: RAM | L1: SAN | M1: NAS | N1: Ceph | O1: Bigdata | P1: Archiving | Q1: Pool/Nguồn tài nguyên | R1: Phân loại nhóm tài nguyên | S1: Ghi chú
A2: 1 | B2: QLHS | C2: BSS | H2: 3 | L2: =(8.5*1024+200+5*1024+60+(8.5*1024+200+60)*2) -> 32012 | Q2: Vật lí 2021 | R2: 2021 | S2: Sv5-22
A3: 2 | B3: AI nhận diện (Bộ CA) | C3: BSS | D3: phund2 | F3: 25/11/2022 | G3: Q4/2022 | H3: 30 | I3: =80*H3 -> 2400 | J3: =I3*3 -> 7200 | K3: =256*H3 -> 7680 | S3: VTNet ko thu hồi sv mượn nữa (từ 2022), hoàn trả bằng QHĐC 2022. 02xIntel Xeon Gold 5218r, 256GB RAM, 2x600 SAS
A4: 3 | B4: IPCC HNI - DR | C4: DVKH | D4: trongtd1 | F4: 26/9/2023 | G4: Q3/2023 | H4: 2 | I4: =96*H4 -> 192 | J4: =I4*3 -> 576 | K4: =8*32*H4 -> 512 | Q4: chaulm5 | S4: PowerEdge R650 Server: 2 x Intel Xeon Gold 5318Y 2.1G, 24C/48T, DDR4 8x32GB, 2x600GB Hard Drive SAS, Dual Port 16Gb Fibre Channel HBA (serial: 3Z822S3, GCYYRR3)
A5: 4 | B5: CCAI | C5: DAC | D5: dungha7 | F5: 23/2/2024 | G5: Q1/2024 | H5: 6 | I5: 201 | J5: 660 | K5: =256*H5 -> 1536 | O5: 150000 | Q5: Vật lí 2021 | R5: 2021 | S5: Sv5-4 (2x Gold 5318Y, 256GB RAM, SSD: 2 x 960G)
A6: 5 | B6: Campaign management | C6: BSS | D6: anhdt156 | F6: 45446 | G6: Q1/2024 | H6: 31 | I6: 903 | J6: 2710 | K6: 7936 | O6: 372736 | Q6: Vật lí 2021 | R6: 2021 | S6: 2x Gold 5318Y, 256GB RAM, SSD: 2 x 960G
A7: 6 | B7: Database V-Tracking 2023 | C7: BSS | D7: tramdtt1 | G7: Q1/2024 | H7: 2 | I7: 8 | J7: 24 | K7: 64 | L7: 1326 | S7: Cấp tài nguyên Database, Yêu cầu cấp hạ tầng vật lí Database cùng tổng trạm với server App (10.60.32.175, 10.60.32.176 - Hòa Lạc) Cụ thể: Bổ sung cụ thể từng phân vùng như sau: Storage : 1326 GB Cụ thể từng phân vùng như sau: CRS: 15G ARC: 500G REDO 1 50G REDO 2 50G DATA: Số dung lượng còn lại
A8: 7 | B8: Cloud CA | C8: BSS | D8: thanhtt69 | G8: Q2/2024 | H8: 8 | I8: 355 | J8: 1063 | K8: 1599 | L8: 28215 | Q8: chaulm5
A9: 8 | B9: VTT Analytic | C9: DAC | D9: dungha7 | G9: Q2/2024 | H9: 30 | I9: 1830 | J9: 5490 | K9: =128*15+128*15 -> 3840 | O9: 528600 | Q9: Vật lý 2021 | S9: VTM bàn giao: 2689/BB-CNTT PowerEdge R750: 2 x Intel Xeon Silver 4314 2.4G, 4x32GB RAM, 8x3.84TB SSD SAS; 2x600GB SAS PowerEdge R750: 2 xIntel Xeon Gold 6326 2.9G, 4x32GB RAM, 2x960GB SSD SAS; 2x600GB SAS, 2xA30
A10: 9 | B10: TSA | C10: BSS | D10: Dungdb1 | G10: Q3/2024 | H10: 3 | I10: =3*2*24 -> 144 | J10: =I10*3 -> 432 | K10: =3*8*32 -> 768 | L10: =3*2*19200 -> 115200 | Q10: chaulm5 | S10: 3 x Máy chủ PowerEdge R650 Server: 2 x Intel Xeon Gold 5318Y 2.1G, 24C/48T, 11.2GT/s, 36M Cache, Turbo, HT (165W) DDR4-2933; 8x32GB RDIMM, 3200MT/s, Dual Rank; 2x1.92TB SSD SAS ISE;
A11: Tài nguyên vật lý 2022
A12: 1 | B12: DB roaming hạn 12 tháng | C12: ĐS | D12: anhnt162 | E12: vinhtq18 | G12: Q4/2024 | H12: 1 | I12: 32 | J12: 96 | K12: 96 | L12: 8192 | Q12: HLC Vat ly loai 1 | R12: 2022 | S12: 1 x máy chủ Dell R650 2xIntel 5318Y 8x32GB 2x600GB SAS 2x NIC 10G dual port
A13: 2 | B13: PBH 3.0 | C13: BSS | D13: thanhdv125 | E13: thongnv31 | G13: Q4/2024 | H13: 3 | I13: 278 | J13: 834 | K13: 768 | L13: 43300 | Q13: HLC Vat ly loai 1 | R13: 2022 | S13: 3 x máy chủ Dell R650 2xIntel 5318Y 8x32GB 2x600GB SAS 2x NIC 10G dual port
U22: San2022 | V22: =SUMIF($R$2:$R$217,"=2022",L2:L217) -> 51492
U23: bigdata2022 | V23: =SUMIF($R$2:$R$217,"=2022",O3:O218) -> 0
U24: Archiving2022 | V24: =SUMIF($R$2:$R$217,"=2022",P3:P218) -> 0

Sheet MyCC
A1: STT | B1: Cloud | C1: Tên dự án | D1: Service | E1: Hostname | F1: IP | H1: Loại OS | I1: Cấu hình phần cứng | K1: Dung lượng ổ cứng | N1: Tài nguyên cấp phát | P1: Network Limit | Q1: Gateway | R1: VHKT | S1: Owner server | T1: Route | U1: Package | V1: Monitored Prometheus | W1: Ghi chú
F2: DCN | G2: IP Khác | I2: vCPU | J2: RAM | K2: Volume OS (GB) | L2: Volume khác (GB) | M2: NAS | N2: HA | O2: Storage Pool
A3: 1 | B3: Cloud_VTT | C3: MyCC | D3: appipccx | E3: mycc-appipccx-10205058089 | F3: 10.205.58.89/24 | G3: 10.207.189.5/24 10.52.125.6/24 171.229.16.33/24 | H3: CentOS_7_7_final | I3: 14 | J3: 54 | K3: 60 | L3: u01: 190 | N3: VTT_SAN_2021_Q4_01 | O3: IDC7F_E07_Unity_880_1020502474_SAS | P3: 1 | Q3: 10.207.189.254 | R3: Yes | S3: anhtt69 | T3: 10.240.201.49/32 via 10.205.58.254 dev eth0 10.254.139.0/24 via 10.205.58.254 dev eth0 10.240.226.0/24 via 10.205.58.254 dev eth0 10.255.58.0/24 via 10.205.58.254 dev eth0 10.60.101.0/24 via 10.205.58.254 dev eth0 10.58.15.114/32 via 10.205.58.254 dev eth0 10.58.137.0/24 via 10.205.58.254 dev eth0 10.60.7.0/24 via 10.205.58.254 dev eth0 10.60.97.0/24 via 10.205.58.254 dev eth0 192.168.182.8/32 via 10.205.58.254 dev eth0 10.60.96.0/24 via 10.205.58.254 dev eth0 10.58.4.0/24 via 10.205.58.254 dev eth0 10.58.65.0/24 via 10.205.58.254 dev eth0 10.40.17.0/24 via 10.205.58.254 dev eth0 10.74.225.0/24 via 10.205.58.254 dev eth0 10.60.131.0/24 via 10.205.58.254 dev eth0 10.60.129.0/24 via 10.205.58.254 dev eth0 10.30.160.0/24 via 10.205.58.254 dev eth0 10.61.151.0/24 via 10.205.58.254 dev eth0 10.60.100.0/24 via 10.205.58.254 dev eth0 192.168.176.0/24 via 10.205.58.254 dev eth0 192.168.252.0/24 via 10.205.58.254 dev eth0 192.168.131.50/32 via 10.205.58.254 dev eth0 10.240.178.0/24 via 10.205.58.254 dev eth0 10.240.166.2/32 via 10.205.58.254 dev eth0 10.240.188.0/24 via 10.205.58.254 dev eth0 10.240.202.0/24 via 10.205.58.254 dev eth0 10.60.100.73/32 via 10.205.58.254 dev eth0 10.60.5.133/32 via 10.205.58.254 dev eth0 | V3: Yes | W3: Dau moi dich vu: tannph | X3: Các server đã cấp nhưng chưa dùng
A4: 2 | B4: Cloud_VTT | C4: MyCC | D4: appipccx | E4: mycc-appipccx-10205058090 | F4: 10.205.58.90/24 | G4: 10.207.189.6/24 10.52.125.7/24 171.229.16.34/24 | H4: CentOS_7_7_final | I4: 14 | J4: 54 | K4: 60 | L4: u01: 190 | N4: VTT_SAN_2021_Q4_01 | O4: IDC7F_E08_Unity_880_1020502476_SAS | P4: 1 | Q4: 10.207.189.254 | R4: Yes | S4: anhtt69 | T4: 10.240.201.49/32 via 10.205.58.254 dev eth0 10.254.139.0/24 via 10.205.58.254 dev eth0 10.240.226.0/24 via 10.205.58.254 dev eth0 10.255.58.0/24 via 10.205.58.254 dev eth0 10.60.101.0/24 via 10.205.58.254 dev eth0 10.58.15.114/32 via 10.205.58.254 dev eth0 10.58.137.0/24 via 10.205.58.254 dev eth0 10.60.7.0/24 via 10.205.58.254 dev eth0 10.60.97.0/24 via 10.205.58.254 dev eth0 192.168.182.8/32 via 10.205.58.254 dev eth0 10.60.96.0/24 via 10.205.58.254 dev eth0 10.58.4.0/24 via 10.205.58.254 dev eth0 10.58.65.0/24 via 10.205.58.254 dev eth0 10.40.17.0/24 via 10.205.58.254 dev eth0 10.74.225.0/24 via 10.205.58.254 dev eth0 10.60.131.0/24 via 10.205.58.254 dev eth0 10.60.129.0/24 via 10.205.58.254 dev eth0 10.30.160.0/24 via 10.205.58.254 dev eth0 10.61.151.0/24 via 10.205.58.254 dev eth0 10.60.100.0/24 via 10.205.58.254 dev eth0 192.168.176.0/24 via 10.205.58.254 dev eth0 192.168.252.0/24 via 10.205.58.254 dev eth0 192.168.131.50/32 via 10.205.58.254 dev eth0 10.240.178.0/24 via 10.205.58.254 dev eth0 10.240.166.2/32 via 10.205.58.254 dev eth0 10.240.188.0/24 via 10.205.58.254 dev eth0 10.240.202.0/24 via 10.205.58.254 dev eth0 10.60.100.73/32 via 10.205.58.254 dev eth0 10.60.5.133/32 via 10.205.58.254 dev eth0 | V4: Yes | W4: Dau moi dich vu: tannph | X4: Các server đã cấp nhưng chưa dùng
A5: 3 | B5: Cloud_VTT | C5: MyCC | D5: appipccx | E5: mycc-appipccx-10205058091 | F5: 10.205.58.91/24 | G5: 10.207.189.7/24 10.52.125.8/24 171.229.16.35/24 | H5: CentOS_7_7_final | I5: 14 | J5: 54 | K5: 60 | L5: u01: 190 | N5: VTT_SAN_2021_Q4_01 | O5: IDC7F_E07_Unity_880_1020502474_SAS | P5: 1 | Q5: 10.207.189.254 | R5: Yes | S5: anhtt69 | T5: 10.240.201.49/32 via 10.205.58.254 dev eth0 10.254.139.0/24 via 10.205.58.254 dev eth0 10.240.226.0/24 via 10.205.58.254 dev eth0 10.255.58.0/24 via 10.205.58.254 dev eth0 10.60.101.0/24 via 10.205.58.254 dev eth0 10.58.15.114/32 via 10.205.58.254 dev eth0 10.58.137.0/24 via 10.205.58.254 dev eth0 10.60.7.0/24 via 10.205.58.254 dev eth0 10.60.97.0/24 via 10.205.58.254 dev eth0 192.168.182.8/32 via 10.205.58.254 dev eth0 10.60.96.0/24 via 10.205.58.254 dev eth0 10.58.4.0/24 via 10.205.58.254 dev eth0 10.58.65.0/24 via 10.205.58.254 dev eth0 10.40.17.0/24 via 10.205.58.254 dev eth0 10.74.225.0/24 via 10.205.58.254 dev eth0 10.60.131.0/24 via 10.205.58.254 dev eth0 10.60.129.0/24 via 10.205.58.254 dev eth0 10.30.160.0/24 via 10.205.58.254 dev eth0 10.61.151.0/24 via 10.205.58.254 dev eth0 10.60.100.0/24 via 10.205.58.254 dev eth0 192.168.176.0/24 via 10.205.58.254 dev eth0 192.168.252.0/24 via 10.205.58.254 dev eth0 192.168.131.50/32 via 10.205.58.254 dev eth0 10.240.178.0/24 via 10.205.58.254 dev eth0 10.240.166.2/32 via 10.205.58.254 dev eth0 10.240.188.0/24 via 10.205.58.254 dev eth0 10.240.202.0/24 via 10.205.58.254 dev eth0 10.60.100.73/32 via 10.205.58.254 dev eth0 10.60.5.133/32 via 10.205.58.254 dev eth0 | V5: Yes | W5: Dau moi dich vu: tannph | X5: Các server đã cấp nhưng chưa dùng
A6: 4 | B6: Cloud_VTT | C6: MyCC | D6: appipccx | E6: mycc-appipccx-10205058092 | F6: 10.205.58.92/24 | G6: 10.207.189.8/24 10.52.125.9/24 171.229.16.36/24 | H6: CentOS_7_7_final | I6: 14 | J6: 54 | K6: 60 | L6: u01: 190 | N6: VTT_SAN_2021_Q4_01 | O6: IDC7F_E08_Unity_880_1020502476_SAS | P6: 1 | Q6: 10.207.189.254 | R6: Yes | S6: anhtt69 | T6: 10.240.201.49/32 via 10.205.58.254 dev eth0 10.254.139.0/24 via 10.205.58.254 dev eth0 10.240.226.0/24 via 10.205.58.254 dev eth0 10.255.58.0/24 via 10.205.58.254 dev eth0 10.60.101.0/24 via 10.205.58.254 dev eth0 10.58.15.114/32 via 10.205.58.254 dev eth0 10.58.137.0/24 via 10.205.58.254 dev eth0 10.60.7.0/24 via 10.205.58.254 dev eth0 10.60.97.0/24 via 10.205.58.254 dev eth0 192.168.182.8/32 via 10.205.58.254 dev eth0 10.60.96.0/24 via 10.205.58.254 dev eth0 10.58.4.0/24 via 10.205.58.254 dev eth0 10.58.65.0/24 via 10.205.58.254 dev eth0 10.40.17.0/24 via 10.205.58.254 dev eth0 10.74.225.0/24 via 10.205.58.254 dev eth0 10.60.131.0/24 via 10.205.58.254 dev eth0 10.60.129.0/24 via 10.205.58.254 dev eth0 10.30.160.0/24 via 10.205.58.254 dev eth0 10.61.151.0/24 via 10.205.58.254 dev eth0 10.60.100.0/24 via 10.205.58.254 dev eth0 192.168.176.0/24 via 10.205.58.254 dev eth0 192.168.252.0/24 via 10.205.58.254 dev eth0 192.168.131.50/32 via 10.205.58.254 dev eth0 10.240.178.0/24 via 10.205.58.254 dev eth0 10.240.166.2/32 via 10.205.58.254 dev eth0 10.240.188.0/24 via 10.205.58.254 dev eth0 10.240.202.0/24 via 10.205.58.254 dev eth0 10.60.100.73/32 via 10.205.58.254 dev eth0 10.60.5.133/32 via 10.205.58.254 dev eth0 | V6: Yes | W6: Dau moi dich vu: tannph | X6: Các server đã cấp nhưng chưa dùng
A7: 5 | B7: Cloud_VTT | C7: MyCC | D7: appipccx | E7: mycc-appipccx-10205058093 | F7: 10.205.58.93/24 | G7: 10.207.189.9/24 10.52.125.10/24 171.229.16.37/24 | H7: CentOS_7_7_final | I7: 14 | J7: 54 | K7: 60 | L7: u01: 190 | N7: VTT_SAN_2021_Q4_01 | O7: IDC7F_E07_Unity_880_1020502474_SAS | P7: 1 | Q7: 10.207.189.254 | R7: Yes | S7: anhtt69 | T7: 10.240.201.49/32 via 10.205.58.254 dev eth0 10.254.139.0/24 via 10.205.58.254 dev eth0 10.240.226.0/24 via 10.205.58.254 dev eth0 10.255.58.0/24 via 10.205.58.254 dev eth0 10.60.101.0/24 via 10.205.58.254 dev eth0 10.58.15.114/32 via 10.205.58.254 dev eth0 10.58.137.0/24 via 10.205.58.254 dev eth0 10.60.7.0/24 via 10.205.58.254 dev eth0 10.60.97.0/24 via 10.205.58.254 dev eth0 192.168.182.8/32 via 10.205.58.254 dev eth0 10.60.96.0/24 via 10.205.58.254 dev eth0 10.58.4.0/24 via 10.205.58.254 dev eth0 10.58.65.0/24 via 10.205.58.254 dev eth0 10.40.17.0/24 via 10.205.58.254 dev eth0 10.74.225.0/24 via 10.205.58.254 dev eth0 10.60.131.0/24 via 10.205.58.254 dev eth0 10.60.129.0/24 via 10.205.58.254 dev eth0 10.30.160.0/24 via 10.205.58.254 dev eth0 10.61.151.0/24 via 10.205.58.254 dev eth0 10.60.100.0/24 via 10.205.58.254 dev eth0 192.168.176.0/24 via 10.205.58.254 dev eth0 192.168.252.0/24 via 10.205.58.254 dev eth0 192.168.131.50/32 via 10.205.58.254 dev eth0 10.240.178.0/24 via 10.205.58.254 dev eth0 10.240.166.2/32 via 10.205.58.254 dev eth0 10.240.188.0/24 via 10.205.58.254 dev eth0 10.240.202.0/24 via 10.205.58.254 dev eth0 10.60.100.73/32 via 10.205.58.254 dev eth0 10.60.5.133/32 via 10.205.58.254 dev eth0 | V7: Yes | W7: Dau moi dich vu: tannph | X7: Các server đã cấp nhưng chưa dùng
A8: 6 | B8: Cloud_VTT | C8: MyCC | D8: appipccx | E8: mycc-appipccx-10205058094 | F8: 10.205.58.94/24 | G8: 10.207.189.10/24 10.52.125.11/24 171.229.16.38/24 | H8: CentOS_7_7_final | I8: 14 | J8: 54 | K8: 60 | L8: u01: 190 | N8: VTT_SAN_2021_Q4_01 | O8: IDC7F_E08_Unity_880_1020502476_SAS | P8: 1 | Q8: 10.207.189.254 | R8: Yes | S8: anhtt69 | T8: 10.240.201.49/32 via 10.205.58.254 dev eth0 10.254.139.0/24 via 10.205.58.254 dev eth0 10.240.226.0/24 via 10.205.58.254 dev eth0 10.255.58.0/24 via 10.205.58.254 dev eth0 10.60.101.0/24 via 10.205.58.254 dev eth0 10.58.15.114/32 via 10.205.58.254 dev eth0 10.58.137.0/24 via 10.205.58.254 dev eth0 10.60.7.0/24 via 10.205.58.254 dev eth0 10.60.97.0/24 via 10.205.58.254 dev eth0 192.168.182.8/32 via 10.205.58.254 dev eth0 10.60.96.0/24 via 10.205.58.254 dev eth0 10.58.4.0/24 via 10.205.58.254 dev eth0 10.58.65.0/24 via 10.205.58.254 dev eth0 10.40.17.0/24 via 10.205.58.254 dev eth0 10.74.225.0/24 via 10.205.58.254 dev eth0 10.60.131.0/24 via 10.205.58.254 dev eth0 10.60.129.0/24 via 10.205.58.254 dev eth0 10.30.160.0/24 via 10.205.58.254 dev eth0 10.61.151.0/24 via 10.205.58.254 dev eth0 10.60.100.0/24 via 10.205.58.254 dev eth0 192.168.176.0/24 via 10.205.58.254 dev eth0 192.168.252.0/24 via 10.205.58.254 dev eth0 192.168.131.50/32 via 10.205.58.254 dev eth0 10.240.178.0/24 via 10.205.58.254 dev eth0 10.240.166.2/32 via 10.205.58.254 dev eth0 10.240.188.0/24 via 10.205.58.254 dev eth0 10.240.202.0/24 via 10.205.58.254 dev eth0 10.60.100.73/32 via 10.205.58.254 dev eth0 10.60.5.133/32 via 10.205.58.254 dev eth0 | V8: Yes | W8: Dau moi dich vu: tannph | X8: Các server đã cấp nhưng chưa dùng
A9: 7 | B9: Cloud_VTT | C9: MyCC | D9: appipcc1x | E9: mycc-appipcc1x-10205058095 | F9: 10.205.58.95/24 | G9: 10.207.189.11/24 10.207.192.43/24 | H9: CentOS_7_7_final | I9: 40 | J9: 26 | K9: 60 | L9: u01: 190 | M9: 5000 | N9: VTT_SAN_2021_Q4_01 | O9: IDC7F_E07_Unity_880_1020502474_SAS | P9: 1 | Q9: 10.207.189.254 | R9: Yes | S9: anhtt69 | T9: 10.240.201.49/32 via 10.205.58.254 dev eth0 10.254.139.0/24 via 10.205.58.254 dev eth0 10.240.226.0/24 via 10.205.58.254 dev eth0 10.255.58.0/24 via 10.205.58.254 dev eth0 10.60.101.0/24 via 10.205.58.254 dev eth0 10.58.15.114/32 via 10.205.58.254 dev eth0 10.58.137.0/24 via 10.205.58.254 dev eth0 10.60.7.0/24 via 10.205.58.254 dev eth0 10.60.97.0/24 via 10.205.58.254 dev eth0 192.168.182.8/32 via 10.205.58.254 dev eth0 10.60.96.0/24 via 10.205.58.254 dev eth0 10.58.4.0/24 via 10.205.58.254 dev eth0 10.58.65.0/24 via 10.205.58.254 dev eth0 10.40.17.0/24 via 10.205.58.254 dev eth0 10.74.225.0/24 via 10.205.58.254 dev eth0 10.60.131.0/24 via 10.205.58.254 dev eth0 10.60.129.0/24 via 10.205.58.254 dev eth0 10.30.160.0/24 via 10.205.58.254 dev eth0 10.61.151.0/24 via 10.205.58.254 dev eth0 10.60.100.0/24 via 10.205.58.254 dev eth0 192.168.176.0/24 via 10.205.58.254 dev eth0 192.168.252.0/24 via 10.205.58.254 dev eth0 192.168.131.50/32 via 10.205.58.254 dev eth0 10.240.178.0/24 via 10.205.58.254 dev eth0 10.240.166.2/32 via 10.205.58.254 dev eth0 10.240.188.0/24 via 10.205.58.254 dev eth0 10.240.202.0/24 via 10.205.58.254 dev eth0 10.60.100.73/32 via 10.205.58.254 dev eth0 10.60.5.133/32 via 10.205.58.254 dev eth0 | V9: Yes | W9: Dau moi dich vu: tannph | X9: Các server đã cấp nhưng chưa dùng
A10: 8 | B10: Cloud_VTT | C10: MyCC | D10: appipcc1x | E10: mycc-appipcc1x-10205058096 | F10: 10.205.58.96/24 | G10: 10.207.189.12/24 10.207.192.44/24 | H10: CentOS_7_7_final | I10: 40 | J10: 26 | K10: 60 | L10: u01: 190 | M10: 5000 | N10: VTT_SAN_2021_Q4_01 | O10: IDC7F_E08_Unity_880_1020502476_SAS | P10: 1 | Q10: 10.207.189.254 | R10: Yes | S10: anhtt69 | T10: 10.240.201.49/32 via 10.205.58.254 dev eth0 10.254.139.0/24 via 10.205.58.254 dev eth0 10.240.226.0/24 via 10.205.58.254 dev eth0 10.255.58.0/24 via 10.205.58.254 dev eth0 10.60.101.0/24 via 10.205.58.254 dev eth0 10.58.15.114/32 via 10.205.58.254 dev eth0 10.58.137.0/24 via 10.205.58.254 dev eth0 10.60.7.0/24 via 10.205.58.254 dev eth0 10.60.97.0/24 via 10.205.58.254 dev eth0 192.168.182.8/32 via 10.205.58.254 dev eth0 10.60.96.0/24 via 10.205.58.254 dev eth0 10.58.4.0/24 via 10.205.58.254 dev eth0 10.58.65.0/24 via 10.205.58.254 dev eth0 10.40.17.0/24 via 10.205.58.254 dev eth0 10.74.225.0/24 via 10.205.58.254 dev eth0 10.60.131.0/24 via 10.205.58.254 dev eth0 10.60.129.0/24 via 10.205.58.254 dev eth0 10.30.160.0/24 via 10.205.58.254 dev eth0 10.61.151.0/24 via 10.205.58.254 dev eth0 10.60.100.0/24 via 10.205.58.254 dev eth0 192.168.176.0/24 via 10.205.58.254 dev eth0 192.168.252.0/24 via 10.205.58.254 dev eth0 192.168.131.50/32 via 10.205.58.254 dev eth0 10.240.178.0/24 via 10.205.58.254 dev eth0 10.240.166.2/32 via 10.205.58.254 dev eth0 10.240.188.0/24 via 10.205.58.254 dev eth0 10.240.202.0/24 via 10.205.58.254 dev eth0 10.60.100.73/32 via 10.205.58.254 dev eth0 10.60.5.133/32 via 10.205.58.254 dev eth0 | V10: Yes | W10: Dau moi dich vu: tannph | X10: Các server đã cấp nhưng chưa dùng
A11: 9 | B11: Cloud_VTT | C11: MyCC | D11: appipcc1x | E11: mycc-appipcc1x-10205058097 | F11: 10.205.58.97/24 | G11: 10.207.189.13/24 10.207.192.45/24 | H11: CentOS_7_7_final | I11: 40 | J11: 26 | K11: 60 | L11: u01: 190 | M11: 5000 | N11: VTT_SAN_2021_Q4_01 | O11: IDC7F_E07_Unity_880_1020502474_SAS | P11: 1 | Q11: 10.207.189.254 | R11: Yes | S11: anhtt69 | T11: 10.240.201.49/32 via 10.205.58.254 dev eth0 10.254.139.0/24 via 10.205.58.254 dev eth0 10.240.226.0/24 via 10.205.58.254 dev eth0 10.255.58.0/24 via 10.205.58.254 dev eth0 10.60.101.0/24 via 10.205.58.254 dev eth0 10.58.15.114/32 via 10.205.58.254 dev eth0 10.58.137.0/24 via 10.205.58.254 dev eth0 10.60.7.0/24 via 10.205.58.254 dev eth0 10.60.97.0/24 via 10.205.58.254 dev eth0 192.168.182.8/32 via 10.205.58.254 dev eth0 10.60.96.0/24 via 10.205.58.254 dev eth0 10.58.4.0/24 via 10.205.58.254 dev eth0 10.58.65.0/24 via 10.205.58.254 dev eth0 10.40.17.0/24 via 10.205.58.254 dev eth0 10.74.225.0/24 via 10.205.58.254 dev eth0 10.60.131.0/24 via 10.205.58.254 dev eth0 10.60.129.0/24 via 10.205.58.254 dev eth0 10.30.160.0/24 via 10.205.58.254 dev eth0 10.61.151.0/24 via 10.205.58.254 dev eth0 10.60.100.0/24 via 10.205.58.254 dev eth0 192.168.176.0/24 via 10.205.58.254 dev eth0 192.168.252.0/24 via 10.205.58.254 dev eth0 192.168.131.50/32 via 10.205.58.254 dev eth0 10.240.178.0/24 via 10.205.58.254 dev eth0 10.240.166.2/32 via 10.205.58.254 dev eth0 10.240.188.0/24 via 10.205.58.254 dev eth0 10.240.202.0/24 via 10.205.58.254 dev eth0 10.60.100.73/32 via 10.205.58.254 dev eth0 10.60.5.133/32 via 10.205.58.254 dev eth0 | V11: Yes | W11: Dau moi dich vu: tannph | X11: Các server đã cấp nhưng chưa dùng
A12: 10 | B12: Cloud_VTT | C12: MyCC | D12: appipcc1x | E12: mycc-appipcc1x-10205058098 | F12: 10.205.58.98/24 | G12: 10.207.189.14/24 10.207.192.46/24 | H12: CentOS_7_7_final | I12: 40 | J12: 26 | K12: 60 | L12: u01: 190 | M12: 5000 | N12: VTT_SAN_2021_Q4_01 | O12: IDC7F_E08_Unity_880_1020502476_SAS | P12: 1 | Q12: 10.207.189.254 | R12: Yes | S12: anhtt69 | T12: 10.240.201.49/32 via 10.205.58.254 dev eth0 10.254.139.0/24 via 10.205.58.254 dev eth0 10.240.226.0/24 via 10.205.58.254 dev eth0 10.255.58.0/24 via 10.205.58.254 dev eth0 10.60.101.0/24 via 10.205.58.254 dev eth0 10.58.15.114/32 via 10.205.58.254 dev eth0 10.58.137.0/24 via 10.205.58.254 dev eth0 10.60.7.0/24 via 10.205.58.254 dev eth0 10.60.97.0/24 via 10.205.58.254 dev eth0 192.168.182.8/32 via 10.205.58.254 dev eth0 10.60.96.0/24 via 10.205.58.254 dev eth0 10.58.4.0/24 via 10.205.58.254 dev eth0 10.58.65.0/24 via 10.205.58.254 dev eth0 10.40.17.0/24 via 10.205.58.254 dev eth0 10.74.225.0/24 via 10.205.58.254 dev eth0 10.60.131.0/24 via 10.205.58.254 dev eth0 10.60.129.0/24 via 10.205.58.254 dev eth0 10.30.160.0/24 via 10.205.58.254 dev eth0 10.61.151.0/24 via 10.205.58.254 dev eth0 10.60.100.0/24 via 10.205.58.254 dev eth0 192.168.176.0/24 via 10.205.58.254 dev eth0 192.168.252.0/24 via 10.205.58.254 dev eth0 192.168.131.50/32 via 10.205.58.254 dev eth0 10.240.178.0/24 via 10.205.58.254 dev eth0 10.240.166.2/32 via 10.205.58.254 dev eth0 10.240.188.0/24 via 10.205.58.254 dev eth0 10.240.202.0/24 via 10.205.58.254 dev eth0 10.60.100.73/32 via 10.205.58.254 dev eth0 10.60.5.133/32 via 10.205.58.254 dev eth0 | V12: Yes | W12: Dau moi dich vu: tannph | X12: Các server đã cấp nhưng chưa dùng
A13: 11 | B13: Cloud_VTT | C13: MyCC | D13: appipcc1x | E13: mycc-appipcc1x-10205058099 | F13: 10.205.58.99/24 | G13: 10.207.189.15/24 10.207.192.47/24 | H13: CentOS_7_7_final | I13: 40 | J13: 26 | K13: 60 | L13: u01: 190 | M13: 5000 | N13: VTT_SAN_2021_Q4_01 | O13: IDC7F_E07_Unity_880_1020502474_SAS | P13: 1 | Q13: 10.207.189.254 | R13: Yes | S13: anhtt69 | T13: 10.240.201.49/32 via 10.205.58.254 dev eth0 10.254.139.0/24 via 10.205.58.254 dev eth0 10.240.226.0/24 via 10.205.58.254 dev eth0 10.255.58.0/24 via 10.205.58.254 dev eth0 10.60.101.0/24 via 10.205.58.254 dev eth0 10.58.15.114/32 via 10.205.58.254 dev eth0 10.58.137.0/24 via 10.205.58.254 dev eth0 10.60.7.0/24 via 10.205.58.254 dev eth0 10.60.97.0/24 via 10.205.58.254 dev eth0 192.168.182.8/32 via 10.205.58.254 dev eth0 10.60.96.0/24 via 10.205.58.254 dev eth0 10.58.4.0/24 via 10.205.58.254 dev eth0 10.58.65.0/24 via 10.205.58.254 dev eth0 10.40.17.0/24 via 10.205.58.254 dev eth0 10.74.225.0/24 via 10.205.58.254 dev eth0 10.60.131.0/24 via 10.205.58.254 dev eth0 10.60.129.0/24 via 10.205.58.254 dev eth0 10.30.160.0/24 via 10.205.58.254 dev eth0 10.61.151.0/24 via 10.205.58.254 dev eth0 10.60.100.0/24 via 10.205.58.254 dev eth0 192.168.176.0/24 via 10.205.58.254 dev eth0 192.168.252.0/24 via 10.205.58.254 dev eth0 192.168.131.50/32 via 10.205.58.254 dev eth0 10.240.178.0/24 via 10.205.58.254 dev eth0 10.240.166.2/32 via 10.205.58.254 dev eth0 10.240.188.0/24 via 10.205.58.254 dev eth0 10.240.202.0/24 via 10.205.58.254 dev eth0 10.60.100.73/32 via 10.205.58.254 dev eth0 10.60.5.133/32 via 10.205.58.254 dev eth0 | V13: Yes | W13: Dau moi dich vu: tannph | X13: Các server đã cấp nhưng chưa dùng
A14: 12 | B14: Cloud_VTT | C14: MyCC | D14: appipcc1x | E14: mycc-appipcc1x-10205058100 | F14: 10.205.58.100/24 | G14: 10.207.189.16/24 10.207.192.48/24 | H14: CentOS_7_7_final | I14: 40 | J14: 26 | K14: 60 | L14: u01: 190 | M14: 5000 | N14: VTT_SAN_2021_Q4_01 | O14: IDC7F_E08_Unity_880_1020502476_SAS | P14: 1 | Q14: 10.207.189.254 | R14: Yes | S14: anhtt69 | T14: 10.240.201.49/32 via 10.205.58.254 dev eth0 10.254.139.0/24 via 10.205.58.254 dev eth0 10.240.226.0/24 via 10.205.58.254 dev eth0 10.255.58.0/24 via 10.205.58.254 dev eth0 10.60.101.0/24 via 10.205.58.254 dev eth0 10.58.15.114/32 via 10.205.58.254 dev eth0 10.58.137.0/24 via 10.205.58.254 dev eth0 10.60.7.0/24 via 10.205.58.254 dev eth0 10.60.97.0/24 via 10.205.58.254 dev eth0 192.168.182.8/32 via 10.205.58.254 dev eth0 10.60.96.0/24 via 10.205.58.254 dev eth0 10.58.4.0/24 via 10.205.58.254 dev eth0 10.58.65.0/24 via 10.205.58.254 dev eth0 10.40.17.0/24 via 10.205.58.254 dev eth0 10.74.225.0/24 via 10.205.58.254 dev eth0 10.60.131.0/24 via 10.205.58.254 dev eth0 10.60.129.0/24 via 10.205.58.254 dev eth0 10.30.160.0/24 via 10.205.58.254 dev eth0 10.61.151.0/24 via 10.205.58.254 dev eth0 10.60.100.0/24 via 10.205.58.254 dev eth0 192.168.176.0/24 via 10.205.58.254 dev eth0 192.168.252.0/24 via 10.205.58.254 dev eth0 192.168.131.50/32 via 10.205.58.254 dev eth0 10.240.178.0/24 via 10.205.58.254 dev eth0 10.240.166.2/32 via 10.205.58.254 dev eth0 10.240.188.0/24 via 10.205.58.254 dev eth0 10.240.202.0/24 via 10.205.58.254 dev eth0 10.60.100.73/32 via 10.205.58.254 dev eth0 10.60.5.133/32 via 10.205.58.254 dev eth0 | V14: Yes | W14: Dau moi dich vu: tannph | X14: Các server đã cấp nhưng chưa dùng
A15: 13 | B15: Cloud_VTT | C15: MyCC | D15: appipcc1x | E15: mycc-appipcc1x-10205058101 | F15: 10.205.58.101/24 | G15: 10.207.189.17/24 10.207.192.49/24 | H15: CentOS_7_7_final | I15: 40 | J15: 26 | K15: 60 | L15: u01: 190 | M15: 5000 | N15: VTT_SAN_2021_Q4_01 | O15: IDC7F_E07_Unity_880_1020502474_SAS | P15: 1 | Q15: 10.207.189.254 | R15: Yes | S15: anhtt69 | T15: 10.240.201.49/32 via 10.205.58.254 dev eth0 10.254.139.0/24 via 10.205.58.254 dev eth0 10.240.226.0/24 via 10.205.58.254 dev eth0 10.255.58.0/24 via 10.205.58.254 dev eth0 10.60.101.0/24 via 10.205.58.254 dev eth0 10.58.15.114/32 via 10.205.58.254 dev eth0 10.58.137.0/24 via 10.205.58.254 dev eth0 10.60.7.0/24 via 10.205.58.254 dev eth0 10.60.97.0/24 via 10.205.58.254 dev eth0 192.168.182.8/32 via 10.205.58.254 dev eth0 10.60.96.0/24 via 10.205.58.254 dev eth0 10.58.4.0/24 via 10.205.58.254 dev eth0 10.58.65.0/24 via 10.205.58.254 dev eth0 10.40.17.0/24 via 10.205.58.254 dev eth0 10.74.225.0/24 via 10.205.58.254 dev eth0 10.60.131.0/24 via 10.205.58.254 dev eth0 10.60.129.0/24 via 10.205.58.254 dev eth0 10.30.160.0/24 via 10.205.58.254 dev eth0 10.61.151.0/24 via 10.205.58.254 dev eth0 10.60.100.0/24 via 10.205.58.254 dev eth0 192.168.176.0/24 via 10.205.58.254 dev eth0 192.168.252.0/24 via 10.205.58.254 dev eth0 192.168.131.50/32 via 10.205.58.254 dev eth0 10.240.178.0/24 via 10.205.58.254 dev eth0 10.240.166.2/32 via 10.205.58.254 dev eth0 10.240.188.0/24 via 10.205.58.254 dev eth0 10.240.202.0/24 via 10.205.58.254 dev eth0 10.60.100.73/32 via 10.205.58.254 dev eth0 10.60.5.133/32 via 10.205.58.254 dev eth0 | V15: Yes | W15: Dau moi dich vu: tannph | X15: Các server đã cấp nhưng chưa dùng
A16: 14 | B16: Cloud_VTT | C16: MyCC | D16: appipcc1x | E16: mycc-appipcc1x-10205058102 | F16: 10.205.58.102/24 | G16: 10.207.189.18/24 10.207.192.50/24 | H16: CentOS_7_7_final | I16: 40 | J16: 26 | K16: 60 | L16: u01: 190 | M16: 5000 | N16: VTT_SAN_2021_Q4_01 | O16: IDC7F_E08_Unity_880_1020502476_SAS | P16: 1 | Q16: 10.207.189.254 | R16: Yes | S16: anhtt69 | T16: 10.240.201.49/32 via 10.205.58.254 dev eth0 10.254.139.0/24 via 10.205.58.254 dev eth0 10.240.226.0/24 via 10.205.58.254 dev eth0 10.255.58.0/24 via 10.205.58.254 dev eth0 10.60.101.0/24 via 10.205.58.254 dev eth0 10.58.15.114/32 via 10.205.58.254 dev eth0 10.58.137.0/24 via 10.205.58.254 dev eth0 10.60.7.0/24 via 10.205.58.254 dev eth0 10.60.97.0/24 via 10.205.58.254 dev eth0 192.168.182.8/32 via 10.205.58.254 dev eth0 10.60.96.0/24 via 10.205.58.254 dev eth0 10.58.4.0/24 via 10.205.58.254 dev eth0 10.58.65.0/24 via 10.205.58.254 dev eth0 10.40.17.0/24 via 10.205.58.254 dev eth0 10.74.225.0/24 via 10.205.58.254 dev eth0 10.60.131.0/24 via 10.205.58.254 dev eth0 10.60.129.0/24 via 10.205.58.254 dev eth0 10.30.160.0/24 via 10.205.58.254 dev eth0 10.61.151.0/24 via 10.205.58.254 dev eth0 10.60.100.0/24 via 10.205.58.254 dev eth0 192.168.176.0/24 via 10.205.58.254 dev eth0 192.168.252.0/24 via 10.205.58.254 dev eth0 192.168.131.50/32 via 10.205.58.254 dev eth0 10.240.178.0/24 via 10.205.58.254 dev eth0 10.240.166.2/32 via 10.205.58.254 dev eth0 10.240.188.0/24 via 10.205.58.254 dev eth0 10.240.202.0/24 via 10.205.58.254 dev eth0 10.60.100.73/32 via 10.205.58.254 dev eth0 10.60.5.133/32 via 10.205.58.254 dev eth0 | V16: Yes | W16: Dau moi dich vu: tannph | X16: Các server đã cấp nhưng chưa dùng
A17: 15 | B17: Cloud_VTT | C17: MyCC | D17: appipcc1x | E17: mycc-appipcc1x-10205058103 | F17: 10.205.58.103/24 | G17: 10.207.189.19/24 10.207.192.51/24 | H17: CentOS_7_7_final | I17: 40 | J17: 26 | K17: 60 | L17: u01: 190 | M17: 5000 | N17: VTT_SAN_2021_Q4_01 | O17: IDC7F_E07_Unity_880_1020502474_SAS | P17: 1 | Q17: 10.207.189.254 | R17: Yes | S17: anhtt69 | T17: 10.240.201.49/32 via 10.205.58.254 dev eth0 10.254.139.0/24 via 10.205.58.254 dev eth0 10.240.226.0/24 via 10.205.58.254 dev eth0 10.255.58.0/24 via 10.205.58.254 dev eth0 10.60.101.0/24 via 10.205.58.254 dev eth0 10.58.15.114/32 via 10.205.58.254 dev eth0 10.58.137.0/24 via 10.205.58.254 dev eth0 10.60.7.0/24 via 10.205.58.254 dev eth0 10.60.97.0/24 via 10.205.58.254 dev eth0 192.168.182.8/32 via 10.205.58.254 dev eth0 10.60.96.0/24 via 10.205.58.254 dev eth0 10.58.4.0/24 via 10.205.58.254 dev eth0 10.58.65.0/24 via 10.205.58.254 dev eth0 10.40.17.0/24 via 10.205.58.254 dev eth0 10.74.225.0/24 via 10.205.58.254 dev eth0 10.60.131.0/24 via 10.205.58.254 dev eth0 10.60.129.0/24 via 10.205.58.254 dev eth0 10.30.160.0/24 via 10.205.58.254 dev eth0 10.61.151.0/24 via 10.205.58.254 dev eth0 10.60.100.0/24 via 10.205.58.254 dev eth0 192.168.176.0/24 via 10.205.58.254 dev eth0 192.168.252.0/24 via 10.205.58.254 dev eth0 192.168.131.50/32 via 10.205.58.254 dev eth0 10.240.178.0/24 via 10.205.58.254 dev eth0 10.240.166.2/32 via 10.205.58.254 dev eth0 10.240.188.0/24 via 10.205.58.254 dev eth0 10.240.202.0/24 via 10.205.58.254 dev eth0 10.60.100.73/32 via 10.205.58.254 dev eth0 10.60.5.133/32 via 10.205.58.254 dev eth0 | V17: Yes | W17: Dau moi dich vu: tannph | X17: Các server đã cấp nhưng chưa dùng
A18: 16 | B18: Cloud_VTT | C18: MyCC | D18: appipcc1x | E18: mycc-appipcc1x-10205058104 | F18: 10.205.58.104/24 | G18: 10.207.189.20/24 10.207.192.52/24 | H18: CentOS_7_7_final | I18: 40 | J18: 26 | K18: 60 | L18: u01: 190 | M18: 5000 | N18: VTT_SAN_2021_Q4_01 | O18: IDC7F_E08_Unity_880_1020502476_SAS | P18: 1 | Q18: 10.207.189.254 | R18: Yes | S18: anhtt69 | T18: 10.240.201.49/32 via 10.205.58.254 dev eth0 10.254.139.0/24 via 10.205.58.254 dev eth0 10.240.226.0/24 via 10.205.58.254 dev eth0 10.255.58.0/24 via 10.205.58.254 dev eth0 10.60.101.0/24 via 10.205.58.254 dev eth0 10.58.15.114/32 via 10.205.58.254 dev eth0 10.58.137.0/24 via 10.205.58.254 dev eth0 10.60.7.0/24 via 10.205.58.254 dev eth0 10.60.97.0/24 via 10.205.58.254 dev eth0 192.168.182.8/32 via 10.205.58.254 dev eth0 10.60.96.0/24 via 10.205.58.254 dev eth0 10.58.4.0/24 via 10.205.58.254 dev eth0 10.58.65.0/24 via 10.205.58.254 dev eth0 10.40.17.0/24 via 10.205.58.254 dev eth0 10.74.225.0/24 via 10.205.58.254 dev eth0 10.60.131.0/24 via 10.205.58.254 dev eth0 10.60.129.0/24 via 10.205.58.254 dev eth0 10.30.160.0/24 via 10.205.58.254 dev eth0 10.61.151.0/24 via 10.205.58.254 dev eth0 10.60.100.0/24 via 10.205.58.254 dev eth0 192.168.176.0/24 via 10.205.58.254 dev eth0 192.168.252.0/24 via 10.205.58.254 dev eth0 192.168.131.50/32 via 10.205.58.254 dev eth0 10.240.178.0/24 via 10.205.58.254 dev eth0 10.240.166.2/32 via 10.205.58.254 dev eth0 10.240.188.0/24 via 10.205.58.254 dev eth0 10.240.202.0/24 via 10.205.58.254 dev eth0 10.60.100.73/32 via 10.205.58.254 dev eth0 10.60.5.133/32 via 10.205.58.254 dev eth0 | V18: Yes | W18: Dau moi dich vu: tannph | X18: Các server đã cấp nhưng chưa dùng
A19: 17 | B19: Cloud_VTT | C19: MyCC | D19: appipcc1x | E19: mycc-appipcc1x-10205058105 | F19: 10.205.58.105/24 | G19: 10.207.189.21/24 10.207.192.53/24 | H19: CentOS_7_7_final | I19: 40 | J19: 26 | K19: 60 | L19: u01: 190 | M19: 5000 | N19: VTT_SAN_2021_Q4_01 | O19: IDC7F_E07_Unity_880_1020502474_SAS | P19: 1 | Q19: 10.207.189.254 | R19: Yes | S19: anhtt69 | T19: 10.240.201.49/32 via 10.205.58.254 dev eth0 10.254.139.0/24 via 10.205.58.254 dev eth0 10.240.226.0/24 via 10.205.58.254 dev eth0 10.255.58.0/24 via 10.205.58.254 dev eth0 10.60.101.0/24 via 10.205.58.254 dev eth0 10.58.15.114/32 via 10.205.58.254 dev eth0 10.58.137.0/24 via 10.205.58.254 dev eth0 10.60.7.0/24 via 10.205.58.254 dev eth0 10.60.97.0/24 via 10.205.58.254 dev eth0 192.168.182.8/32 via 10.205.58.254 dev eth0 10.60.96.0/24 via 10.205.58.254 dev eth0 10.58.4.0/24 via 10.205.58.254 dev eth0 10.58.65.0/24 via 10.205.58.254 dev eth0 10.40.17.0/24 via 10.205.58.254 dev eth0 10.74.225.0/24 via 10.205.58.254 dev eth0 10.60.131.0/24 via 10.205.58.254 dev eth0 10.60.129.0/24 via 10.205.58.254 dev eth0 10.30.160.0/24 via 10.205.58.254 dev eth0 10.61.151.0/24 via 10.205.58.254 dev eth0 10.60.100.0/24 via 10.205.58.254 dev eth0 192.168.176.0/24 via 10.205.58.254 dev eth0 192.168.252.0/24 via 10.205.58.254 dev eth0 192.168.131.50/32 via 10.205.58.254 dev eth0 10.240.178.0/24 via 10.205.58.254 dev eth0 10.240.166.2/32 via 10.205.58.254 dev eth0 10.240.188.0/24 via 10.205.58.254 dev eth0 10.240.202.0/24 via 10.205.58.254 dev eth0 10.60.100.73/32 via 10.205.58.254 dev eth0 10.60.5.133/32 via 10.205.58.254 dev eth0 | V19: Yes | W19: Dau moi dich vu: tannph | X19: Các server đã cấp nhưng chưa dùng
A20: 18 | B20: Cloud_VTT | C20: MyCC | D20: appipcc1x | E20: mycc-appipcc1x-10205058106 | F20: 10.205.58.106/24 | G20: 10.207.189.22/24 10.207.192.54/24 | H20: CentOS_7_7_final | I20: 40 | J20: 26 | K20: 60 | L20: u01: 190 | M20: 5000 | N20: VTT_SAN_2021_Q4_01 | O20: IDC7F_E08_Unity_880_1020502476_SAS | P20: 1 | Q20: 10.207.189.254 | R20: Yes | S20: anhtt69 | T20: 10.240.201.49/32 via 10.205.58.254 dev eth0 10.254.139.0/24 via 10.205.58.254 dev eth0 10.240.226.0/24 via 10.205.58.254 dev eth0 10.255.58.0/24 via 10.205.58.254 dev eth0 10.60.101.0/24 via 10.205.58.254 dev eth0 10.58.15.114/32 via 10.205.58.254 dev eth0 10.58.137.0/24 via 10.205.58.254 dev eth0 10.60.7.0/24 via 10.205.58.254 dev eth0 10.60.97.0/24 via 10.205.58.254 dev eth0 192.168.182.8/32 via 10.205.58.254 dev eth0 10.60.96.0/24 via 10.205.58.254 dev eth0 10.58.4.0/24 via 10.205.58.254 dev eth0 10.58.65.0/24 via 10.205.58.254 dev eth0 10.40.17.0/24 via 10.205.58.254 dev eth0 10.74.225.0/24 via 10.205.58.254 dev eth0 10.60.131.0/24 via 10.205.58.254 dev eth0 10.60.129.0/24 via 10.205.58.254 dev eth0 10.30.160.0/24 via 10.205.58.254 dev eth0 10.61.151.0/24 via 10.205.58.254 dev eth0 10.60.100.0/24 via 10.205.58.254 dev eth0 192.168.176.0/24 via 10.205.58.254 dev eth0 192.168.252.0/24 via 10.205.58.254 dev eth0 192.168.131.50/32 via 10.205.58.254 dev eth0 10.240.178.0/24 via 10.205.58.254 dev eth0 10.240.166.2/32 via 10.205.58.254 dev eth0 10.240.188.0/24 via 10.205.58.254 dev eth0 10.240.202.0/24 via 10.205.58.254 dev eth0 10.60.100.73/32 via 10.205.58.254 dev eth0 10.60.5.133/32 via 10.205.58.254 dev eth0 | V20: Yes | W20: Dau moi dich vu: tannph | X20: Các server đã cấp nhưng chưa dùng
... A22: 20 | B22: Cloud_VTT | C22: MyCC | D22: appipcc1x | E22: mycc-appipcc1x-10205058108 | F22: 10.205.58.108/24 | G22: 10.207.189.24/24 10.207.192.56/24 | H22: CentOS_7_7_final | I22: 40 | J22: 26 | K22: 60 | L22: u01: 190 | M22: 5000 | N22: VTT_SAN_2021_Q4_01 | O22: IDC7F_E08_Unity_880_1020502476_SAS | P22: 1 | Q22: 10.207.189.254 | R22: Yes | S22: anhtt69 | T22: 10.240.201.49/32 via 10.205.58.254 dev eth0 10.254.139.0/24 via 10.205.58.254 dev eth0 10.240.226.0/24 via 10.205.58.254 dev eth0 10.255.58.0/24 via 10.205.58.254 dev eth0 10.60.101.0/24 via 10.205.58.254 dev eth0 10.58.15.114/32 via 10.205.58.254 dev eth0 10.58.137.0/24 via 10.205.58.254 dev eth0 10.60.7.0/24 via 10.205.58.254 dev eth0 10.60.97.0/24 via 10.205.58.254 dev eth0 192.168.182.8/32 via 10.205.58.254 dev eth0 10.60.96.0/24 via 10.205.58.254 dev eth0 10.58.4.0/24 via 10.205.58.254 dev eth0 10.58.65.0/24 via 10.205.58.254 dev eth0 10.40.17.0/24 via 10.205.58.254 dev eth0 10.74.225.0/24 via 10.205.58.254 dev eth0 10.60.131.0/24 via 10.205.58.254 dev eth0 10.60.129.0/24 via 10.205.58.254 dev eth0 10.30.160.0/24 via 10.205.58.254 dev eth0 10.61.151.0/24 via 10.205.58.254 dev eth0 10.60.100.0/24 via 10.205.58.254 dev eth0 192.168.176.0/24 via 10.205.58.254 dev eth0 192.168.252.0/24 via 10.205.58.254 dev eth0 192.168.131.50/32 via 10.205.58.254 dev eth0 10.240.178.0/24 via 10.205.58.254 dev eth0 10.240.166.2/32 via 10.205.58.254 dev eth0 10.240.188.0/24 via 10.205.58.254 dev eth0 10.240.202.0/24 via 10.205.58.254 dev eth0 10.60.100.73/32 via 10.205.58.254 dev eth0 10.60.5.133/32 via 10.205.58.254 dev eth0 | V22: Yes | W22: Dau moi dich vu: tannph | X22: Các server đã cấp nhưng chưa dùng
A23: 21 | B23: Cloud_VTT | C23: MyCC | D23: appipcc1x | E23: mycc-appipcc1x-10205058109 | F23: 10.205.58.109/24 | G23: 10.207.189.25/24 10.207.192.57/24 | H23: CentOS_7_7_final | I23: 40 | J23: 26 | K23: 60 | L23: u01: 190 | M23: 5000 | N23: VTT_SAN_2021_Q4_01 | O23: IDC7F_E07_Unity_880_1020502474_SAS | P23: 1 | Q23: 10.207.189.254 | R23: Yes | S23: anhtt69 | T23: 10.240.201.49/32 via 10.205.58.254 dev eth0 10.254.139.0/24 via 10.205.58.254 dev eth0 10.240.226.0/24 via 10.205.58.254 dev eth0 10.255.58.0/24 via 10.205.58.254 dev eth0 10.60.101.0/24 via 10.205.58.254 dev eth0 10.58.15.114/32 via 10.205.58.254 dev eth0 10.58.137.0/24 via 10.205.58.254 dev eth0 10.60.7.0/24 via 10.205.58.254 dev eth0 10.60.97.0/24 via 10.205.58.254 dev eth0 192.168.182.8/32 via 10.205.58.254 dev eth0 10.60.96.0/24 via 10.205.58.254 dev eth0 10.58.4.0/24 via 10.205.58.254 dev eth0 10.58.65.0/24 via 10.205.58.254 dev eth0 10.40.17.0/24 via 10.205.58.254 dev eth0 10.74.225.0/24 via 10.205.58.254 dev eth0 10.60.131.0/24 via 10.205.58.254 dev eth0 10.60.129.0/24 via 10.205.58.254 dev eth0 10.30.160.0/24 via 10.205.58.254 dev eth0 10.61.151.0/24 via 10.205.58.254 dev eth0 10.60.100.0/24 via 10.205.58.254 dev eth0 192.168.176.0/24 via 10.205.58.254 dev eth0 192.168.252.0/24 via 10.205.58.254 dev eth0 192.168.131.50/32 via 10.205.58.254 dev eth0 10.240.178.0/24 via 10.205.58.254 dev eth0 10.240.166.2/32 via 10.205.58.254 dev eth0 10.240.188.0/24 via 10.205.58.254 dev eth0 10.240.202.0/24 via 10.205.58.254 dev eth0 10.60.100.73/32 via 10.205.58.254 dev eth0 10.60.5.133/32 via 10.205.58.254 dev eth0 | W23: Dau moi dich vu: tannph | X23: Các server đã cấp nhưng chưa dùng
A24: 22 | B24: Cloud_VTT | C24: MyCC | D24: appipcc1x | E24: mycc-appipcc1x-10205058110 | F24: 10.205.58.110/24 | G24: 10.207.189.26/24 10.207.192.58/24 | H24: CentOS_7_7_final | I24: 40 | J24: 26 | K24: 60 | L24: u01: 190 | M24: 5000 | N24: VTT_SAN_2021_Q4_01 | O24: IDC7F_E08_Unity_880_1020502476_SAS | P24: 1 | Q24: 10.207.189.254 | R24: Yes | S24: anhtt69 | T24: 10.240.201.49/32 via 10.205.58.254 dev eth0 10.254.139.0/24 via 10.205.58.254 dev eth0 10.240.226.0/24 via 10.205.58.254 dev eth0 10.255.58.0/24 via 10.205.58.254 dev eth0 10.60.101.0/24 via 10.205.58.254 dev eth0 10.58.15.114/32 via 10.205.58.254 dev eth0 10.58.137.0/24 via 10.205.58.254 dev eth0 10.60.7.0/24 via 10.205.58.254 dev eth0 10.60.97.0/24 via 10.205.58.254 dev eth0 192.168.182.8/32 via 10.205.58.254 dev eth0 10.60.96.0/24 via 10.205.58.254 dev eth0 10.58.4.0/24 via 10.205.58.254 dev eth0 10.58.65.0/24 via 10.205.58.254 dev eth0 10.40.17.0/24 via 10.205.58.254 dev eth0 10.74.225.0/24 via 10.205.58.254 dev eth0 10.60.131.0/24 via 10.205.58.254 dev eth0 10.60.129.0/24 via 10.205.58.254 dev eth0 10.30.160.0/24 via 10.205.58.254 dev eth0 10.61.151.0/24 via 10.205.58.254 dev eth0 10.60.100.0/24 via 10.205.58.254 dev eth0 192.168.176.0/24 via 10.205.58.254 dev eth0 192.168.252.0/24 via 10.205.58.254 dev eth0 192.168.131.50/32 via 10.205.58.254 dev eth0 10.240.178.0/24 via 10.205.58.254 dev eth0 10.240.166.2/32 via 10.205.58.254 dev eth0 10.240.188.0/24 via 10.205.58.254 dev eth0 10.240.202.0/24 via 10.205.58.254 dev eth0 10.60.100.73/32 via 10.205.58.254 dev eth0 10.60.5.133/32 via 10.205.58.254 dev eth0 | W24: Dau moi dich vu: tannph | X24: Các server đã cấp nhưng chưa dùng
A25: 23 | B25: Cloud_VTT | C25: MyCC | D25: appipcc1x | E25: mycc-appipcc1x-10205058111 | F25: 10.205.58.111/24 | G25: 10.207.189.27/24 10.207.192.59/24 | H25: CentOS_7_7_final | I25: 40 | J25: 26 | K25: 60 | L25: u01: 190 | M25: 5000 | N25: VTT_SAN_2021_Q4_01 | O25: IDC7F_E07_Unity_880_1020502474_SAS | P25: 1 | Q25: 10.207.189.254 | R25: Yes | S25: anhtt69 | T25: 10.240.201.49/32 via 10.205.58.254 dev eth0 10.254.139.0/24 via 10.205.58.254 dev eth0 10.240.226.0/24 via 10.205.58.254 dev eth0 10.255.58.0/24 via 10.205.58.254 dev eth0 10.60.101.0/24 via 10.205.58.254 dev eth0 10.58.15.114/32 via 10.205.58.254 dev eth0 10.58.137.0/24 via 10.205.58.254 dev eth0 10.60.7.0/24 via 10.205.58.254 dev eth0 10.60.97.0/24 via 10.205.58.254 dev eth0 192.168.182.8/32 via 10.205.58.254 dev eth0 10.60.96.0/24 via 10.205.58.254 dev eth0 10.58.4.0/24 via 10.205.58.254 dev eth0 10.58.65.0/24 via 10.205.58.254 dev eth0 10.40.17.0/24 via 10.205.58.254 dev eth0 10.74.225.0/24 via 10.205.58.254 dev eth0 10.60.131.0/24 via 10.205.58.254 dev eth0 10.60.129.0/24 via 10.205.58.254 dev eth0 10.30.160.0/24 via 10.205.58.254 dev eth0 10.61.151.0/24 via 10.205.58.254 dev eth0 10.60.100.0/24 via 10.205.58.254 dev eth0 192.168.176.0/24 via 10.205.58.254 dev eth0 192.168.252.0/24 via 10.205.58.254 dev eth0 192.168.131.50/32 via 10.205.58.254 dev eth0 10.240.178.0/24 via 10.205.58.254 dev eth0 10.240.166.2/32 via 10.205.58.254 dev eth0 10.240.188.0/24 via 10.205.58.254 dev eth0 10.240.202.0/24 via 10.205.58.254 dev eth0 10.60.100.73/32 via 10.205.58.254 dev eth0 10.60.5.133/32 via 10.205.58.254 dev eth0 | W25: Dau moi dich vu: tannph | X25: Các server đã cấp nhưng chưa dùng
A26: 24 | B26: Cloud_VTT | C26: MyCC | D26: appipcc1x | E26: mycc-appipcc1x-10205058112 | F26: 10.205.58.112/24 | G26: 10.207.189.28/24 10.207.192.60/24 | H26: CentOS_7_7_final | I26: 40 | J26: 26 | K26: 60 | L26: u01: 190 | M26: 5000 | N26: VTT_SAN_2021_Q4_01 | O26: IDC7F_E08_Unity_880_1020502476_SAS | P26: 1 | Q26: 10.207.189.254 | R26: Yes | S26: anhtt69 | T26: 10.240.201.49/32 via 10.205.58.254 dev eth0 10.254.139.0/24 via 10.205.58.254 dev eth0 10.240.226.0/24 via 10.205.58.254 dev eth0 10.255.58.0/24 via 10.205.58.254 dev eth0 10.60.101.0/24 via 10.205.58.254 dev eth0 10.58.15.114/32 via 10.205.58.254 dev eth0 10.58.137.0/24 via 10.205.58.254 dev eth0 10.60.7.0/24 via 10.205.58.254 dev eth0 10.60.97.0/24 via 10.205.58.254 dev eth0 192.168.182.8/32 via 10.205.58.254 dev eth0 10.60.96.0/24 via 10.205.58.254 dev eth0 10.58.4.0/24 via 10.205.58.254 dev eth0 10.58.65.0/24 via 10.205.58.254 dev eth0 10.40.17.0/24 via 10.205.58.254 dev eth0 10.74.225.0/24 via 10.205.58.254 dev eth0 10.60.131.0/24 via 10.205.58.254 dev eth0 10.60.129.0/24 via 10.205.58.254 dev eth0 10.30.160.0/24 via 10.205.58.254 dev eth0 10.61.151.0/24 via 10.205.58.254 dev eth0 10.60.100.0/24 via 10.205.58.254 dev eth0 192.168.176.0/24 via 10.205.58.254 dev eth0 192.168.252.0/24 via 10.205.58.254 dev eth0 192.168.131.50/32 via 10.205.58.254 dev eth0 10.240.178.0/24 via 10.205.58.254 dev eth0 10.240.166.2/32 via 10.205.58.254 dev eth0 10.240.188.0/24 via 10.205.58.254 dev eth0 10.240.202.0/24 via 10.205.58.254 dev eth0 10.60.100.73/32 via 10.205.58.254 dev eth0 10.60.5.133/32 via 10.205.58.254 dev eth0 | W26: Dau moi dich vu: tannph | X26: Các server đã cấp nhưng chưa dùng
A27: 25 | B27: Cloud_VTT | C27: MyCC | D27: appipcc1x | E27: mycc-appipcc1x-10205058113 | F27: 10.205.58.113/24 | G27: 10.207.189.29/24 10.207.192.61/24 | H27: CentOS_7_7_final | I27: 40 | J27: 26 | K27: 60 | L27: u01: 190 | M27: 5000 | N27: VTT_SAN_2021_Q4_01 | O27: IDC7F_E07_Unity_880_1020502474_SAS | P27: 1 | Q27: 10.207.189.254 | R27: Yes | S27: anhtt69 | T27: 10.240.201.49/32 via 10.205.58.254 dev eth0 10.254.139.0/24 via 10.205.58.254 dev eth0 10.240.226.0/24 via 10.205.58.254 dev eth0 10.255.58.0/24 via 10.205.58.254 dev eth0 10.60.101.0/24 via 10.205.58.254 dev eth0 10.58.15.114/32 via 10.205.58.254 dev eth0 10.58.137.0/24 via 10.205.58.254 dev eth0 10.60.7.0/24 via 10.205.58.254 dev eth0 10.60.97.0/24 via 10.205.58.254 dev eth0 192.168.182.8/32 via 10.205.58.254 dev eth0 10.60.96.0/24 via 10.205.58.254 dev eth0 10.58.4.0/24 via 10.205.58.254 dev eth0 10.58.65.0/24 via 10.205.58.254 dev eth0 10.40.17.0/24 via 10.205.58.254 dev eth0 10.74.225.0/24 via 10.205.58.254 dev eth0 10.60.131.0/24 via 10.205.58.254 dev eth0 10.60.129.0/24 via 10.205.58.254 dev eth0 10.30.160.0/24 via 10.205.58.254 dev eth0 10.61.151.0/24 via 10.205.58.254 dev eth0 10.60.100.0/24 via 10.205.58.254 dev eth0 192.168.176.0/24 via 10.205.58.254 dev eth0 192.168.252.0/24 via 10.205.58.254 dev eth0 192.168.131.50/32 via 10.205.58.254 dev eth0 10.240.178.0/24 via 10.205.58.254 dev eth0 10.240.166.2/32 via 10.205.58.254 dev eth0 10.240.188.0/24 via 10.205.58.254 dev eth0 10.240.202.0/24 via 10.205.58.254 dev eth0 10.60.100.73/32 via 10.205.58.254 dev eth0 10.60.5.133/32 via 10.205.58.254 dev eth0 | W27: Dau moi dich vu: tannph | X27: Các server đã cấp nhưng chưa dùng
A28: 26 | B28: Cloud_VTT | C28: MyCC | D28: appipcc1x | E28: mycc-appipcc1x-10205058114 | F28: 10.205.58.114/24 | G28: 10.207.189.30/24 10.207.192.62/24 | H28: CentOS_7_7_final | I28: 40 | J28: 26 | K28: 60 | L28: u01: 190 | M28: 5000 | N28: VTT_SAN_2021_Q4_01 | O28: IDC7F_E08_Unity_880_1020502476_SAS | P28: 1 | Q28: 10.207.189.254 | R28: Yes | S28: anhtt69 | T28: 10.240.201.49/32 via 10.205.58.254 dev eth0 10.254.139.0/24 via 10.205.58.254 dev eth0 10.240.226.0/24 via 10.205.58.254 dev eth0 10.255.58.0/24 via 10.205.58.254 dev eth0 10.60.101.0/24 via 10.205.58.254 dev eth0 10.58.15.114/32 via 10.205.58.254 dev eth0 10.58.137.0/24 via 10.205.58.254 dev eth0 10.60.7.0/24 via 10.205.58.254 dev eth0 10.60.97.0/24 via 10.205.58.254 dev eth0 192.168.182.8/32 via 10.205.58.254 dev eth0 10.60.96.0/24 via 10.205.58.254 dev eth0 10.58.4.0/24 via 10.205.58.254 dev eth0 10.58.65.0/24 via 10.205.58.254 dev eth0 10.40.17.0/24 via 10.205.58.254 dev eth0 10.74.225.0/24 via 10.205.58.254 dev eth0 10.60.131.0/24 via 10.205.58.254 dev eth0 10.60.129.0/24 via 10.205.58.254 dev eth0 10.30.160.0/24 via 10.205.58.254 dev eth0 10.61.151.0/24 via 10.205.58.254 dev eth0 10.60.100.0/24 via 10.205.58.254 dev eth0 192.168.176.0/24 via 10.205.58.254 dev eth0 192.168.252.0/24 via 10.205.58.254 dev eth0 192.168.131.50/32 via 10.205.58.254 dev eth0 10.240.178.0/24 via 10.205.58.254 dev eth0 10.240.166.2/32 via 10.205.58.254 dev eth0 10.240.188.0/24 via 10.205.58.254 dev eth0 10.240.202.0/24 via 10.205.58.254 dev eth0 10.60.100.73/32 via 10.205.58.254 dev eth0 10.60.5.133/32 via 10.205.58.254 dev eth0 | W28: Dau moi dich vu: tannph | X28: Các server đã cấp nhưng chưa dùng
A29: 27 | B29: Cloud_VTT | C29: MyCC | D29: appipcc3x | E29: mycc-appipcc3x-10205058115 | F29: 10.205.58.115/24 | G29: 10.207.189.31/24 10.207.192.63/24 | H29: CentOS_7_7_final | I29: 28 | J29: 80 | K29: 60 | L29: u01: 510 | N29: VTT_SAN_2021_Q4_01 | O29: IDC7F_E07_Unity_880_1020502474_SAS | P29: 1 | Q29: 10.207.189.254 | R29: Yes | S29: anhtt69 | T29: 10.240.201.49/32 via 10.205.58.254 dev eth0 10.254.139.0/24 via 10.205.58.254 dev eth0 10.240.226.0/24 via 10.205.58.254 dev eth0 10.255.58.0/24 via 10.205.58.254 dev eth0 10.60.101.0/24 via 10.205.58.254 dev eth0 10.58.15.114/32 via 10.205.58.254 dev eth0 10.58.137.0/24 via 10.205.58.254 dev eth0 10.60.7.0/24 via 10.205.58.254 dev eth0 10.60.97.0/24 via 10.205.58.254 dev eth0 192.168.182.8/32 via 10.205.58.254 dev eth0 10.60.96.0/24 via 10.205.58.254 dev eth0 10.58.4.0/24 via 10.205.58.254 dev eth0 10.58.65.0/24 via 10.205.58.254 dev eth0 10.40.17.0/24 via 10.205.58.254 dev eth0 10.74.225.0/24 via 10.205.58.254 dev eth0 10.60.131.0/24 via 10.205.58.254 dev eth0 10.60.129.0/24 via 10.205.58.254 dev eth0 10.30.160.0/24 via 10.205.58.254 dev eth0 10.61.151.0/24 via 10.205.58.254 dev eth0 10.60.100.0/24 via 10.205.58.254 dev eth0 192.168.176.0/24 via 10.205.58.254 dev eth0 192.168.252.0/24 via 10.205.58.254 dev eth0 192.168.131.50/32 via 10.205.58.254 dev eth0 10.240.178.0/24 via 10.205.58.254 dev eth0 10.240.166.2/32 via 10.205.58.254 dev eth0 10.240.188.0/24 via 10.205.58.254 dev eth0 10.240.202.0/24 via 10.205.58.254 dev eth0 10.60.100.73/32 via 10.205.58.254 dev eth0 10.60.5.133/32 via 10.205.58.254 dev eth0 | W29: Dau moi dich vu: tannph | X29: Các server đã cấp nhưng chưa dùng
A30: 28 | B30: Cloud_VTT | C30: MyCC | D30: appipcc3x | E30: mycc-appipcc3x-10205058116 | F30: 10.205.58.116/24 | G30: 10.207.189.32/24 10.207.192.64/24 | H30: CentOS_7_7_final | I30: 28 | J30: 80 | K30: 60 | L30: u01: 510 | N30: VTT_SAN_2021_Q4_01 | O30: IDC7F_E08_Unity_880_1020502476_SAS | P30: 1 | Q30: 10.207.189.254 | R30: Yes | S30: anhtt69 | T30: 10.240.201.49/32 via 10.205.58.254 dev eth0 10.254.139.0/24 via 10.205.58.254 dev eth0 10.240.226.0/24 via 10.205.58.254 dev eth0 10.255.58.0/24 via 10.205.58.254 dev eth0 10.60.101.0/24 via 10.205.58.254 dev eth0 10.58.15.114/32 via 10.205.58.254 dev eth0 10.58.137.0/24 via 10.205.58.254 dev eth0 10.60.7.0/24 via 10.205.58.254 dev eth0 10.60.97.0/24 via 10.205.58.254 dev eth0 192.168.182.8/32 via 10.205.58.254 dev eth0 10.60.96.0/24 via 10.205.58.254 dev eth0 10.58.4.0/24 via 10.205.58.254 dev eth0 10.58.65.0/24 via 10.205.58.254 dev eth0 10.40.17.0/24 via 10.205.58.254 dev eth0 10.74.225.0/24 via 10.205.58.254 dev eth0 10.60.131.0/24 via 10.205.58.254 dev eth0 10.60.129.0/24 via 10.205.58.254 dev eth0 10.30.160.0/24 via 10.205.58.254 dev eth0 10.61.151.0/24 via 10.205.58.254 dev eth0 10.60.100.0/24 via 10.205.58.254 dev eth0 192.168.176.0/24 via 10.205.58.254 dev eth0 192.168.252.0/24 via 10.205.58.254 dev eth0 192.168.131.50/32 via 10.205.58.254 dev eth0 10.240.178.0/24 via 10.205.58.254 dev eth0 10.240.166.2/32 via 10.205.58.254 dev eth0 10.240.188.0/24 via 10.205.58.254 dev eth0 10.240.202.0/24 via 10.205.58.254 dev eth0 10.60.100.73/32 via 10.205.58.254 dev eth0 10.60.5.133/32 via 10.205.58.254 dev eth0 | W30: Dau moi dich vu: tannph | X30: Các server đã cấp nhưng chưa dùng
A31: 29 | B31: Cloud_VTT | C31: MyCC | D31: appipcc3x | E31: mycc-appipcc3x-10205058117 | F31: 10.205.58.117/24 | G31: 10.207.189.33/24 10.207.192.65/24 | H31: CentOS_7_7_final | I31: 28 | J31: 80 | K31: 60 | L31: u01: 510 | N31: VTT_SAN_2021_Q4_01 | O31: IDC7F_E07_Unity_880_1020502474_SAS | P31: 1 | Q31: 10.207.189.254 | R31: Yes | S31: anhtt69 | T31: 10.240.201.49/32 via 10.205.58.254 dev eth0 10.254.139.0/24 via 10.205.58.254 dev eth0 10.240.226.0/24 via 10.205.58.254 dev eth0 10.255.58.0/24 via 10.205.58.254 dev eth0 10.60.101.0/24 via 10.205.58.254 dev eth0 10.58.15.114/32 via 10.205.58.254 dev eth0 10.58.137.0/24 via 10.205.58.254 dev eth0 10.60.7.0/24 via 10.205.58.254 dev eth0 10.60.97.0/24 via 10.205.58.254 dev eth0 192.168.182.8/32 via 10.205.58.254 dev eth0 10.60.96.0/24 via 10.205.58.254 dev eth0 10.58.4.0/24 via 10.205.58.254 dev eth0 10.58.65.0/24 via 10.205.58.254 dev eth0 10.40.17.0/24 via 10.205.58.254 dev eth0 10.74.225.0/24 via 10.205.58.254 dev eth0 10.60.131.0/24 via 10.205.58.254 dev eth0 10.60.129.0/24 via 10.205.58.254 dev eth0 10.30.160.0/24 via 10.205.58.254 dev eth0 10.61.151.0/24 via 10.205.58.254 dev eth0 10.60.100.0/24 via 10.205.58.254 dev eth0 192.168.176.0/24 via 10.205.58.254 dev eth0 192.168.252.0/24 via 10.205.58.254 dev eth0 192.168.131.50/32 via 10.205.58.254 dev eth0 10.240.178.0/24 via 10.205.58.254 dev eth0 10.240.166.2/32 via 10.205.58.254 dev eth0 10.240.188.0/24 via 10.205.58.254 dev eth0 10.240.202.0/24 via 10.205.58.254 dev eth0 10.60.100.73/32 via 10.205.58.254 dev eth0 10.60.5.133/32 via 10.205.58.254 dev eth0 | W31: Dau moi dich vu: tannph | X31: Các server đã cấp nhưng chưa dùng
A32: 30 | B32: Cloud_VTT | C32: MyCC | D32: appipcc3x | E32: mycc-appipcc3x-10205058118 | F32: 10.205.58.118/24 | G32: 10.207.189.34/24 10.207.192.66/24 | H32: CentOS_7_7_final | I32: 28 | J32: 80 | K32: 60 | L32: u01: 510 | N32: VTT_SAN_2021_Q4_01 | O32: IDC7F_E08_Unity_880_1020502476_SAS | P32: 1 | Q32: 10.207.189.254 | R32: Yes | S32: anhtt69 | T32: 10.240.201.49/32 via 10.205.58.254 dev eth0 10.254.139.0/24 via 10.205.58.254 dev eth0 10.240.226.0/24 via 10.205.58.254 dev eth0 10.255.58.0/24 via 10.205.58.254 dev eth0 10.60.101.0/24 via 10.205.58.254 dev eth0 10.58.15.114/32 via 10.205.58.254 dev eth0 10.58.137.0/24 via 10.205.58.254 dev eth0 10.60.7.0/24 via 10.205.58.254 dev eth0 10.60.97.0/24 via 10.205.58.254 dev eth0 192.168.182.8/32 via 10.205.58.254 dev eth0 10.60.96.0/24 via 10.205.58.254 dev eth0 10.58.4.0/24 via 10.205.58.254 dev eth0 10.58.65.0/24 via 10.205.58.254 dev eth0 10.40.17.0/24 via 10.205.58.254 dev eth0 10.74.225.0/24 via 10.205.58.254 dev eth0 10.60.131.0/24 via 10.205.58.254 dev eth0 10.60.129.0/24 via 10.205.58.254 dev eth0 10.30.160.0/24 via 10.205.58.254 dev eth0 10.61.151.0/24 via 10.205.58.254 dev eth0 10.60.100.0/24 via 10.205.58.254 dev eth0 192.168.176.0/24 via 10.205.58.254 dev eth0 192.168.252.0/24 via 10.205.58.254 dev eth0 192.168.131.50/32 via 10.205.58.254 dev eth0 10.240.178.0/24 via 10.205.58.254 dev eth0 10.240.166.2/32 via 10.205.58.254 dev eth0 10.240.188.0/24 via 10.205.58.254 dev eth0 10.240.202.0/24 via 10.205.58.254 dev eth0 10.60.100.73/32 via 10.205.58.254 dev eth0 10.60.5.133/32 via 10.205.58.254 dev eth0 | W32: Dau moi dich vu: tannph | X32: Các server đã cấp nhưng chưa dùng
A33: 31 | B33: Cloud_VTT | C33: MyCC | D33: appipcc3x | E33: mycc-appipcc3x-10205058119 | F33: 10.205.58.119/24 | G33: 10.207.189.35/24 10.207.192.67/24 | H33: CentOS_7_7_final | I33: 28 | J33: 80 | K33: 60 | L33: u01: 510 | N33: VTT_SAN_2021_Q4_01 | O33: IDC7F_E07_Unity_880_1020502474_SAS | P33: 1 | Q33: 10.207.189.254 | R33: Yes | S33: anhtt69 | T33: 10.240.201.49/32 via 10.205.58.254 dev eth0 10.254.139.0/24 via 10.205.58.254 dev eth0 10.240.226.0/24 via 10.205.58.254 dev eth0 10.255.58.0/24 via 10.205.58.254 dev eth0 10.60.101.0/24 via 10.205.58.254 dev eth0 10.58.15.114/32 via 10.205.58.254 dev eth0 10.58.137.0/24 via 10.205.58.254 dev eth0 10.60.7.0/24 via 10.205.58.254 dev eth0 10.60.97.0/24 via 10.205.58.254 dev eth0 192.168.182.8/32 via 10.205.58.254 dev eth0 10.60.96.0/24 via 10.205.58.254 dev eth0 10.58.4.0/24 via 10.205.58.254 dev eth0 10.58.65.0/24 via 10.205.58.254 dev eth0 10.40.17.0/24 via 10.205.58.254 dev eth0 10.74.225.0/24 via 10.205.58.254 dev eth0 10.60.131.0/24 via 10.205.58.254 dev eth0 10.60.129.0/24 via 10.205.58.254 dev eth0 10.30.160.0/24 via 10.205.58.254 dev eth0 10.61.151.0/24 via 10.205.58.254 dev eth0 10.60.100.0/24 via 10.205.58.254 dev eth0 192.168.176.0/24 via 10.205.58.254 dev eth0 192.168.252.0/24 via 10.205.58.254 dev eth0 192.168.131.50/32 via 10.205.58.254 dev eth0 10.240.178.0/24 via 10.205.58.254 dev eth0 10.240.166.2/32 via 10.205.58.254 dev eth0 10.240.188.0/24 via 10.205.58.254 dev eth0 10.240.202.0/24 via 10.205.58.254 dev eth0 10.60.100.73/32 via 10.205.58.254 dev eth0 10.60.5.133/32 via 10.205.58.254 dev eth0 | W33: Dau moi dich vu: tannph | X33: Các server đã cấp nhưng chưa dùng
A34: 32 | B34: Cloud_VTT | C34: MyCC | D34: appipcc3x | E34: mycc-appipcc3x-10205058120 | F34: 10.205.58.120/24 | G34: 10.207.189.36/24 10.207.192.68/24 | H34: CentOS_7_7_final | I34: 28 | J34: 80 | K34: 60 | L34: u01: 510 | N34: VTT_SAN_2021_Q4_01 | O34: IDC7F_E08_Unity_880_1020502476_SAS | P34: 1 | Q34: 10.207.189.254 | R34: Yes | S34: anhtt69 | T34: 10.240.201.49/32 via 10.205.58.254 dev eth0 10.254.139.0/24 via 10.205.58.254 dev eth0 10.240.226.0/24 via 10.205.58.254 dev eth0 10.255.58.0/24 via 10.205.58.254 dev eth0 10.60.101.0/24 via 10.205.58.254 dev eth0 10.58.15.114/32 via 10.205.58.254 dev eth0 10.58.137.0/24 via 10.205.58.254 dev eth0 10.60.7.0/24 via 10.205.58.254 dev eth0 10.60.97.0/24 via 10.205.58.254 dev eth0 192.168.182.8/32 via 10.205.58.254 dev eth0 10.60.96.0/24 via 10.205.58.254 dev eth0 10.58.4.0/24 via 10.205.58.254 dev eth0 10.58.65.0/24 via 10.205.58.254 dev eth0 10.40.17.0/24 via 10.205.58.254 dev eth0 10.74.225.0/24 via 10.205.58.254 dev eth0 10.60.131.0/24 via 10.205.58.254 dev eth0 10.60.129.0/24 via 10.205.58.254 dev eth0 10.30.160.0/24 via 10.205.58.254 dev eth0 10.61.151.0/24 via 10.205.58.254 dev eth0 10.60.100.0/24 via 10.205.58.254 dev eth0 192.168.176.0/24 via 10.205.58.254 dev eth0 192.168.252.0/24 via 10.205.58.254 dev eth0 192.168.131.50/32 via 10.205.58.254 dev eth0 10.240.178.0/24 via 10.205.58.254 dev eth0 10.240.166.2/32 via 10.205.58.254 dev eth0 10.240.188.0/24 via 10.205.58.254 dev eth0 10.240.202.0/24 via 10.205.58.254 dev eth0 10.60.100.73/32 via 10.205.58.254 dev eth0 10.60.5.133/32 via 10.205.58.254 dev eth0 | W34: Dau moi dich vu: tannph | X34: Các server đã cấp nhưng chưa dùng
A35: 33 | B35: Cloud_VTT | C35: MyCC | D35: database | E35: mycc-database-10205058121 | F35: 10.205.58.121/24 | G35: 10.207.191.45/24 | H35: CentOS_7_7_final | I35: 22 | J35: 46 | K35: 60 | L35: u01: 930 | N35: VTT_SAN_2021_Q4_01 | O35: IDC7F_E07_Unity_880_1020502474_SSD | P35: 1 | Q35: 10.207.191.254 | R35: Yes | S35: anhtt69 | T35: 10.240.201.49/32 via 10.205.58.254 dev eth0 10.254.139.0/24 via 10.205.58.254 dev eth0 10.240.226.0/24 via 10.205.58.254 dev eth0 10.255.58.0/24 via 10.205.58.254 dev eth0 10.60.101.0/24 via 10.205.58.254 dev eth0 10.58.15.114/32 via 10.205.58.254 dev eth0 10.58.137.0/24 via 10.205.58.254 dev eth0 10.60.7.0/24 via 10.205.58.254 dev eth0 10.60.97.0/24 via 10.205.58.254 dev eth0 192.168.182.8/32 via 10.205.58.254 dev eth0 10.60.96.0/24 via 10.205.58.254 dev eth0 10.58.4.0/24 via 10.205.58.254 dev eth0 10.58.65.0/24 via 10.205.58.254 dev eth0 10.40.17.0/24 via 10.205.58.254 dev eth0 10.74.225.0/24 via 10.205.58.254 dev eth0 10.60.131.0/24 via 10.205.58.254 dev eth0 10.60.129.0/24 via 10.205.58.254 dev eth0 10.30.160.0/24 via 10.205.58.254 dev eth0 10.61.151.0/24 via 10.205.58.254 dev eth0 10.60.100.0/24 via 10.205.58.254 dev eth0 192.168.176.0/24 via 10.205.58.254 dev eth0 192.168.252.0/24 via 10.205.58.254 dev eth0 192.168.131.50/32 via 10.205.58.254 dev eth0 10.240.178.0/24 via 10.205.58.254 dev eth0 10.240.166.2/32 via 10.205.58.254 dev eth0 10.240.188.0/24 via 10.205.58.254 dev eth0 10.240.202.0/24 via 10.205.58.254 dev eth0 10.60.100.73/32 via 10.205.58.254 dev eth0 10.60.5.133/32 via 10.205.58.254 dev eth0 | W35: Dau moi dich vu: tannph | X35: Các server đã cấp nhưng chưa dùng
A36: 34 | B36: Cloud_VTT | C36: MyCC | D36: database | E36: mycc-database-10205058122 | F36: 10.205.58.122/24 | G36: 10.207.191.46/24 | H36: CentOS_7_7_final | I36: 22 | J36: 46 | K36: 60 | L36: u01: 930 | N36: VTT_SAN_2021_Q4_01 | O36: IDC7F_E08_Unity_880_1020502476_SSD | P36: 1 | Q36: 10.207.191.254 | R36: Yes | S36: anhtt69 | T36: 10.240.201.49/32 via 10.205.58.254 dev eth0 10.254.139.0/24 via 10.205.58.254 dev eth0 10.240.226.0/24 via 10.205.58.254 dev eth0 10.255.58.0/24 via 10.205.58.254 dev eth0 10.60.101.0/24 via 10.205.58.254 dev eth0 10.58.15.114/32 via 10.205.58.254 dev eth0 10.58.137.0/24 via 10.205.58.254 dev eth0 10.60.7.0/24 via 10.205.58.254 dev eth0 10.60.97.0/24 via 10.205.58.254 dev eth0 192.168.182.8/32 via 10.205.58.254 dev eth0 10.60.96.0/24 via 10.205.58.254 dev eth0 10.58.4.0/24 via 10.205.58.254 dev eth0 10.58.65.0/24 via 10.205.58.254 dev eth0 10.40.17.0/24 via 10.205.58.254 dev eth0 10.74.225.0/24 via 10.205.58.254 dev eth0 10.60.131.0/24 via 10.205.58.254 dev eth0 10.60.129.0/24 via 10.205.58.254 dev eth0 10.30.160.0/24 via 10.205.58.254 dev eth0 10.61.151.0/24 via 10.205.58.254 dev eth0 10.60.100.0/24 via 10.205.58.254 dev eth0 192.168.176.0/24 via 10.205.58.254 dev eth0 192.168.252.0/24 via 10.205.58.254 dev eth0 192.168.131.50/32 via 10.205.58.254 dev eth0 10.240.178.0/24 via 10.205.58.254 dev eth0 10.240.166.2/32 via 10.205.58.254 dev eth0 10.240.188.0/24 via 10.205.58.254 dev eth0 10.240.202.0/24 via 10.205.58.254 dev eth0 10.60.100.73/32 via 10.205.58.254 dev eth0 10.60.5.133/32 via 10.205.58.254 dev eth0 | W36: Dau moi dich vu: tannph | X36: Các server đã cấp nhưng chưa dùng
A37: 35 | B37: Cloud_VTT | C37: MyCC | D37: database | E37: mycc-database-10205058123 | F37: 10.205.58.123/24 | G37: 10.207.191.47/24 | H37: CentOS_7_7_final | I37: 22 | J37: 46 | K37: 60 | L37: u01: 930 | N37: VTT_SAN_2021_Q4_01 | O37: IDC7F_E08_Unity_880_1020502476_SSD | P37: 1 | Q37: 10.207.191.254 | R37: Yes | S37: anhtt69 | T37: 10.240.201.49/32 via 10.205.58.254 dev eth0 10.254.139.0/24 via 10.205.58.254 dev eth0 10.240.226.0/24 via 10.205.58.254 dev eth0 10.255.58.0/24 via 10.205.58.254 dev eth0 10.60.101.0/24 via 10.205.58.254 dev eth0 10.58.15.114/32 via 10.205.58.254 dev eth0 10.58.137.0/24 via 10.205.58.254 dev eth0 10.60.7.0/24 via 10.205.58.254 dev eth0 10.60.97.0/24 via 10.205.58.254 dev eth0 192.168.182.8/32 via 10.205.58.254 dev eth0 10.60.96.0/24 via 10.205.58.254 dev eth0 10.58.4.0/24 via 10.205.58.254 dev eth0 10.58.65.0/24 via 10.205.58.254 dev eth0 10.40.17.0/24 via 10.205.58.254 dev eth0 10.74.225.0/24 via 10.205.58.254 dev eth0 10.60.131.0/24 via 10.205.58.254 dev eth0 10.60.129.0/24 via 10.205.58.254 dev eth0 10.30.160.0/24 via 10.205.58.254 dev eth0 10.61.151.0/24 via 10.205.58.254 dev eth0 10.60.100.0/24 via 10.205.58.254 dev eth0 192.168.176.0/24 via 10.205.58.254 dev eth0 192.168.252.0/24 via 10.205.58.254 dev eth0 192.168.131.50/32 via 10.205.58.254 dev eth0 10.240.178.0/24 via 10.205.58.254 dev eth0 10.240.166.2/32 via 10.205.58.254 dev eth0 10.240.188.0/24 via 10.205.58.254 dev eth0 10.240.202.0/24 via 10.205.58.254 dev eth0 10.60.100.73/32 via 10.205.58.254 dev eth0 10.60.5.133/32 via 10.205.58.254 dev eth0 | W37: Dau moi dich vu: tannph | X37: Các server đã cấp nhưng chưa dùng

Sheet Datalake
A1: 1. Cụm Dell isilon (QHĐC 2021) ở tổng trạm Hòa Khánh
A2: TT | B2: Hệ thống CNTT | C2: NHU CẦU TÀI NGUYÊN | E2: Số lượng máy chủ compute quy hoạch | F2: Vị trí máy chủ | G2: Cấu hình máy chủ | J2: Đơn vị quản lý ứng dụng | K2: Đầu mối ứng dụng | L2: Trạng thái
C3: Total lưu trữ Bigdata(GB) | D3: Total archiving Bigdat (GB) | G3: CPU | H3: RAM | I3: Disk
A4: 1 | B4: Campaign Management_VTT | C4: 365000 | E4: 31 | F4: Tầng 3, Ttr Hòa Khánh | G4: 2x Intel Xeon Gold 5318Y | H4: 256GB | I4: 2x 960GB SAS | J4: VTT | K4: AnhDT156 | L4: Đã cấu hình quy hoạch lưu trữ trên Datalake
A5: 2 | B5: CUS 360 | C5: 612000 | D5: 1020000 | E5: 48 | F5: Tầng 3, Ttr Hòa Khánh | J5: VTT | K5: Sonln3 | L5: Đã cấu hình quy hoạch lưu trữ trên Datalake
A6: 3 | B6: Adhoc VTT | C6: 7500 | D6: 7500 | E6: 2 | F6: Tầng 3, Ttr Hòa Khánh | J6: VTT | K6: Sonln3 | L6: Đã cấu hình quy hoạch lưu trữ trên Datalake
A7: 4 | B7: Adhoc VTG | C7: 7500 | D7: 7500 | E7: 2 | F7: Tầng 3, Ttr Hòa Khánh | J7: VTT | K7: Sonln3 | L7: Đã cấu hình quy hoạch lưu trữ trên Datalake
A8: 5 | B8: Analytic VTT | C8: 359800 | E8: 19 | F8: Tầng 3, Ttr Hòa Khánh | J8: VTT | K8: Dungha7 | L8: Đã cấu hình quy hoạch lưu trữ trên Datalake
A9: 6 | B9: CCAI | C9: 150000 | E9: 6 | F9: Tầng 3, Ttr Hòa Khánh | J9: VTT | K9: Dungha7 | L9: Đã cấu hình quy hoạch lưu trữ trên Datalake
A10: 7 | B10: BCCS_BILLING | C10: 10240 | E10: 6 | F10: Tầng 3, Ttr Hòa Khánh | J10: VTT | K10: Dungpt16 | L10: Đã cấu hình quy hoạch lưu trữ trên Datalake
C11: =SUM(C4:C10) -> 1512040 | D11: =SUM(D4:D10) -> 1035000
A13: 2. Cụm IBM ESS (QHĐC 2022) ở tổng trạm Hòa Khánh
A14: TT | B14: Hệ thống CNTT | C14: NHU CẦU TÀI NGUYÊN | E14: Số lượng máy chủ compute quy hoạch | F14: Vị trí máy chủ | G14: Cấu hình máy chủ | J14: Đơn vị quản lý ứng dụng | K14: Đầu mối ứng dụng | L14: Trạng thái
C15: Total lưu trữ Bigdata(GB) | D15: Total archiving Bigdat (GB) | G15: CPU | H15: RAM | I15: Disk
A16: 1 | B16: Bổ sung tăng trưởng DATA - DataLake VTT | C16: 1179197 | D16: 1100000 | E16: 22 | F16: Tầng 4, Ttr Hòa Khánh | G16: 2xIntel 5318Y | H16: 256GB | I16: 2*1.92TB SSD | J16: VTT | K16: DungHA7 | L16: Đã cấu hình quy hoạch lưu trữ trên Datalake
A18: 3. Cụm Cloud chuyển Bigdata(QHĐC 2022) ở tổng trạm Hòa Khánh
A19: TT | B19: Hệ thống CNTT | C19: NHU CẦU TÀI NGUYÊN | E19: Số lượng máy chủ compute quy hoạch | F19: Vị trí máy chủ | G19: Cấu hình máy chủ | J19: Đơn vị quản lý ứng dụng | K19: Đầu mối ứng dụng | L19: Trạng thái
C20: Total lưu trữ Bigdata(GB) | D20: Total archiving Bigdat (GB) | G20: CPU | H20: RAM | I20: Disk
A21: 1 | B21: Bigdata VTT 2022 | C21: Dùng chung IBM 2022 và Dell 2021 | D21: Dùng chung IBM 2022 và Dell 2021 | E21: 193 | F21: Tầng 4, Ttr Hòa Khánh | G21: 2xIntel 5318Y | H21: 256GB | I21: 2*600GB SAS | J21: VTT
A23: 4. Cụm Dell isilon (QHĐC 2023) ở tổng trạm Hòa Lạc 2
A24: TT | B24: Hệ thống CNTT | C24: NHU CẦU TÀI NGUYÊN | E24: Số lượng máy chủ compute quy hoạch | F24: Vị trí máy chủ | G24: Cấu hình máy chủ | J24: Đơn vị quản lý ứng dụng | K24: Đầu mối ứng dụng | L24: Trạng thái
C25: Total lưu trữ Bigdata(GB) | D25: Total archiving Bigdat (GB) | G25: CPU | H25: RAM | I25: Disk
A26: 1 | B26: Hệ thống Campaign Management | C26: 36000 | E26: 11 | F26: Tầng 3, Ttr Hòa Lạc 2 (HLA) | G26: 2xIntel Xeon-Gold 5418Y | H26: 256GB | I26: 2x960GB SSD | J26: VTT | K26: AnhDT156
E27: 9 | F27: Tầng 3, Ttr Hòa Lạc 2 (HLA) | G27: 2xIntel Xeon-Gold 5418Y | H27: 256GB | I27: 2x960GB SSD
I28: 8x8TB SAS
A29: 2 | B29: DataLake VTT(FMRA) | D29: 3112950 | E29: 75 | F29: Tầng 3, Ttr Hòa Lạc 2 (HLA) | G29: 2xIntel Xeon-Gold 5418Y | H29: 256GB | I29: 2x960GB SSD | J29: VTT | K29: TamDX
A30: 3 | B30: DataLake VTT | C30: 4068681 | D30: 3800 | E30: 112 | F30: Tầng 3, Ttr Hòa Lạc 2 (HLA) | G30: 2xIntel Xeon-Gold 5418Y | H30: 256GB | I30: 2x960GB SSD | J30: VTT | K30: DungHA7
A31: 4 | B31: Hệ thống Marketing tập trung | C31: 127500 | E31: 17 | F31: Tầng 3, Ttr Hòa Lạc 2 (HLA) | G31: 2xIntel Xeon-Gold 5418Y | H31: 256GB | I31: 2x960GB SSD | J31: VTT | K31: AnhDT156
A32: 5 | B32: Hệ thống vRAFM 3.0 (Các server ứng dụng và DB) | E32: 14 | F32: Tầng 3, Ttr Hòa Lạc 2 (HLA) | G32: 2xIntel Xeon-Gold 5418Y | H32: 256GB | I32: 2x960GB SSD | J32: VTT | K32: TuanNM33
I33: 2x1.92 SSD
I34: 8x8TB SAS
C35: =SUM(C26:C34) -> 4232181 | D35: =SUM(D26:D34) -> 3116750
A37: 5. Cụm Dell isilon ở tổng trạm Hòa Lạc
A38: TT | B38: Hệ thống CNTT | C38: NHU CẦU TÀI NGUYÊN | E38: Số lượng máy chủ compute quy hoạch | F38: Vị trí máy chủ | G38: Cấu hình máy chủ | J38: Đơn vị quản lý ứng dụng | K38: Đầu mối ứng dụng
C39: Total lưu trữ Bigdata(GB) | D39: Total archiving Bigdat (GB) | G39: CPU | H39: RAM | I39: Disk
A40: 1 | B40: Event Management | C40: 660000 | D40: 2240000 | E40: 29 | J40: TT CNTT - TCT VTT | K40: anhdt156
A41: 2 | B41: Eureka | C41: 500000 | D41: 0 | E41: 13 | J41: VTT | K41: hieunt82
C42: =SUM(C40:C41) -> 1160000 | D42: =SUM(D40:D41) -> 2240000

Sheet DA2022
A1: STT | B1: Ký hiệu | C1: Đơn vị tính | D1: Đơn vị | E1: DA Cloud | F1: DA CĐBR | G1: DA HĐH | H1: HLC | I1: GVM | J1: HKH | K1: NTH | L1: HHT | M1: Chi tiết
A2: 1.1 | B2: VTT
A3: 1 | B3: Server Cloud loại 1 | C3: Bộ | D3: VTT | E3: 253.03 | F3: - | G3: - | J3: 253 | M3: - 60 compute chia 02 HA ảo hóa cloud, còn lại chuyển bigdata (Cụm mới HKH) | O3: Server | P3: Loại thiết bị | Q3: HLC | R3: HKH | S3: vCPU | T3: RAM(GB) | U3: HBA
A4: 2 | B4: Server Cloud loại 2 | C4: Bộ | D4: VTT | E4: 179.48 | F4: 246 | G4: - | H4: 179 | J4: 246 | M4: -179 HLC | O4: SAN | P4: svr cloud loại 2 | Q4: 179 | R4: 246 | S4: 96 | T4: 288 | U4: y
M5: - 246 ở HKH | O5: bigdata | P5: svr cloud loại 1 | R5: 193 | S5: 96 | T5: 288 | U5: n
O6: Ceph | P6: svr cloud loại 1 | Q6: 60 | R6: 0 | S6: 96 | T6: 288 | U6: n
A7: 3 | B7: Server vật lý loại 1 | C7: Bộ | D7: VTT | E7: 117 | F7: 52 | G7: - | H7: 68 | J7: 101 | M7: Chạy vật lý, kết nối SAN ( Oracle, App....)
M8: 40% HLC , 60% HKH ( tương 2+2 SAN) mỗi SAN switch 38 server
A9: 4 | B9: Server vật lý loại 2 | C9: Bộ | D9: VTT | E9: 2.00 | F9: - | G9: - | J9: 2 | M9: Đấu nối SAN tương tự vật lý loại 1
A10: 5 | B10: Server vật lý loại 4 | C10: Bộ | D10: VTT | E10: 20.00 | F10: - | G10: - | J10: 20 | M10: Bare HKH
A11: 6 | B11: Server vật lý loại 6 | C11: Bộ | D11: VTT | E11: 18.00 | F11: - | G11: - | H11: 18 | M11: Bare HLC
A12: 7 | B12: Lưu trữ Ceph | C12: Bộ | D12: VTT | E12: 18 | F12: - | G12: - | M12: - Chia 02 HA để dự phòng
A13: 8 | B13: Server Bigdata loại 1 | C13: Bộ | D13: VTT | E13: - | F13: - | G13: 22 | M13: HKH
A14: 9 | B14: Lưu trữ Object | C14: TB | D14: VTT | E14: 5,550 | F14: - | G14: - | M14: HKH tv360
A15: 10 | B15: Lưu trữ SAN | C15: Bộ | D15: VTT | E15: 9.6 | F15: 6 | G15: - | H15: 7 | I15: 8 | M15: 4 HLC, 6 HKH cho cloud (theo danh sách TB SAN thì VTT có 5 HLC)
M16: 2 HLC, 2 HKH cho vật lý
A17: 11 | B17: Lưu trữ NAS | C17: TB | D17: VTT | E17: 755.19 | F17: - | G17: - | M17: HKH
A18: 12 | B18: Lưu trữ Big data | C18: TB | D18: VTT | E18: - | F18: - | G18: 1,151.56 | M18: HKH
A19: 13 | B19: Lưu trữ Archiving | C19: TB | D19: VTT | E19: - | F19: - | G19: 1,074.22 | M19: HKH
A24: Loại | B24: Cấu hình
B25: Model | C25: CPU | D25: RAM | E25: Disk | F25: NiC | G25: HBA | H25: GPU
A27: Server Cloud loại 1 | B27: HPE DL360 Gen10 | C27: 2xIntel 5318Y | D27: 12x32GB | E27: 2x600GB SAS | F27: 2x NIC 10G dual port | G27: N/A | H27: N/A
A28: Server Cloud loại 2 | B28: HPE DL360 Gen10 | C28: 2xIntel 5318Y | D28: 12x32GB | E28: 2x600GB SAS | F28: 2x NIC 10G dual port | G28: 1xHBA Dual Port | H28: N/A
A29: Server vật lý loại 1 | B29: Dell R650 | C29: 2xIntel 5318Y | D29: 8x32GB | E29: 2x600GB SAS | F29: 2x NIC 10G dual port | G29: 1xHBA Dual Port | H29: N/A
A30: Server vật lý loại 2 | B30: Dell R650 | C30: 2xIntel 5318Y | D30: 8x64GB | E30: 2x600GB SAS | F30: 2x NIC 10G dual port | G30: 1xHBA Dual Port | H30: N/A
A31: Server vật lý loại 3 | B31: DELL R750 | C31: 2xIntel 5318Y | D31: 2x64GB | E31: 2x600GB SAS | F31: 2x NIC 10G dual port | G31: N/A | H31: N/A
E32: 4x8TB NLSAS
A33: Server vật lý loại 4 | B33: Dell R650 | C33: 2xIntel 5318Y | D33: 4x32GB | E33: 2x600GB SAS | F33: 2x NIC 10G dual port | G33: N/A | H33: N/A
D34: 4x64GB | E34: 2x1,92TB SSD
A35: Server vật lý loại 5 | B35: DELL R750XA | C35: 2xIntel 5318S | D35: 4x64GB | E35: 2x800GB SSD | F35: 2x NIC 10G dual port | G35: N/A | H35: 3xNVIDIA A30
E36: 2x1,92TB SSD
A37: Server vật lý loại 6 | B37: DELL R750XA | C37: 2xIntel 5318S | D37: 4x64GB | E37: 2x800G SSD | F37: 1x NIC 10G Quad port | G37: 1xHBA Dual Port | H37: 3xNVIDIA A30
E38: 2x1,92TB SSD
A39: Server vật lý loại 7 | B39: DELL R750 | C39: 2xIntel 5318Y | D39: 4x32GB | E39: 2x600GB SAS | F39: 2x NIC 10G dual port | G39: N/A | H39: N/A
D40: 4x64GB | E40: 3x8TB NLSAS
E41: 2x1,92TB SSD
A42: Server vật lý loại 8 | B42: DELL R750 | C42: 2xIntel 5318Y | D42: 4x64GB | E42: 2x600GB SAS | F42: 2x NIC 10G dual port | G42: N/A | H42: N/A
E43: 6x8TB NLSAS
E44: 2x1,92TB SSD
A45: Server vật lý loại 9 | B45: Dell R650 | C45: 2xIntel 5318Y | D45: 4x64GB | E45: 2x600GB SAS | F45: 2x NIC 10G dual port | G45: N/A | H45: N/A
E46: 3x3,84TB SSD
A47: Server SDS loại 1, 3 (ceph) | B47: DELL R750 | C47: 2xIntel Xeon Silver 4310 | D47: 2x64GB | E47: 5x16TB SAS | F47: 2x NIC 10G dual port | G47: N/A | H47: N/A
E48: 2x1,9TB SSD
E49: 4x3,84TB SSD
E50: 2x800GB SSD
A51: 2.2 | B51: Thiết bị SAN-SAN Switch
I52: SSD(TB) | J52: HDD(TB)
A53: 1 | B53: 12/Viettel-SVTech/2023 | C53: Thiết bị lưu trữ Cloud loại 1 | D53: VSP E590H Appliance Product: 93x2.4TB SFF SAS HDD; 59x3.8TB SAS SSD | I53: =59*3.8 -> 224.2 | J53: =93*2.4 -> 223.2
A54: 2 | B54: 18/Viettel-SVTech/2023 | C54: Thiết bị lưu trữ Cloud loại 1 | D54: VSP E590H Appliance Product: 93x2.4TB SFF SAS HDD; 59x3.8TB SAS SSD | I54: =59*3.8 -> 224.2 | J54: =93*2.4 -> 223.2

Sheet Chi tiết Cấp phát 2025
A1: STT | B1: Mã SR cấp phát | C1: Pool/ Nguồn tài nguyên | D1: Tên dự án | E1: Service (App, DB, K8s, master, worker,…) | F1: Hostname (Compute) | G1: IP DCN | H1: IP Khác | I1: Lọai OS | J1: vCPU | K1: RAM (GB) | L1: Volume OS (GB) | M1: Volume khác (GB) | N1: NAS (GB) | O1: Host aggregate | P1: Storage Pool | Q1: Instance Name | R1: Status (Running/Thu hồi) | S1: Đơn vị | T1: Owner server | U1: Đầu mối dự án | V1: Ghi chú | W1: Status
A2: 1 | B2: SR_VN_20220223_542239 | C2: Private Cloud | D2: VDA_VTT | E2: Redis | F2: hlc3f-vtt01-com-1020718351 | G2: 10.207.188.148 | J2: 8 | K2: 64 | L2: 60 | M2: 1000 | O2: VTT_SAN_2023_Q2_01 | P2: HLC9103.D12A.Unity_880.VTT-SAN-03 | Q2: Redis-10.207.188.148 | R2: Running | S2: TT VAS | T2: NDTho
A3: 2 | B3: SR_VN_20220223_542239 | C3: Private Cloud | D3: VDA_VTT | E3: Master | F3: hlc3f-vtt01-com-1020718350 | G3: 10.207.188.90 | J3: 8 | K3: 24 | L3: 60 | M3: 240 | O3: VTT_SAN_2023_Q2_01 | P3: HLC9103.D12A.Unity_880.VTT-SAN-03 | Q3: Master-10.207.188.90 | R3: Running | S3: TT VAS | T3: NDTho
A4: 3 | B4: SR_VN_20220223_542239 | C4: Private Cloud | D4: VDA_VTT | E4: Redis | F4: hlc7f-vtt01-com-1020718345 | G4: 10.207.188.149 | J4: 8 | K4: 64 | L4: 60 | M4: 1000 | O4: VTT_SAN_2021_Q4_01 | P4: IDC7F_E07_Unity_880_1020502474_SAS | Q4: Redis-10.207.188.149 | R4: Running | S4: TT VAS | T4: NDTho
A5: 4 | B5: SR_VN_20220223_542239 | C5: Private Cloud | D5: VDA_VTT | E5: Redis | F5: hlc3f-vtt01-com-1020718369 | G5: 10.207.188.146 | J5: 8 | K5: 64 | L5: 60 | M5: 1000 | O5: VTT_SAN_2023_Q2_01 | P5: HLC9103.D12A.Unity_880.VTT-SAN-03 | Q5: Redis-10.207.188.146 | R5: Running | S5: TT VAS | T5: NDTho
A6: 5 | B6: SR_VN_20220223_542239 | C6: Private Cloud | D6: VDA_VTT | E6: DB | F6: hlc7f-vtt01-com-1020718317 | G6: 10.207.191.26 | J6: 24 | K6: 48 | L6: 60 | M6: 600 | O6: VTT_SAN_2021_Q4_01 | P6: IDC7F_E08_Unity_880_1020502476_SAS | Q6: DB-10.207.191.26 | R6: Running | S6: TT VAS | T6: NDTho
A7: 6 | B7: SR_VN_20220223_542239 | C7: Private Cloud | D7: VDA_VTT | E7: Redis | F7: hlc3f-vtt01-com-1020718354 | G7: 10.207.188.145 | J7: 8 | K7: 64 | L7: 60 | M7: 1000 | O7: VTT_SAN_2023_Q2_01 | P7: HLC9103.D12A.Unity_880.VTT-SAN-03 | Q7: Redis-10.207.188.145 | R7: Running | S7: TT VAS | T7: NDTho
A8: 7 | B8: SR_VN_20220223_542239 | C8: Private Cloud | D8: VDA_VTT | E8: Redis | F8: hlc3f-vtt01-com-1020718381 | G8: 10.207.188.143 | J8: 8 | K8: 64 | L8: 60 | M8: 1000 | O8: VTT_SAN_2023_Q2_02 | P8: HLC9103.D12A.Unity_880.VTT-SAN-04 | Q8: Redis-10.207.188.143 | R8: Running | S8: TT VAS | T8: NDTho
A9: 8 | B9: SR_VN_20220223_542239 | C9: Private Cloud | D9: VDA_VTT | E9: Etcd | F9: hlc7f-vtt01-com-1020718342 | G9: 10.207.188.81 | J9: 8 | K9: 24 | L9: 60 | M9: 240 | O9: VTT_SAN_2021_Q4_01 | P9: IDC7F_E07_Unity_880_1020502474_SSD | Q9: Etcd-10.207.188.81 | R9: Running | S9: TT VAS | T9: NDTho
A10: 9 | B10: SR_VN_20220223_542239 | C10: Private Cloud | D10: VDA_VTT | E10: Etcd | F10: hlc7f-vtt01-com-1020718319 | G10: 10.207.188.80 | J10: 8 | K10: 24 | L10: 60 | M10: 240 | O10: VTT_SAN_2021_Q4_01 | P10: IDC7F_E07_Unity_880_1020502474_SSD | Q10: Etcd-10.207.188.80 | R10: Running | S10: TT VAS | T10: NDTho
A11: 10 | B11: SR_VN_20220223_542239 | C11: Private Cloud | D11: VDA_VTT | E11: Redis | F11: hlc7f-vtt01-com-1020718322 | G11: 10.207.188.102 | J11: 24 | K11: 64 | L11: 60 | M11: 2000 | O11: VTT_SAN_2021_Q4_01 | P11: IDC7F_E08_Unity_880_1020502476_SAS | Q11: Redis-10.207.188.102 | R11: Running | S11: TT VAS | T11: NDTho
A12: 11 | B12: SR_VN_20220223_542239 | C12: Private Cloud | D12: VDA_VTT | E12: Kafka | F12: hlc3f-vtt01-com-1020718348 | G12: 10.207.188.92 | J12: 24 | K12: 64 | L12: 60 | M12: 2000 | O12: VTT_SAN_2023_Q2_01 | P12: HLC9103.D12A.Unity_880.VTT-SAN-03 | Q12: Kafka-10.207.188.92 | R12: Running | S12: TT VAS | T12: NDTho
A13: 12 | B13: SR_VN_20220223_542239 | C13: Private Cloud | D13: VDA_VTT | E13: Kafka | F13: hlc7f-vtt01-com-1020718332 | G13: 10.207.188.97 | J13: 24 | K13: 64 | L13: 60 | M13: 2000 | O13: VTT_SAN_2021_Q4_01 | P13: IDC7F_E07_Unity_880_1020502474_SSD | Q13: Kafka-10.207.188.97 | R13: Running | S13: TT VAS | T13: NDTho
... A61: 60 | B61: SR_VN_20220223_542239 | C61: Private Cloud | D61: VDA_VTT | E61: Worker | F61: hlc7f-vtt01-com-1020718342 | G61: 10.207.188.127 | J61: 8 | K61: 24 | L61: 60 | M61: 200 | O61: VTT_SAN_2021_Q4_01 | P61: IDC7F_E07_Unity_880_1020502474_SAS | Q61: Worker-10.207.188.127 | R61: Running | S61: TT VAS | T61: NDTho
M62: u01:200
M63: logs:100
B64: SR_VN_20250205_1313362 | C64: Cloud_HLC_2024 | D64: TTOnline | E64: APP | F64: TTOnline_01-01 | G64: 10.211.126.99/24 | I64: CentOS_Stream_9_final | J64: 32 | K64: 64 | L64: 100 | M64: data:374 | O64: VTT_SAN_2024_Q4_01 | P64: VTT_HITACHI_E590H_SAN_01 | S64: TT VAS | T64: thangnd21
B65: SR_VN_20250205_1313362 | C65: Cloud_HLC_2024 | D65: TTOnline | E65: APP | F65: TTOnline_01-02 | G65: 10.211.126.100/24 | I65: CentOS_Stream_9_final | J65: 32 | K65: 64 | L65: 100 | M65: data:374 | O65: VTT_SAN_2024_Q4_02 | P65: VTT_HITACHI_E590H_SAN_02 | S65: TT VAS | T65: thangnd21
B66: SR_VN_20250205_1313362 | C66: Cloud_HLC_2024 | D66: TTOnline | E66: APP | F66: TTOnline_01-03 | G66: 10.211.126.101/24 | I66: CentOS_Stream_9_final | J66: 32 | K66: 64 | L66: 100 | M66: data:374 | O66: VTT_SAN_2024_Q4_03 | P66: VTT_HITACHI_E590H_SAN_03 | S66: TT VAS | T66: thangnd21
B67: SR_VN_20250205_1313362 | C67: Cloud_HLC_2024 | D67: TTOnline | E67: APP | F67: TTOnline_01-04 | G67: 10.211.126.102/24 | I67: CentOS_Stream_9_final | J67: 32 | K67: 64 | L67: 100 | M67: data:374 | O67: VTT_SAN_2024_Q4_04 | P67: VTT_HITACHI_E590H_SAN_04 | S67: TT VAS | T67: thangnd21
B68: SR_VN_20250205_1313362 | C68: Cloud_HLC_2024 | D68: TTOnline | E68: APP | F68: TTOnline_01-05 | G68: 10.211.126.103/24 | I68: CentOS_Stream_9_final | J68: 32 | K68: 64 | L68: 100 | M68: data:374 | O68: VTT_SAN_2024_Q4_05 | P68: VTT_HITACHI_E590H_SAN_05 | S68: TT VAS | T68: thangnd21
B69: SR_VN_20250205_1313362 | C69: Cloud_HLC_2024 | D69: TTOnline | E69: APP | F69: TTOnline_01-06 | G69: 10.211.126.104/24 | I69: CentOS_Stream_9_final | J69: 32 | K69: 64 | L69: 100 | M69: data:374 | O69: VTT_SAN_2024_Q4_01 | P69: VTT_HITACHI_E590H_SAN_01 | S69: TT VAS | T69: thangnd21
B70: SR_VN_20250205_1313362 | C70: Cloud_HLC_2024 | D70: TTOnline | E70: APP | F70: TTOnline_01-07 | G70: 10.211.126.105/24 | I70: CentOS_Stream_9_final | J70: 32 | K70: 64 | L70: 100 | M70: data:374 | O70: VTT_SAN_2024_Q4_02 | P70: VTT_HITACHI_E590H_SAN_02 | S70: TT VAS | T70: thangnd21
B71: SR_VN_20250205_1313362 | C71: Cloud_HLC_2024 | D71: TTOnline | E71: APP | F71: TTOnline_01-08 | G71: 10.211.126.106/24 | I71: CentOS_Stream_9_final | J71: 32 | K71: 64 | L71: 100 | M71: data:374 | O71: VTT_SAN_2024_Q4_03 | P71: VTT_HITACHI_E590H_SAN_03 | S71: TT VAS | T71: thangnd21
B72: SR_VN_20250205_1313362 | C72: Cloud_HLC_2024 | D72: TTOnline | E72: APP | F72: TTOnline_01-09 | G72: 10.211.126.107/24 | I72: CentOS_Stream_9_final | J72: 32 | K72: 64 | L72: 100 | M72: data:374 | O72: VTT_SAN_2024_Q4_04 | P72: VTT_HITACHI_E590H_SAN_04 | S72: TT VAS | T72: thangnd21
B73: SR_VN_20250205_1313362 | C73: Cloud_HLC_2024 | D73: TTOnline | E73: APP | F73: TTOnline_01-10 | G73: 10.211.126.108/24 | I73: CentOS_Stream_9_final | J73: 32 | K73: 64 | L73: 100 | M73: data:374 | O73: VTT_SAN_2024_Q4_05 | P73: VTT_HITACHI_E590H_SAN_05 | S73: TT VAS | T73: thangnd21
B74: SR_VN_20250205_1313362 | C74: Cloud_HLC_2024 | D74: TTOnline | E74: APP | F74: TTOnline_01-11 | G74: 10.211.126.109/24 | I74: CentOS_Stream_9_final | J74: 32 | K74: 64 | L74: 100 | M74: data:374 | O74: VTT_SAN_2024_Q4_01 | P74: VTT_HITACHI_E590H_SAN_01 | S74: TT VAS | T74: thangnd21
B75: SR_VN_20250205_1313362 | C75: Cloud_HLC_2024 | D75: TTOnline | E75: APP | F75: TTOnline_01-12 | G75: 10.211.126.110/24 | I75: CentOS_Stream_9_final | J75: 32 | K75: 64 | L75: 100 | M75: data:374 | O75: VTT_SAN_2024_Q4_02 | P75: VTT_HITACHI_E590H_SAN_02 | S75: TT VAS | T75: thangnd21
... B91: SR_VN_20250205_1313362 | C91: Cloud_HLC_2024 | D91: TTOnline | E91: APP | F91: TTOnline_01-28 | G91: 10.211.126.126/24 | I91: CentOS_Stream_9_final | J91: 32 | K91: 64 | L91: 100 | M91: data:374 | O91: VTT_SAN_2024_Q4_03 | P91: VTT_HITACHI_E590H_SAN_03 | S91: TT VAS | T91: thangnd21
B92: SR_VN_20250205_1313362 | C92: Cloud_HLC_2024 | D92: TTOnline | E92: APP | F92: TTOnline_02-01 | G92: 10.211.126.127/24 | H92: 10.52.156.1/25 | I92: CentOS_Stream_9_final | J92: 32 | K92: 64 | L92: 100 | M92: data:374 | O92: VTT_SAN_2024_Q4_04 | P92: VTT_HITACHI_E590H_SAN_04 | S92: TT VAS | T92: thangnd21
B93: SR_VN_20250205_1313362 | C93: Cloud_HLC_2024 | D93: TTOnline | E93: APP | F93: TTOnline_02-02 | G93: 10.211.126.128/24 | H93: 10.52.156.2/25 | I93: CentOS_Stream_9_final | J93: 32 | K93: 64 | L93: 100 | M93: data:374 | O93: VTT_SAN_2024_Q4_05 | P93: VTT_HITACHI_E590H_SAN_05 | S93: TT VAS | T93: thangnd21
B94: SR_VN_20250205_1313362 | C94: Cloud_HLC_2024 | D94: TTOnline | E94: APP | F94: TTOnline_02-03 | G94: 10.211.126.129/24 | H94: 10.52.156.3/25 | I94: CentOS_Stream_9_final | J94: 32 | K94: 64 | L94: 100 | M94: data:374 | O94: VTT_SAN_2024_Q4_01 | P94: VTT_HITACHI_E590H_SAN_01 | S94: TT VAS | T94: thangnd21
B95: SR_VN_20250205_1313362 | C95: Cloud_HLC_2024 | D95: TTOnline | E95: APP | F95: TTOnline_03-01 | G95: 10.211.126.130/24 | I95: CentOS_Stream_9_final | J95: 20 | K95: 32 | L95: 100 | M95: data:224 | O95: VTT_SAN_2024_Q4_02 | P95: VTT_HITACHI_E590H_SAN_02 | S95: TT VAS | T95: thangnd21
B96: SR_VN_20250205_1313362 | C96: Cloud_HLC_2024 | D96: TTOnline | E96: APP | F96: TTOnline_03-02 | G96: 10.211.126.131/24 | I96: CentOS_Stream_9_final | J96: 20 | K96: 32 | L96: 100 | M96: data:224 | O96: VTT_SAN_2024_Q4_03 | P96: VTT_HITACHI_E590H_SAN_03 | S96: TT VAS | T96: thangnd21
B97: SR_VN_20250205_1313362 | C97: Cloud_HLC_2024 | D97: TTOnline | E97: APP | F97: TTOnline_03-03 | G97: 10.211.126.132/24 | I97: CentOS_Stream_9_final | J97: 20 | K97: 32 | L97: 100 | M97: data:224 | O97: VTT_SAN_2024_Q4_04 | P97: VTT_HITACHI_E590H_SAN_04 | S97: TT VAS | T97: thangnd21
B98: SR_VN_20250205_1313362 | C98: Cloud_HLC_2024 | D98: TTOnline | E98: APP | F98: TTOnline_03-04 | G98: 10.211.126.133/24 | I98: CentOS_Stream_9_final | J98: 20 | K98: 32 | L98: 100 | M98: data:224 | O98: VTT_SAN_2024_Q4_05 | P98: VTT_HITACHI_E590H_SAN_05 | S98: TT VAS | T98: thangnd21
B99: SR_VN_20250205_1313362 | C99: Cloud_HLC_2024 | D99: TTOnline | E99: APP | F99: TTOnline_03-05 | G99: 10.211.126.134/24 | I99: CentOS_Stream_9_final | J99: 20 | K99: 32 | L99: 100 | M99: data:224 | O99: VTT_SAN_2024_Q4_01 | P99: VTT_HITACHI_E590H_SAN_01 | S99: TT VAS | T99: thangnd21
B100: SR_VN_20250205_1313362 | C100: Cloud_HLC_2024 | D100: TTOnline | E100: APP | F100: TTOnline_03-06 | G100: 10.211.126.135/24 | I100: CentOS_Stream_9_final | J100: 20 | K100: 32 | L100: 100 | M100: data:224 | O100: VTT_SAN_2024_Q4_02 | P100: VTT_HITACHI_E590H_SAN_02 | S100: TT VAS | T100: thangnd21
B101: SR_VN_20250205_1313362 | C101: Cloud_HLC_2024 | D101: TTOnline | E101: APP | F101: TTOnline_03-07 | G101: 10.211.126.136/24 | I101: CentOS_Stream_9_final | J101: 20 | K101: 32 | L101: 100 | M101: data:224 | O101: VTT_SAN_2024_Q4_03 | P101: VTT_HITACHI_E590H_SAN_03 | S101: TT VAS | T101: thangnd21
B102: SR_VN_20250205_1313362 | C102: Cloud_HLC_2024 | D102: TTOnline | E102: APP | F102: TTOnline_03-08 | G102: 10.211.126.137/24 | I102: CentOS_Stream_9_final | J102: 20 | K102: 32 | L102: 100 | M102: data:224 | O102: VTT_SAN_2024_Q4_04 | P102: VTT_HITACHI_E590H_SAN_04 | S102: TT VAS | T102: thangnd21
B103: SR_VN_20250205_1313362 | C103: Cloud_HLC_2024 | D103: TTOnline | E103: APP | F103: TTOnline_03-09 | G103: 10.211.126.138/24 | I103: CentOS_Stream_9_final | J103: 20 | K103: 32 | L103: 100 | M103: data:224 | O103: VTT_SAN_2024_Q4_05 | P103: VTT_HITACHI_E590H_SAN_05 | S103: TT VAS | T103: thangnd21
B104: SR_VN_20250205_1313362 | C104: Cloud_HLC_2024 | D104: TTOnline | E104: APP | F104: TTOnline_04-01 | G104: 10.211.126.139/24 | I104: CentOS_Stream_9_final | J104: 22 | K104: 38 | L104: 100 | M104: data:135 | O104: VTT_SAN_2024_Q4_01 | P104: VTT_HITACHI_E590H_SAN_01 | S104: TT VAS | T104: thangnd21
B105: SR_VN_20250205_1313362 | C105: Cloud_HLC_2024 | D105: TTOnline | E105: APP | F105: TTOnline_04-02 | G105: 10.211.126.140/24 | I105: CentOS_Stream_9_final | J105: 22 | K105: 38 | L105: 100 | M105: data:135 | O105: VTT_SAN_2024_Q4_02 | P105: VTT_HITACHI_E590H_SAN_02 | S105: TT VAS | T105: thangnd21
B106: SR_VN_20250205_1313362 | C106: Cloud_HLC_2024 | D106: TTOnline | E106: APP | F106: TTOnline_04-03 | G106: 10.211.126.141/24 | I106: CentOS_Stream_9_final | J106: 22 | K106: 38 | L106: 100 | M106: data:135 | O106: VTT_SAN_2024_Q4_03 | P106: VTT_HITACHI_E590H_SAN_03 | S106: TT VAS | T106: thangnd21
... B108: SR_VN_20250205_1313265 | C108: Cloud_HLC_2024 | D108: Crawler | E108: APP | F108: app-crawler-02 | G108: 10.211.126.143/24 | I108: CentOS_Stream_9_final | J108: 4 | K108: 8 | L108: 100 | M108: u01:18650 | O108: VTT_SAN_2024_Q4_02 | P108: VTT_HITACHI_E590H_SAN_02 | S108: TT CNTT | T108: hungdt54
B109: SR_VN_20250206_1314391 | C109: Cloud_VTT | D109: APIGW | E109: App | F109: public-test-01 | G109: 10.210.103.78/24 | H109: 171.229.16.123/24 | I109: CentOS_Stream_9_final | J109: 4 | K109: 40 | L109: 60 | M109: u01:240 | O109: VTT_SAN_2023_Q2_01 | P109: HLC9103.D12A.Unity_880.VTT-SAN-03
B110: SR_VN_20250206_1314391 | C110: Cloud_VTT | D110: APIGW | E110: App | F110: public-test-02 | G110: 10.210.103.79/24 | H110: 171.229.16.124/24 | I110: CentOS_Stream_9_final | J110: 4 | K110: 40 | L110: 60 | M110: u01:240 | O110: VTT_SAN_2023_Q2_02 | P110: HLC9103.D12A.Unity_880.VTT-SAN-04
F111: hkh-vtt-app-10-211-45-19 | G111: 10.211.45.19 | I111: Ubuntu 22.04 LTS | J111: 96 | K111: 128
F112: hkh-vtt-app-10-211-45-20 | G112: 10.211.45.20 | I112: Ubuntu 22.04 LTS | J112: 96 | K112: 128
F113: hkh-vtt-app-10-211-45-33 | G113: 10.211.45.33 | I113: Ubuntu 22.04 LTS | J113: 96 | K113: 128
F114: hkh-vtt-app-10-211-45-39 | G114: 10.211.45.39 | I114: Ubuntu 22.04 LTS | J114: 96 | K114: 128
F115: hkh-vtt-app-10-211-45-40 | G115: 10.211.45.40 | I115: Ubuntu 22.04 LTS | J115: 96 | K115: 128
F116: hkh-vtt-app-10-211-45-41 | G116: 10.211.45.41 | I116: Ubuntu 22.04 LTS | J116: 96 | K116: 128
F117: hkh-vtt-app-10-211-45-42 | G117: 10.211.45.42 | I117: Ubuntu 22.04 LTS | J117: 96 | K117: 128
F118: hkh-vtt-app-10-211-45-43 | G118: 10.211.45.43 | I118: Ubuntu 22.04 LTS | J118: 96 | K118: 128
F119: hkh-vtt-app-10-211-45-44 | G119: 10.211.45.44 | I119: Ubuntu 22.04 LTS | J119: 96 | K119: 128
F120: hkh-vtt-app-10-211-45-45 | G120: 10.211.45.45 | I120: Ubuntu 22.04 LTS | J120: 96 | K120: 128
F121: hkh-vtt-app-10-211-45-46 | G121: 10.211.45.46 | I121: Ubuntu 22.04 LTS | J121: 96 | K121: 128
F122: hkh-vtt-app-10-211-45-47 | G122: 10.211.45.47 | I122: Ubuntu 22.04 LTS | J122: 96 | K122: 128
... F161: hkh-vtt-db-10-211-45-99 | G161: 10.211.45.99 | I161: Ubuntu 22.04 LTS | J161: 96 | K161: 128
B162: SR_VN_20250219_1322876 | C162: Cloud_VTT | D162: TBC_Payment | E162: App | F162: TBC_app_01 | G162: 10.207.186.60/24 | I162: CentOS_Stream_9_final | J162: 24 | K162: 48 | L162: 60 | M162: u01:797 | O162: VTT_SAN_2023_Q2_01 | P162: HLC9103.D12A.Unity_880.VTT-SAN-03 | T162: tuanha3 | U162: huyct13
B163: SR_VN_20250219_1322876 | C163: Cloud_VTT | D163: TBC_Payment | E163: App | F163: TBC_app_02 | G163: 10.207.186.61/24 | I163: CentOS_Stream_9_final | J163: 24 | K163: 48 | L163: 60 | M163: u01: 797 | O163: VTT_SAN_2023_Q2_02 | P163: HLC9103.D12A.Unity_880.VTT-SAN-04 | T163: tuanha3 | U163: huyct13

Sheet ALL SERVER VTT
A1: Tên hệ thống | B1: IP Server | C1: Đầu mối dịch vụ | D1: BU | E1: Đơn vị | F1: vCPU | G1: RAM (GB) | H1: Disk (GB) | I1: NAS (GB) | J1: Pool tài nguyên | K1: Host aggregate | L1: Storage Pool | M1: Thời gian cấp máy chủ | N1: Mã SR | O1: Đầu mối PHT | P1: Ghi chú | Q1: Status | R1: Instance Name | S1: Instance Type | T1: Instance OS | U1: Service | V1: Instance Manager | W1: Device Manager | X1: Tenant | Y1: Role | Z1: Manufacturer | AA1: Type | AB1: Serial number | AC1: Site | AD1: Location | AE1: Rack | AF1: Tải trung bình CPU (%) | AG1: Tải trung bình RAM (%) | AH1: % Disk sử dụng
A2: IM-BCCS 2.0 | B2: 10.240.147.58 | C2: anhdk | D2: QLBH | E2: TTCNTT | F2: 56 | G2: 252 | H2: 324 | R2: SV_10.240.147.58-bccs2-im-extws-01-OS | S2: Device OS | T2: CentOS release 6.8 kernel 2.6.32-642.el6.x86_64 | U2: IM - BCCS2.0 | V2: huonglttt | W2: thucnh2 | X2: VIETTEL | Y2: Server | Z2: Cisco | AA2: UCSC-C240-M4SX | AB2: FCH2106V15Q | AC2: HLC | AD2: Floor 6.1 | AE2: T6.1-J06
A3: IM-BCCS 2.0 | B3: 10.240.147.59 | C3: anhdk | D3: QLBH | E3: TTCNTT | F3: 56 | G3: 252 | H3: 324 | R3: SV_10.240.147.59-bccs2-im-extws-02-OS | S3: Device OS | T3: CentOS release 6.8 kernel 2.6.32-642.el6.x86_64 | U3: IM - BCCS2.0 | V3: huonglttt | W3: thucnh2 | X3: VIETTEL | Y3: Server | Z3: Cisco | AA3: UCSC-C240-M4SX | AB3: FCH2109V100 | AC3: HLC | AD3: Floor 6.1 | AE3: T6.1-K07
A4: IM-BCCS 2.0 | B4: 10.240.147.60 | C4: anhdk | D4: QLBH | E4: TTCNTT | F4: 48 | G4: 189 | H4: 324 | R4: SV_10.240.147.60-bccs2-im-internalws-01-OS | S4: Device OS | T4: CentOS release 6.8 kernel 2.6.32-642.el6.x86_64 | U4: IM - BCCS2.0 | V4: huonglttt | W4: thucnh2 | X4: VIETTEL | Y4: Server | Z4: Cisco | AA4: UCSC-C240-M4SX | AB4: FCH2112V0NF | AC4: HLC | AD4: Floor 6.1 | AE4: T6.1-J06
A5: IM-BCCS 2.0 | B5: 10.240.147.61 | C5: anhdk | D5: QLBH | E5: TTCNTT | F5: 48 | G5: 189 | H5: 324 | R5: SV_10.240.147.61-bccs2-im-internalws-02-OS | S5: Device OS | T5: CentOS release 6.8 kernel 2.6.32-642.el6.x86_64 | U5: IM - BCCS2.0 | V5: huonglttt | W5: thucnh2 | X5: VIETTEL | Y5: Server | Z5: Cisco | AA5: UCSC-C240-M4SX | AB5: FCH2112V0LH | AC5: HLC | AD5: Floor 6.1 | AE5: T6.1-J06
A6: IM-BCCS 2.0 | B6: 10.240.147.62 | C6: anhdk | D6: QLBH | E6: TTCNTT | F6: 48 | G6: 189 | H6: 324 | R6: SV_10.240.147.62-bccs2-im-intws-03-OS | S6: Device OS | T6: CentOS release 6.8 kernel 2.6.32-642.el6.x86_64 | U6: IM - BCCS2.0 | V6: huonglttt | W6: thucnh2 | X6: VIETTEL | Y6: Server | Z6: Cisco | AA6: UCSC-C240-M4SX | AB6: FCH2112V0N8 | AC6: HLC | AD6: Floor 6.1 | AE6: T6.1-K07
A7: IM-BCCS 2.0 | B7: 10.240.147.63 | C7: anhdk | D7: QLBH | E7: TTCNTT | F7: 32 | G7: 63 | H7: 344 | R7: SV_10.240.147.63-bccs2-im-solr-01-OS | S7: VM | T7: CentOS release 6.10 kernel 2.6.32-754.29.1.el6.x86_64 | U7: IM - BCCS2.0 | V7: huonglttt | W7: 0 | X7: VIETTEL | Y7: Server | Z7: Fujitsu | AA7: PRIMERGY RX2530 M5 | AB7: MALU006553 | AC7: HLC | AD7: Floor 6.2 | AE7: T6.2-G04
A8: IM-BCCS 2.0 | B8: 10.240.147.64 | C8: anhdk | D8: QLBH | E8: TTCNTT | F8: 32 | G8: 63 | H8: 344 | R8: SV_10.240.147.64-bccs2-im-solr-02-OS | S8: VM | T8: CentOS release 6.10 kernel 2.6.32-754.29.1.el6.x86_64 | U8: IM - BCCS2.0 | V8: huonglttt | W8: 0 | X8: VIETTEL | Y8: Server | Z8: Fujitsu | AA8: PRIMERGY CX2560 M5 | AB8: MAAG001433 | AC8: HLC | AD8: Floor 6.2 | AE8: T6.2-G12
A9: IM-BCCS 2.0 | B9: 10.240.147.65 | C9: anhdk | D9: QLBH | E9: TTCNTT | F9: 32 | G9: 63 | H9: 344 | R9: SV_10.240.147.65-bccs2-im-solr-03-OS | S9: VM | T9: CentOS release 6.10 kernel 2.6.32-754.29.1.el6.x86_64 | U9: IM - BCCS2.0 | V9: huonglttt | W9: 0 | X9: VIETTEL | Y9: Server | Z9: Fujitsu | AA9: PRIMERGY RX2530 M5 | AB9: MALU008594 | AC9: HLC | AD9: Floor 6.2 | AE9: T6.2-H06
A10: IM-BCCS 2.0 | B10: 10.240.147.66 | C10: anhdk | D10: QLBH | E10: TTCNTT | F10: 32 | G10: 189 | H10: 324 | R10: bccs2-im-web-02-OS | S10: Device OS | T10: CentOS release 6.8 kernel 2.6.32-642.el6.x86_64 | U10: IM - BCCS2.0 | V10: huonglttt | W10: thucnh2 | X10: VIETTEL | Y10: Server | Z10: Cisco | AA10: UCSC-C240-M4SX | AB10: FCH2109V17R | AC10: HLC | AD10: Floor 6.1 | AE10: T6.1-K07
A11: IM-BCCS 2.0 | B11: 10.240.147.67 | C11: anhdk | D11: QLBH | E11: TTCNTT | F11: 32 | G11: 189 | H11: 324 | R11: SV_10.240.147.67-bccs2-im-web-01-OS | S11: Device OS | T11: CentOS release 6.8 kernel 2.6.32-642.el6.x86_64 | U11: IM - BCCS2.0 | V11: huonglttt | W11: thucnh2 | X11: VIETTEL | Y11: Server | Z11: Cisco | AA11: UCSC-C240-M4SX | AB11: FCH2109V0Y6 | AC11: HLC | AD11: Floor 6.1 | AE11: T6.1-J06
A12: IM-BCCS 2.0 | B12: 10.240.147.68 | C12: anhdk | D12: QLBH | E12: TTCNTT | F12: 32 | G12: 63 | H12: 344 | R12: App-10.240.147.68 | S12: VM | T12: CentOS Stream 9 kernel 5.14.0-480.el9.x86_64 | U12: IM - BCCS2.0 | V12: sonvt8 | W12: 0 | X12: VIETTEL | Y12: Server | Z12: HPE | AA12: ProLiant DL360 Gen10 | AB12: SGH143TSYB | AC12: HLC | AD12: 20T-Floor 6.IDC2 | AE12: T6.IDC2-Q14
A13: IM-BCCS 2.0 | B13: 10.240.147.69 | C13: anhdk | D13: QLBH | E13: TTCNTT | F13: 32 | G13: 63 | H13: 344 | R13: App-10.240.147.69 | S13: VM | T13: CentOS Stream 9 kernel 5.14.0-480.el9.x86_64 | U13: IM - BCCS2.0 | V13: sonvt8 | W13: 0 | X13: VIETTEL | Y13: Server | Z13: HPE | AA13: ProLiant DL360 Gen10 | AB13: SGH213YMXZ | AC13: HLC | AD13: 20T-Floor 6.IDC2 | AE13: T6.IDC2-Q10
A14: IM-BCCS 2.0 | B14: 10.240.147.70 | C14: anhdk | D14: QLBH | E14: TTCNTT | F14: 32 | G14: 63 | H14: 344 | R14: App-10.240.147.70 | S14: VM | T14: CentOS Stream 9 kernel 5.14.0-480.el9.x86_64 | U14: IM - BCCS2.0 | V14: sonvt8 | W14: 0 | X14: VIETTEL | Y14: Server | Z14: HPE | AA14: ProLiant DL360 Gen10 | AB14: SGH143TSYL | AC14: HLC | AD14: 20T-Floor 6.IDC2 | AE14: T6.IDC2-Q14
A15: Smartmotor | B15: 10.207.163.59 | C15: hoangnt14 | D15: CSKH | E15: TTCNTT | F15: 6 | G15: 33 | H15: 500 | R15: App-10.207.163.59 | S15: VM | T15: CentOS Stream 9 kernel 5.14.0-480.el9.x86_64 | U15: Smart motor | V15: hoangnt14 | W15: 0 | X15: VTT | Y15: Server | Z15: Dell | AA15: PowerEdge R640 | AB15: 357XB33 | AC15: HLC | AD15: Floor 7.2 | AE15: T7.2-C05
A16: Smartmotor | B16: 10.207.163.60 | C16: hoangnt14 | D16: CSKH | E16: TTCNTT | F16: 6 | G16: 33 | H16: 100 | R16: App-10.207.163.60 | S16: VM | T16: CentOS Stream 9 kernel 5.14.0-480.el9.x86_64 | U16: Smart motor | V16: hoangnt14 | W16: 0 | X16: VTT | Y16: Server | Z16: HPE | AA16: ProLiant DL360 Gen10 | AB16: SGH143TSKL | AC16: HLC | AD16: Floor 7.2 | AE16: T7.2-A15
A17: Smartmotor | B17: 10.207.163.61 | C17: hoangnt14 | D17: CSKH | E17: TTCNTT | F17: 6 | G17: 33 | H17: 100 | R17: App-10.207.163.61 | S17: VM | T17: CentOS Stream 9 kernel 5.14.0-480.el9.x86_64 | U17: Smart motor | V17: hoangnt14 | W17: 0 | X17: VTT | Y17: Server | Z17: Fujitsu | AA17: PRIMERGY CX2560 M5 | AB17: MAAG002350 | AC17: HLC | AD17: Floor 6.2 | AE17: T6.2-G02
A18: Smartmotor | B18: 10.207.163.62 | C18: hoangnt14 | D18: CSKH | E18: TTCNTT | F18: 6 | G18: 33 | H18: 100 | R18: App-10.207.163.62 | S18: VM | T18: CentOS Stream 9 kernel 5.14.0-480.el9.x86_64 | U18: Smart motor | V18: hoangnt14 | W18: 0 | X18: VTT | Y18: Server | Z18: Fujitsu | AA18: PRIMERGY CX2560 M5 | AB18: MAAG002395 | AC18: HLC | AD18: Floor 6.2 | AE18: T6.2-G02
A19: Smartmotor | B19: 10.207.163.63 | C19: hoangnt14 | D19: CSKH | E19: TTCNTT | F19: 9 | G19: 52 | H19: 100 | R19: App-10.207.163.63 | S19: VM | T19: CentOS Stream 9 kernel 5.14.0-480.el9.x86_64 | U19: Smart motor | V19: hoangnt14 | W19: 0 | X19: VTT | Y19: Server | Z19: HPE | AA19: ProLiant DL360 Gen10 | AB19: SGH143TSLV | AC19: HLC | AD19: Floor 7.2 | AE19: T7.2-A15
A20: Smartmotor | B20: 10.207.163.64 | C20: hoangnt14 | D20: CSKH | E20: TTCNTT | F20: 9 | G20: 52 | H20: 100 | R20: App-10.207.163.64 | S20: VM | T20: CentOS Stream 9 kernel 5.14.0-480.el9.x86_64 | U20: Smart motor | V20: hoangnt14 | W20: 0 | X20: VTT | Y20: Server | Z20: HPE | AA20: ProLiant DL360 Gen10 | AB20: SGH143TSJ1 | AC20: HLC | AD20: Floor 7.2 | AE20: T7.2-A15
A21: Smartmotor | B21: 10.207.163.65 | C21: hoangnt14 | D21: CSKH | E21: TTCNTT | F21: 9 | G21: 52 | H21: 100 | R21: App-10.207.163.65 | S21: VM | T21: CentOS Stream 9 kernel 5.14.0-480.el9.x86_64 | U21: Smart motor | V21: hoangnt14 | W21: 0 | X21: VTT | Y21: Server | Z21: Fujitsu | AA21: PRIMERGY CX2560 M5 | AB21: MAAG002511 | AC21: HLC | AD21: Floor 6.2 | AE21: T6.2-G02
A22: Smartmotor | B22: 10.207.163.66 | C22: hoangnt14 | D22: CSKH | E22: TTCNTT | F22: 9 | G22: 18 | H22: 100 | R22: App-10.207.163.66 | S22: VM | T22: CentOS Stream 9 kernel 5.14.0-480.el9.x86_64 | U22: Smart motor | V22: hoangnt14 | W22: 0 | X22: VTT | Y22: Server | Z22: HPE | AA22: ProLiant DL360 Gen10 | AB22: SGH143TST6 | AC22: HLC | AD22: Floor 7.2 | AE22: T7.2-A15
A23: Smartmotor | B23: 10.207.163.67 | C23: hoangnt14 | D23: CSKH | E23: TTCNTT | F23: 9 | G23: 18 | H23: 100 | R23: App-10.207.163.67 | S23: VM | T23: CentOS Stream 9 kernel 5.14.0-480.el9.x86_64 | U23: Smart motor | V23: hoangnt14 | W23: 0 | X23: VTT | Y23: Server | Z23: Fujitsu | AA23: PRIMERGY CX2560 M5 | AB23: MAAG002350 | AC23: HLC | AD23: Floor 6.2 | AE23: T6.2-G02
A24: Smartmotor | B24: 10.207.163.68 | C24: hoangnt14 | D24: CSKH | E24: TTCNTT | F24: 9 | G24: 18 | H24: 100 | R24: App-10.207.163.68 | S24: VM | T24: CentOS Stream 9 kernel 5.14.0-480.el9.x86_64 | U24: Smart motor | V24: hoangnt14 | W24: 0 | X24: VTT | Y24: Server | Z24: Fujitsu | AA24: PRIMERGY CX2560 M5 | AB24: MAAG002396 | AC24: HLC | AD24: Floor 6.2 | AE24: T6.2-G02
A25: Survey | B25: 10.207.57.144 | C25: hoangnt14 | D25: CSKH | E25: TTCNTT | F25: 8 | G25: 16 | H25: 60 | R25: App-10.207.57.144 | S25: VM | T25: CentOS Stream 9 kernel 5.14.0-480.el9.x86_64 | U25: 0 | V25: hungpm8 | W25: 0 | X25: 0 | Y25: Server | Z25: HPE | AA25: ProLiant DL360 Gen10 | AB25: SGH103YD0V | AC25: HLC | AD25: Floor 7.2 | AE25: T7.2-C08
A26: Survey | B26: 10.207.57.145 | C26: hoangnt14 | D26: CSKH | E26: TTCNTT | F26: 8 | G26: 16 | H26: 60 | R26: App-10.207.57.145 | S26: VM | T26: CentOS Stream 9 kernel 5.14.0-480.el9.x86_64 | U26: 0 | V26: anhtt69 | W26: 0 | X26: 0 | Y26: Server | Z26: Dell | AA26: PowerEdge R640 | AB26: 2MQR643 | AC26: HLC | AD26: Floor 7.2 | AE26: T7.2-C04
A27: Survey | B27: 10.207.57.147 | C27: hoangnt14 | D27: CSKH | E27: TTCNTT | F27: 8 | G27: 16 | H27: 60 | R27: App-10.207.57.147 | S27: VM | T27: CentOS Stream 9 kernel 5.14.0-480.el9.x86_64 | U27: 0 | V27: hungpm8 | W27: 0 | X27: 0 | Y27: Server | Z27: HPE | AA27: ProLiant DL360 Gen10 | AB27: SGH103YC6N | AC27: HLC | AD27: Floor 7.2 | AE27: T7.2-C08
A28: Survey | B28: 10.207.57.148 | C28: hoangnt14 | D28: CSKH | E28: TTCNTT | F28: 8 | G28: 16 | H28: 60 | R28: App-10.207.57.148 | S28: VM | T28: CentOS Stream 9 kernel 5.14.0-480.el9.x86_64 | U28: 0 | V28: hungpm8 | W28: 0 | X28: 0 | Y28: Server | Z28: HPE | AA28: ProLiant DL360 Gen10 | AB28: SGH103YD0X | AC28: HLC | AD28: Floor 7.2 | AE28: T7.2-C08
A29: Survey | B29: 10.207.57.149 | C29: hoangnt14 | D29: CSKH | E29: TTCNTT | F29: 8 | G29: 16 | H29: 60 | R29: App-10.207.57.149 | S29: VM | T29: CentOS Stream 9 kernel 5.14.0-480.el9.x86_64 | U29: 0 | V29: anhtt69 | W29: 0 | X29: 0 | Y29: Server | Z29: Dell | AA29: PowerEdge R640 | AB29: 1MQR643 | AC29: HLC | AD29: Floor 7.2 | AE29: T7.2-C03
A30: Survey | B30: 10.207.57.151 | C30: hoangnt14 | D30: CSKH | E30: TTCNTT | F30: 8 | G30: 16 | H30: 60 | R30: App-10.207.57.151 | S30: VM | T30: CentOS Stream 9 kernel 5.14.0-480.el9.x86_64 | U30: 0 | V30: hungpm8 | W30: 0 | X30: 0 | Y30: Server | Z30: HPE | AA30: ProLiant DL360 Gen10 | AB30: SGH103YCZW | AC30: HLC | AD30: Floor 7.2 | AE30: T7.2-C09
A31: Survey | B31: 10.207.57.152 | C31: hoangnt14 | D31: CSKH | E31: TTCNTT | F31: 8 | G31: 16 | H31: 60 | R31: App-10.207.57.152 | S31: VM | T31: CentOS Stream 9 kernel 5.14.0-480.el9.x86_64 | U31: 0 | V31: anhtt69 | W31: 0 | X31: 0 | Y31: Server | Z31: Dell | AA31: PowerEdge R640 | AB31: 8QQR643 | AC31: HLC | AD31: Floor 7.2 | AE31: T7.2-C04
A32: Survey | B32: 10.207.57.153 | C32: hoangnt14 | D32: CSKH | E32: TTCNTT | F32: 8 | G32: 16 | H32: 60 | R32: App-10.207.57.153 | S32: VM | T32: CentOS Stream 9 kernel 5.14.0-480.el9.x86_64 | U32: 0 | V32: anhtt69 | W32: 0 | X32: 0 | Y32: Server | Z32: Dell | AA32: PowerEdge R640 | AB32: 1MQR643 | AC32: HLC | AD32: Floor 7.2 | AE32: T7.2-C03
A33: Survey | B33: 10.207.57.154 | C33: hoangnt14 | D33: CSKH | E33: TTCNTT | F33: 8 | G33: 16 | H33: 60 | R33: App-10.207.57.154 | S33: VM | T33: CentOS Stream 9 kernel 5.14.0-480.el9.x86_64 | U33: 0 | V33: hungpm8 | W33: 0 | X33: 0 | Y33: Server | Z33: HPE | AA33: ProLiant DL360 Gen10 | AB33: SGH103YCZW | AC33: HLC | AD33: Floor 7.2 | AE33: T7.2-C09
A34: Survey | B34: 10.207.57.155 | C34: hoangnt14 | D34: CSKH | E34: TTCNTT | F34: 8 | G34: 16 | H34: 60 | R34: App-10.207.57.155 | S34: VM | T34: CentOS Stream 9 kernel 5.14.0-480.el9.x86_64 | U34: 0 | V34: hungpm8 | W34: 0 | X34: 0 | Y34: Server | Z34: HPE | AA34: ProLiant DL360 Gen10 | AB34: SGH103YCZF | AC34: HLC | AD34: Floor 7.2 | AE34: T7.2-C09
A35: Survey | B35: 10.207.57.156 | C35: hoangnt14 | D35: CSKH | E35: TTCNTT | F35: 8 | G35: 16 | H35: 60 | R35: App-10.207.57.156 | S35: VM | T35: CentOS Stream 9 kernel 5.14.0-480.el9.x86_64 | U35: 0 | V35: anhtt69 | W35: 0 | X35: 0 | Y35: Server | Z35: Dell | AA35: PowerEdge R640 | AB35: 8QQR643 | AC35: HLC | AD35: Floor 7.2 | AE35: T7.2-C04
A36: Survey | B36: 10.207.57.157 | C36: hoangnt14 | D36: CSKH | E36: TTCNTT | F36: 8 | G36: 16 | H36: 60 | R36: App-10.207.57.157 | S36: VM | T36: CentOS Stream 9 kernel 5.14.0-480.el9.x86_64 | U36: 0 | V36: hungpm8 | W36: 0 | X36: 0 | Y36: Server | Z36: HPE | AA36: ProLiant DL360 Gen10 | AB36: SGH103YC6N | AC36: HLC | AD36: Floor 7.2 | AE36: T7.2-C08
... A40: Survey | B40: 10.254.150.79 | C40: hoangnt14 | D40: CSKH | E40: TTCNTT | F40: 8 | G40: 16 | H40: 60 | R40: DB-10.254.150.79 | S40: VM | T40: CentOS Stream 9 kernel 5.14.0-480.el9.x86_64 | U40: 0 | V40: hungpm8 | W40: 0 | X40: 0 | Y40: Server | Z40: HPE | AA40: ProLiant DL360 Gen10 | AB40: SGH103YD0X | AC40: HLC | AD40: Floor 7.2 | AE40: T7.2-C08
A41: Survey | B41: 10.254.150.80 | C41: hoangnt14 | D41: CSKH | E41: TTCNTT | F41: 8 | G41: 16 | H41: 60 | R41: DB-10.254.150.80 | S41: VM | T41: CentOS Stream 9 kernel 5.14.0-480.el9.x86_64 | U41: 0 | V41: locnm2 | W41: nhienpv | X41: #N/A | Y41: Server | Z41: Dell | AA41: PowerEdge R640 | AB41: 8QQR643 | AC41: HLC | AD41: Floor 7.2 | AE41: T7.2-C04
A42: BCCS_CC2.0 | B42: 10.240.147.43 | C42: hoangnt14 | D42: CSKH | E42: TTCNTT | F42: 2xIntel Xeon E5-2620v4 | G42: 192 | H42: 500 | R42: SV_10.240.147.43-bccs2-cc-websv-01-OS | S42: Device OS | T42: CentOS release 6.8 kernel 2.6.32-642.el6.x86_64 | U42: CC - BCCS2.0 | V42: huonglttt | W42: thucnh2 | X42: VIETTEL | Y42: Server | Z42: Cisco | AA42: UCSC-C240-M4SX | AB42: FCH2108V0S5 | AC42: HLC | AD42: Floor 6.1 | AE42: T6.1-J05
A43: BCCS_CC2.0 | B43: 10.240.147.44 | C43: hoangnt14 | D43: CSKH | E43: TTCNTT | F43: 2xIntel Xeon E5-2620v4 | G43: 192 | H43: 500 | R43: SV_10.240.147.44-bccs2-cc-websv-02-OS | S43: Device OS | T43: CentOS release 6.8 kernel 2.6.32-642.el6.x86_64 | U43: CC - BCCS2.0 | V43: huonglttt | W43: thucnh2 | X43: VIETTEL | Y43: Server | Z43: Cisco | AA43: UCSC-C240-M4SX | AB43: FCH2108V0SZ | AC43: HLC | AD43: Floor 6.1 | AE43: T6.1-J05
A44: BCCS_CC2.0 | B44: 10.240.147.45 | C44: hoangnt14 | D44: CSKH | E44: TTCNTT | F44: 2xIntel Xeon E5-2620v4 | G44: 192 | H44: 500 | R44: SV_10.240.147.45-bccs2-cc-websv-03-OS | S44: Device OS | T44: CentOS release 6.8 kernel 2.6.32-642.el6.x86_64 | U44: CC - BCCS2.0 | V44: huonglttt | W44: thucnh2 | X44: VIETTEL | Y44: Server | Z44: Cisco | AA44: UCSC-C240-M4SX | AB44: FCH2111V24W | AC44: HLC | AD44: Floor 6.1 | AE44: T6.1-J05
A45: BCCS_CC2.0 | B45: 10.240.147.46 | C45: hoangnt14 | D45: CSKH | E45: TTCNTT | F45: 2xIntel Xeon E5-2620v4 | G45: 192 | H45: 500 | R45: SV_10.240.147.46-bccs2-cc-websv-04-OS | S45: Device OS | T45: CentOS release 6.8 kernel 2.6.32-642.el6.x86_64 | U45: CC - BCCS2.0 | V45: huonglttt | W45: thucnh2 | X45: VIETTEL | Y45: Server | Z45: Cisco | AA45: UCSC-C240-M4SX | AB45: FCH2109V15A | AC45: HLC | AD45: Floor 6.1 | AE45: T6.1-K11
A46: BCCS_CC2.0 | B46: 10.240.147.47 | C46: hoangnt14 | D46: CSKH | E46: TTCNTT | F46: 2xIntel Xeon E5-2620v4 | G46: 192 | H46: 500 | R46: SV_10.240.147.47-bccs2-cc-solrcc-02-OS | S46: Device OS | T46: CentOS release 6.8 kernel 2.6.32-642.el6.x86_64 | U46: CC - BCCS2.0 | V46: huonglttt | W46: thucnh2 | X46: VIETTEL | Y46: Server | Z46: Cisco | AA46: UCSC-C240-M4SX | AB46: FCH2109V16Y | AC46: HLC | AD46: Floor 6.1 | AE46: T6.1-K11
A47: BCCS_CC2.0 | B47: 10.240.147.25 | C47: hoangnt14 | D47: CSKH | E47: TTCNTT | F47: 2xIntel Xeon E5-2650v4 | G47: 192 | H47: 500 | R47: SV_10.240.147.25-bccs2-cc-extws-01-OS | S47: Device OS | T47: CentOS release 6.8 kernel 2.6.32-642.el6.x86_64 | U47: CC - BCCS2.0 | V47: huonglttt | W47: thucnh2 | X47: VIETTEL | Y47: Server | Z47: Cisco | AA47: UCSC-C240-M4SX | AB47: FCH2110V2BN | AC47: HLC | AD47: Floor 6.1 | AE47: T6.1-J05
A48: BCCS_CC2.0 | B48: 10.240.147.26 | C48: hoangnt14 | D48: CSKH | E48: TTCNTT | F48: 2xIntel Xeon E5-2650v4 | G48: 192 | H48: 500 | R48: SV_10.240.147.26-bccs2-cc-extws-02-OS | S48: Device OS | T48: CentOS release 6.8 kernel 2.6.32-642.el6.x86_64 | U48: CC - BCCS2.0 | V48: huonglttt | W48: thucnh2 | X48: VIETTEL | Y48: Server | Z48: Cisco | AA48: UCSC-C240-M4SX | AB48: FCH2038V217 | AC48: HLC | AD48: Floor 6.1 | AE48: T6.1-K11
A49: BCCS_CC2.0 | B49: 10.240.147.27 | C49: hoangnt14 | D49: CSKH | E49: TTCNTT | F49: 2xIntel Xeon E5-2620v4 | G49: 256 | H49: 500 | R49: SV_10.240.147.27-bccs2-cc-internalws-01-OS | S49: Device OS | T49: CentOS release 6.8 kernel 2.6.32-642.el6.x86_64 | U49: CC - BCCS2.0 | V49: huonglttt | W49: thucnh2 | X49: VIETTEL | Y49: Server | Z49: Cisco | AA49: UCSC-C240-M4SX | AB49: FCH2111V1D0 | AC49: HLC | AD49: Floor 6.1 | AE49: T6.1-J05
A50: BCCS_CC2.0 | B50: 10.240.147.28 | C50: hoangnt14 | D50: CSKH | E50: TTCNTT | F50: 2xIntel Xeon E5-2620v4 | G50: 256 | H50: 500 | R50: SV_10.240.147.28-bccs2-cc-internalws-02-OS | S50: Device OS | T50: CentOS release 6.8 kernel 2.6.32-642.el6.x86_64 | U50: CC - BCCS2.0 | V50: huonglttt | W50: thucnh2 | X50: VIETTEL | Y50: Server | Z50: Cisco | AA50: UCSC-C240-M4SX | AB50: FCH2108V0ZG | AC50: HLC | AD50: Floor 6.1 | AE50: T6.1-J05
A51: BCCS_CC2.0 | B51: 10.240.147.29 | C51: hoangnt14 | D51: CSKH | E51: TTCNTT | F51: 2xIntel Xeon E5-2620v4 | G51: 256 | H51: 500 | R51: SV_10.240.147.29-bccs2-cc-internalws-03-OS | S51: Device OS | T51: CentOS release 6.8 kernel 2.6.32-642.el6.x86_64 | U51: 0 | V51: huonglttt | W51: thucnh2 | X51: VIETTEL | Y51: Server | Z51: Cisco | AA51: UCSC-C240-M4SX | AB51: FCH2111V1ZZ | AC51: HLC | AD51: Floor 6.1 | AE51: T6.1-K11
A52: BCCS_CC2.0 | B52: 10.240.147.30 | C52: hoangnt14 | D52: CSKH | E52: TTCNTT | F52: 2xIntel Xeon E5-2620v4 | G52: 256 | H52: 500 | R52: SV_10.240.147.30-bccs2-cc-internalws-04-OS | S52: Device OS | T52: CentOS release 6.8 kernel 2.6.32-642.el6.x86_64 | U52: 0 | V52: huonglttt | W52: thucnh2 | X52: VIETTEL | Y52: Server | Z52: Cisco | AA52: UCSC-C240-M4SX | AB52: FCH2109V121 | AC52: HLC | AD52: Floor 6.1 | AE52: T6.1-K11
A53: BCCS_CC2.0 | B53: 10.240.147.34 | C53: hoangnt14 | D53: CSKH | E53: TTCNTT | F53: 2xIntel Xeon E5-2650v4 | G53: 256 | H53: 500 | R53: SV_10.240.147.34-bccs2-cc-solrctc-01-OS | S53: Device OS | T53: CentOS release 6.8 kernel 2.6.32-642.el6.x86_64 | U53: 0 | V53: huonglttt | W53: thucnh2 | X53: VIETTEL | Y53: Server | Z53: Cisco | AA53: UCSC-C240-M4SX | AB53: FCH2138V07A | AC53: HLC | AD53: Floor 6.1 | AE53: T6.1-I06
A54: BCCS_CC2.0 | B54: 10.240.147.35 | C54: hoangnt14 | D54: CSKH | E54: TTCNTT | F54: 2xIntel Xeon E5-2650v4 | G54: 256 | H54: 500 | R54: bccs2-cc-solrctc-02-OS | S54: Device OS | T54: CentOS release 6.8 kernel 2.6.32-642.el6.x86_64 | U54: 0 | V54: huonglttt | W54: thucnh2 | X54: VIETTEL | Y54: Server | Z54: Cisco | AA54: UCSC-C240-M4SX | AB54: FCH2109V13G | AC54: HLC | AD54: Floor 6.1 | AE54: T6.1-I06
A55: BCCS_CC2.0 | B55: 10.240.147.36 | C55: hoangnt14 | D55: CSKH | E55: TTCNTT | F55: 2xIntel Xeon E5-2650v4 | G55: 256 | H55: 500 | R55: SV_10.240.147.36-bccs2-cc-solrctc-03-OS | S55: Device OS | T55: CentOS release 6.8 kernel 2.6.32-642.el6.x86_64 | U55: 0 | V55: huonglttt | W55: thucnh2 | X55: VIETTEL | Y55: Server | Z55: Cisco | AA55: UCSC-C240-M4SX | AB55: FCH2109V15G | AC55: HLC | AD55: Floor 6.1 | AE55: T6.1-I06
A56: BCCS_CC2.0 | B56: 10.240.147.37 | C56: hoangnt14 | D56: CSKH | E56: TTCNTT | F56: 2xIntel Xeon E5-2650v4 | G56: 256 | H56: 500 | R56: SV_10.240.147.37-bccs2-cc-solrctc-04-OS | S56: Device OS | T56: CentOS release 6.8 kernel 2.6.32-642.el6.x86_64 | U56: 0 | V56: huonglttt | W56: thucnh2 | X56: VIETTEL | Y56: Server | Z56: Cisco | AA56: UCSC-C240-M4SX | AB56: FCH2109V0NN | AC56: HLC | AD56: Floor 6.1 | AE56: T6.1-I06
A57: BCCS_CC2.0 | B57: 10.240.147.38 | C57: hoangnt14 | D57: CSKH | E57: TTCNTT | F57: 2xIntel Xeon E5-2650v4 | G57: 256 | H57: 500 | R57: SV_10.240.147.38-bccs2-cc-solrctc-05-OS | S57: Device OS | T57: CentOS release 6.8 kernel 2.6.32-642.el6.x86_64 | U57: 0 | V57: huonglttt | W57: thucnh2 | X57: VIETTEL | Y57: Server | Z57: Cisco | AA57: UCSC-C240-M4SX | AB57: FCH2108V0HQ | AC57: HLC | AD57: Floor 6.1 | AE57: T6.1-K06
A58: BCCS_CC2.0 | B58: 10.240.147.39 | C58: hoangnt14 | D58: CSKH | E58: TTCNTT | F58: 2xIntel Xeon E5-2650v4 | G58: 256 | H58: 500 | R58: SV_10.240.147.39-bccs2-cc-solrctc-06-OS | S58: Device OS | T58: CentOS release 6.8 kernel 2.6.32-642.el6.x86_64 | U58: 0 | V58: huonglttt | W58: thucnh2 | X58: VIETTEL | Y58: Server | Z58: Cisco | AA58: UCSC-C240-M4SX | AB58: FCH2109V0G5 | AC58: HLC | AD58: Floor 6.1 | AE58: T6.1-K06
A59: BCCS_CC2.0 | B59: 10.240.147.40 | C59: hoangnt14 | D59: CSKH | E59: TTCNTT | F59: 2xIntel Xeon E5-2650v4 | G59: 256 | H59: 500 | R59: SV_10.240.147.40-bccs2-cc-solrctc-07-OS | S59: Device OS | T59: CentOS release 6.8 kernel 2.6.32-642.el6.x86_64 | U59: 0 | V59: huonglttt | W59: thucnh2 | X59: VIETTEL | Y59: Server | Z59: Cisco | AA59: UCSC-C240-M4SX | AB59: FCH2111V20D | AC59: HLC | AD59: Floor 6.1 | AE59: T6.1-K06
A60: BCCS_CC2.0 | B60: 10.240.147.41 | C60: hoangnt14 | D60: CSKH | E60: TTCNTT | F60: 2xIntel Xeon E5-2650v4 | G60: 256 | H60: 500 | R60: SV_10.240.147.41-bccs2-cc-solrctc-08-OS | S60: Device OS | T60: CentOS release 6.8 kernel 2.6.32-642.el6.x86_64 | U60: 0 | V60: huonglttt | W60: thucnh2 | X60: VIETTEL | Y60: Server | Z60: Cisco | AA60: UCSC-C240-M4SX | AB60: FCH2109V154 | AC60: HLC | AD60: Floor 6.1 | AE60: T6.1-K06
A61: BCCS_CC2.0 | B61: 10.240.147.42 | C61: hoangnt14 | D61: CSKH | E61: TTCNTT | F61: 2xIntel Xeon E5-2650v4 | G61: 256 | H61: 500 | R61: SV_10.240.147.42-bccs2-cc-solrctc-09-OS | S61: Device OS | T61: CentOS release 6.8 kernel 2.6.32-642.el6.x86_64 | U61: 0 | V61: huonglttt | W61: thucnh2 | X61: VIETTEL | Y61: Server | Z61: Cisco | AA61: UCSC-C240-M4SX | AB61: FCH2109V14S | AC61: HLC | AD61: Floor 6.1 | AE61: T6.1-K06
A62: BCCS_CC2.0 | B62: 10.240.147.31 | C62: hoangnt14 | D62: CSKH | E62: TTCNTT | F62: 2xIntel Xeon E5-2650v4 | G62: 192 | H62: 500 | R62: SV_10.240.147.31-bccs2-cc-solrcc-01-OS | S62: Device OS | T62: CentOS release 6.8 kernel 2.6.32-642.el6.x86_64 | U62: 0 | V62: huonglttt | W62: thucnh2 | X62: VIETTEL | Y62: Server | Z62: Cisco | AA62: UCSC-C240-M4SX | AB62: FCH2110V3GP | AC62: HLC | AD62: Floor 6.1 | AE62: T6.1-I06
... A64: BCCS_CC2.0 | B64: 10.240.147.33 | C64: hoangnt14 | D64: CSKH | E64: TTCNTT | F64: 2xIntel Xeon E5-2650v4 | G64: 192 | H64: 500 | R64: SV_10.240.147.33-bccs2-im-solr-03-OS | S64: Device OS | T64: CentOS release 6.8 kernel 2.6.32-642.el6.x86_64 | U64: 0 | V64: huonglttt | W64: thucnh2 | X64: VIETTEL | Y64: Server | Z64: Cisco | AA64: UCSC-C240-M4SX | AB64: FCH2110V1ZF | AC64: HLC | AD64: Floor 6.1 | AE64: T6.1-K06
A65: BCCS_CC2.0 | B65: 10.240.147.150 | C65: hoangnt14 | D65: CSKH | E65: TTCNTT | F65: 16 | G65: 64 | H65: 120 | R65: App-10.240.147.150 | S65: VM | T65: CentOS Stream 9 kernel 5.14.0-480.el9.x86_64 | U65: 0 | V65: chinhvc2 | W65: nguyentl | X65: VIETTEL | Y65: Server | Z65: HPE | AA65: ProLiant DL360 Gen10 | AB65: SGH213YMYC | AC65: HLC | AD65: 20T-Floor 6.IDC2 | AE65: T6.IDC2-Q10
A66: BCCS_CC2.0 | B66: 10.240.147.151 | C66: hoangnt14 | D66: CSKH | E66: TTCNTT | F66: 16 | G66: 64 | H66: 120 | R66: App-10.240.147.151 | S66: VM | T66: CentOS Stream 9 kernel 5.14.0-480.el9.x86_64 | U66: 0 | V66: chinhvc2 | W66: nguyentl | X66: VIETTEL | Y66: Server | Z66: HPE | AA66: ProLiant DL360 Gen10 | AB66: SGH143TSW8 | AC66: HLC | AD66: 20T-Floor 6.IDC2 | AE66: T6.IDC2-Q12B
A67: BCCS_CC2.0 | B67: 10.240.147.152 | C67: hoangnt14 | D67: CSKH | E67: TTCNTT | F67: 16 | G67: 64 | H67: 120 | R67: App-10.240.147.152 | S67: VM | T67: CentOS Stream 9 kernel 5.14.0-480.el9.x86_64 | U67: 0 | V67: chinhvc2 | W67: nguyentl | X67: VIETTEL | Y67: Server | Z67: HPE | AA67: ProLiant DL360 Gen10 | AB67: SGH213YMXZ | AC67: HLC | AD67: 20T-Floor 6.IDC2 | AE67: T6.IDC2-Q10
A68: BCCS_CC2.0 | B68: 10.240.147.153 | C68: hoangnt14 | D68: CSKH | E68: TTCNTT | F68: 16 | G68: 64 | H68: 120 | R68: App-10.240.147.153 | S68: VM | T68: CentOS Stream 9 kernel 5.14.0-480.el9.x86_64 | U68: 0 | V68: chinhvc2 | W68: nguyentl | X68: VIETTEL | Y68: Server | Z68: HPE | AA68: ProLiant DL360 Gen10 | AB68: SGH143TSW4 | AC68: HLC | AD68: 20T-Floor 6.IDC2 | AE68: T6.IDC2-Q12B
A69: BCCS_CC2.0 | B69: 10.240.147.154 | C69: hoangnt14 | D69: CSKH | E69: TTCNTT | F69: 16 | G69: 64 | H69: 120 | R69: App-10.240.147.154 | S69: VM | T69: CentOS Stream 9 kernel 5.14.0-480.el9.x86_64 | U69: 0 | V69: chinhvc2 | W69: nguyentl | X69: VIETTEL | Y69: Server | Z69: HPE | AA69: ProLiant DL360 Gen10 | AB69: SGH213YMXP | AC69: HLC | AD69: 20T-Floor 6.IDC2 | AE69: T6.IDC2-Q10
A70: BCCS_CC2.0 | B70: 10.240.147.155 | C70: hoangnt14 | D70: CSKH | E70: TTCNTT | F70: 16 | G70: 64 | H70: 120 | R70: App-10.240.147.155 | S70: VM | T70: CentOS Stream 9 kernel 5.14.0-480.el9.x86_64 | U70: 0 | V70: chinhvc2 | W70: nguyentl | X70: VIETTEL | Y70: Server | Z70: HPE | AA70: ProLiant DL360 Gen10 | AB70: SGH143TSYZ | AC70: HLC | AD70: 20T-Floor 6.IDC2 | AE70: T6.IDC2-Q14
A71: BCCS_CC2.0 | B71: 10.240.147.172 | C71: hoangnt14 | D71: CSKH | E71: TTCNTT | F71: 16 | G71: 64 | H71: 120 | R71: App-10.240.147.172 | S71: VM | T71: CentOS Stream 9 kernel 5.14.0-480.el9.x86_64 | U71: 0 | V71: chinhvc2 | W71: kietna | X71: VIETTEL | Y71: Server | Z71: HPE | AA71: ProLiant DL360 Gen10 | AB71: SGH103S2WK | AC71: HLC | AD71: Floor 7.2 | AE71: T7.2-C13
A72: BCCS_CC2.0 | B72: 10.240.147.173 | C72: hoangnt14 | D72: CSKH | E72: TTCNTT | F72: 16 | G72: 64 | H72: 120 | R72: App-10.240.147.173 | S72: VM | T72: CentOS Stream 9 kernel 5.14.0-480.el9.x86_64 | U72: 0 | V72: chinhvc2 | W72: kietna | X72: VIETTEL | Y72: Server | Z72: HPE | AA72: ProLiant DL360 Gen10 | AB72: SGH103YD0V | AC72: HLC | AD72: Floor 7.2 | AE72: T7.2-C08
A73: BCCS_CC2.0 | B73: 10.240.147.174 | C73: hoangnt14 | D73: CSKH | E73: TTCNTT | F73: 16 | G73: 64 | H73: 120 | R73: App-10.240.147.174 | S73: VM | T73: CentOS Stream 9 kernel 5.14.0-480.el9.x86_64 | U73: 0 | V73: chinhvc2 | W73: kietna | X73: VIETTEL | Y73: Server | Z73: HPE | AA73: ProLiant DL360 Gen10 | AB73: SGH103S2W9 | AC73: HLC | AD73: Floor 7.2 | AE73: T7.2-C10
A74: BCCS_CC2.0 | B74: 10.240.147.175 | C74: hoangnt14 | D74: CSKH | E74: TTCNTT | F74: 16 | G74: 64 | H74: 120 | R74: App-10.240.147.175 | S74: VM | T74: CentOS Stream 9 kernel 5.14.0-480.el9.x86_64 | U74: 0 | V74: chinhvc2 | W74: sonvt8 | X74: VIETTEL | Y74: Server | Z74: HPE | AA74: ProLiant DL360 Gen10 | AB74: SGH103YCGQ | AC74: HLC | AD74: Floor 7.2 | AE74: T7.2-C09
A75: BCCS_CC2.0 | B75: 10.240.147.176 | C75: hoangnt14 | D75: CSKH | E75: TTCNTT | F75: 16 | G75: 64 | H75: 120 | R75: App-10.240.147.176 | S75: VM | T75: CentOS Stream 9 kernel 5.14.0-480.el9.x86_64 | U75: 0 | V75: chinhvc2 | W75: kietna | X75: VIETTEL | Y75: Server | Z75: HPE | AA75: ProLiant DL360 Gen10 | AB75: SGH103S2WP | AC75: HLC | AD75: Floor 7.2 | AE75: T7.2-C13
A76: BCCS_CC2.0 | B76: 10.240.147.177 | C76: hoangnt14 | D76: CSKH | E76: TTCNTT | F76: 16 | G76: 64 | H76: 120 | R76: App-10.240.147.177 | S76: VM | T76: CentOS Stream 9 kernel 5.14.0-480.el9.x86_64 | U76: 0 | V76: chinhvc2 | W76: kietna | X76: VIETTEL | Y76: Server | Z76: HPE | AA76: ProLiant DL360 Gen10 | AB76: SGH103S2XV | AC76: HLC | AD76: Floor 7.2 | AE76: T7.2-C13
... A103: BCCS_CC2.0 | B103: 10.240.147.123 | C103: hoangnt14 | D103: CSKH | E103: TTCNTT | F103: 16 | G103: 64 | H103: 120 | R103: SV_10.240.147.123-app-10.240.147.123.novalocal-OS | S103: VM | T103: CentOS release 6.10 kernel 2.6.32-754.24.3.el6.x86_64 | U103: 0 | V103: huonglttt | W103: nguyentl | X103: VIETTEL | Y103: Server | Z103: Fujitsu | AA103: PRIMERGY CX2560 M5 | AB103: MAAG001409 | AC103: HLC | AD103: Floor 6.2 | AE103: T6.2-G13
A104: Viettel++ | B104: 10.205.32.49 | C104: hoangnt14 | D104: CSKH | E104: TTCNTT | F104: 24 | G104: 64 | H104: 500 | R104: App-10.205.32.49 | S104: VM | T104: CentOS Stream 9 kernel 5.14.0-480.el9.x86_64 | U104: 0 | V104: 0 | W104: 0 | X104: VTT | Y104: Server | Z104: Fujitsu | AA104: PRIMERGY CX2560 M5 | AB104: MAAG002372 | AC104: HLC | AD104: Floor 6.2 | AE104: T6.2-G03
A105: Viettel++ | B105: 10.205.32.50 | C105: hoangnt14 | D105: CSKH | E105: TTCNTT | F105: 24 | G105: 64 | H105: 500 | R105: App-10.205.32.50 | S105: VM | T105: CentOS Stream 9 kernel 5.14.0-480.el9.x86_64 | U105: 0 | V105: grominh | W105: kietna | X105: VTT | Y105: Server | Z105: Fujitsu | AA105: PRIMERGY CX2560 M5 | AB105: MAAG002372 | AC105: HLC | AD105: Floor 6.2 | AE105: T6.2-G03
A106: Viettel++ | B106: 10.205.32.51 | C106: hoangnt14 | D106: CSKH | E106: TTCNTT | F106: 24 | G106: 64 | H106: 500 | R106: App-10.205.32.51 | S106: VM | T106: CentOS Stream 9 kernel 5.14.0-480.el9.x86_64 | U106: 0 | V106: grominh | W106: sonvt8 | X106: VTT | Y106: Server | Z106: Fujitsu | AA106: PRIMERGY CX2560 M5 | AB106: MAAG002510 | AC106: HLC | AD106: Floor 6.2 | AE106: T6.2-G02
A107: Viettel++ | B107: 10.205.32.52 | C107: hoangnt14 | D107: CSKH | E107: TTCNTT | F107: 24 | G107: 64 | H107: 500 | R107: App-10.205.32.52 | S107: VM | T107: CentOS Stream 9 kernel 5.14.0-480.el9.x86_64 | U107: 0 | V107: grominh | W107: sonvt8 | X107: VTT | Y107: Server | Z107: Fujitsu | AA107: PRIMERGY CX2560 M5 | AB107: MAAG002444 | AC107: HLC | AD107: Floor 6.2 | AE107: T6.2-G02
A108: Viettel++ | B108: 10.205.32.53 | C108: hoangnt14 | D108: CSKH | E108: TTCNTT | F108: 24 | G108: 64 | H108: 500 | R108: App-10.205.32.53 | S108: VM | T108: CentOS Stream 9 kernel 5.14.0-480.el9.x86_64 | U108: 0 | V108: grominh | W108: kietna | X108: VTT | Y108: Server | Z108: Fujitsu | AA108: PRIMERGY CX2560 M5 | AB108: MAAG002372 | AC108: HLC | AD108: Floor 6.2 | AE108: T6.2-G03
A109: Viettel++ | B109: 10.205.32.54 | C109: hoangnt14 | D109: CSKH | E109: TTCNTT | F109: 24 | G109: 64 | H109: 500 | R109: App-10.205.32.54 | S109: VM | T109: CentOS Stream 9 kernel 5.14.0-480.el9.x86_64 | U109: 0 | V109: grominh | W109: kietna | X109: VTT | Y109: Server | Z109: Fujitsu | AA109: PRIMERGY CX2560 M5 | AB109: MAAG002371 | AC109: HLC | AD109: Floor 6.2 | AE109: T6.2-G03
A110: Viettel++ | B110: 10.205.32.55 | C110: hoangnt14 | D110: CSKH | E110: TTCNTT | F110: 24 | G110: 64 | H110: 500 | R110: App-10.205.32.55 | S110: VM | T110: CentOS Stream 9 kernel 5.14.0-480.el9.x86_64 | U110: 0 | V110: grominh | W110: sonvt8 | X110: VTT | Y110: Server | Z110: Fujitsu | AA110: PRIMERGY CX2560 M5 | AB110: MAAG002444 | AC110: HLC | AD110: Floor 6.2 | AE110: T6.2-G02
A111: Viettel++ | B111: 10.205.32.56 | C111: hoangnt14 | D111: CSKH | E111: TTCNTT | F111: 24 | G111: 64 | H111: 500 | R111: App-10.205.32.56 | S111: VM | T111: CentOS Stream 9 kernel 5.14.0-480.el9.x86_64 | U111: 0 | V111: grominh | W111: chinhvc2 | X111: VTT | Y111: Server | Z111: Fujitsu | AA111: PRIMERGY CX2560 M5 | AB111: MAAG002350 | AC111: HLC | AD111: Floor 6.2 | AE111: T6.2-G02
